Workbook
Name balanceSh_RG: '02. Nhap lieu tai chinh_RG'!$D$11:$H$57
Name CountBlankBCTC_RG: '03. Dulieutaichinhlamsach_RG'!$K$2
Name CountNegProvision_RG: '02. Nhap lieu tai chinh_RG'!$P$2
Name genInfo_RG: '02. Nhap lieu tai chinh_RG'!$D$7:$H$9
Name incomeStmt_RG: '02. Nhap lieu tai chinh_RG'!$D$59:$H$80
Name CountBlankTTC: '01. Thong tin chung'!$B$10
Name custInfo: '01. Thong tin chung'!$B$3:$B$9
Name balanceSh: '02. Nhap lieu tai chinh_DD'!$D$11:$H$128
Name CountNegProvision: '02. Nhap lieu tai chinh_DD'!$P$2
Name genInfo: '02. Nhap lieu tai chinh_DD'!$D$7:$H$9
Name incomeStmt: '02. Nhap lieu tai chinh_DD'!$D$130:$H$155
Name CountBlankBCTC: '03. Dulieutaichinhlamsach_DD'!$K$2

Sheet Financial_Report1
A1: code | B1: name | C1: =D1-1 | D1: =E1-1 | E1: ='01. Thong tin chung'!B7 | F1: ='01. Thong tin chung'!B8
A2: BS001 | B2: TỔNG TÀI SẢN | C2: =IF('01. Thong tin chung'!$B$9="Đầy đủ", IF(ISBLANK('06. Phan tich tai chinh_DD'!B9),0,'06. Phan tich tai chinh_DD'!B9),IF(ISBLANK('06. Phan tich tai chinh_RG'!B9),0,'06. Phan tich tai chinh_RG'!B9)) | D2: =IF('01. Thong tin chung'!$B$9="Đầy đủ", IF(ISBLANK('06. Phan tich tai chinh_DD'!C9),0,'06. Phan tich tai chinh_DD'!C9),IF(ISBLANK('06. Phan tich tai chinh_RG'!C9),0,'06. Phan tich tai chinh_RG'!C9)) | E2: =IF('01. Thong tin chung'!$B$9="Đầy đủ", IF(ISBLANK('06. Phan tich tai chinh_DD'!D9),0,'06. Phan tich tai chinh_DD'!D9),IF(ISBLANK('06. Phan tich tai chinh_RG'!D9),0,'06. Phan tich tai chinh_RG'!D9)) | F2: =IF('01. Thong tin chung'!$B$9="Đầy đủ", IF(ISBLANK('06. Phan tich tai chinh_DD'!G9),0,'06. Phan tich tai chinh_DD'!G9),IF(ISBLANK('06. Phan tich tai chinh_RG'!G9),0,'06. Phan tich tai chinh_RG'!G9))
A3: BS002 | B3: A. Tài sản ngắn hạn | C3: =IF('01. Thong tin chung'!$B$9="Đầy đủ",'06. Phan tich tai chinh_DD'!B10,-99999) | D3: =IF('01. Thong tin chung'!$B$9="Đầy đủ",'06. Phan tich tai chinh_DD'!C10,-99999) | E3: =IF('01. Thong tin chung'!$B$9="Đầy đủ",'06. Phan tich tai chinh_DD'!D10,-99999) | F3: =IF('01. Thong tin chung'!$B$9="Đầy đủ",'06. Phan tich tai chinh_DD'!G10,-99999)
A4: BS003 | B4: I. Tiền và các khoản tương đương tiền | C4: =IF('01. Thong tin chung'!$B$9="Đầy đủ", IF(ISBLANK('06. Phan tich tai chinh_DD'!B11),0,'06. Phan tich tai chinh_DD'!B11),IF(ISBLANK('06. Phan tich tai chinh_RG'!B10),0,'06. Phan tich tai chinh_RG'!B10)) | D4: =IF('01. Thong tin chung'!$B$9="Đầy đủ", IF(ISBLANK('06. Phan tich tai chinh_DD'!C11),0,'06. Phan tich tai chinh_DD'!C11),IF(ISBLANK('06. Phan tich tai chinh_RG'!C10),0,'06. Phan tich tai chinh_RG'!C10)) | E4: =IF('01. Thong tin chung'!$B$9="Đầy đủ", IF(ISBLANK('06. Phan tich tai chinh_DD'!D11),0,'06. Phan tich tai chinh_DD'!D11),IF(ISBLANK('06. Phan tich tai chinh_RG'!D10),0,'06. Phan tich tai chinh_RG'!D10)) | F4: =IF('01. Thong tin chung'!$B$9="Đầy đủ", IF(ISBLANK('06. Phan tich tai chinh_DD'!G11),0,'06. Phan tich tai chinh_DD'!G11),IF(ISBLANK('06. Phan tich tai chinh_RG'!G10),0,'06. Phan tich tai chinh_RG'!G10))
A5: BS022 | B5: 1. Tiền mặt | C5: =IF('01. Thong tin chung'!$B$9="Đầy đủ",'06. Phan tich tai chinh_DD'!B12,-99999) | D5: =IF('01. Thong tin chung'!$B$9="Đầy đủ",'06. Phan tich tai chinh_DD'!C12,-99999) | E5: =IF('01. Thong tin chung'!$B$9="Đầy đủ",'06. Phan tich tai chinh_DD'!D12,-99999) | F5: =IF('01. Thong tin chung'!$B$9="Đầy đủ",'06. Phan tich tai chinh_DD'!G12,-99999)
A6: BS023 | B6: 2. Tiền gửi ngân hàng | C6: =IF('01. Thong tin chung'!$B$9="Đầy đủ",'06. Phan tich tai chinh_DD'!B13,-99999) | D6: =IF('01. Thong tin chung'!$B$9="Đầy đủ",'06. Phan tich tai chinh_DD'!C13,-99999) | E6: =IF('01. Thong tin chung'!$B$9="Đầy đủ",'06. Phan tich tai chinh_DD'!D13,-99999) | F6: =IF('01. Thong tin chung'!$B$9="Đầy đủ",'06. Phan tich tai chinh_DD'!G13,-99999)
A7: BS024 | B7: 3. Tiền đang chuyển | C7: =IF('01. Thong tin chung'!$B$9="Đầy đủ",'06. Phan tich tai chinh_DD'!B14,-99999) | D7: =IF('01. Thong tin chung'!$B$9="Đầy đủ",'06. Phan tich tai chinh_DD'!C14,-99999) | E7: =IF('01. Thong tin chung'!$B$9="Đầy đủ",'06. Phan tich tai chinh_DD'!D14,-99999) | F7: =IF('01. Thong tin chung'!$B$9="Đầy đủ",'06. Phan tich tai chinh_DD'!G14,-99999)
A8: BS025 | B8: 4. Tiền (trong trường hợp Báo cáo không có 3 thông tin trên) | C8: =IF('01. Thong tin chung'!$B$9="Đầy đủ",'06. Phan tich tai chinh_DD'!B15,-99999) | D8: =IF('01. Thong tin chung'!$B$9="Đầy đủ",'06. Phan tich tai chinh_DD'!C15,-99999) | E8: =IF('01. Thong tin chung'!$B$9="Đầy đủ",'06. Phan tich tai chinh_DD'!D15,-99999) | F8: =IF('01. Thong tin chung'!$B$9="Đầy đủ",'06. Phan tich tai chinh_DD'!G15,-99999)
A9: BS026 | B9: 5. Các khoản tương đương tiền | C9: =IF('01. Thong tin chung'!$B$9="Đầy đủ",'06. Phan tich tai chinh_DD'!B16,-99999) | D9: =IF('01. Thong tin chung'!$B$9="Đầy đủ",'06. Phan tich tai chinh_DD'!C16,-99999) | E9: =IF('01. Thong tin chung'!$B$9="Đầy đủ",'06. Phan tich tai chinh_DD'!D16,-99999) | F9: =IF('01. Thong tin chung'!$B$9="Đầy đủ",'06. Phan tich tai chinh_DD'!G16,-99999)
A10: BS119 | B10: II. Đầu tư tài chính | C10: =IF('01. Thong tin chung'!$B$9="Rút gọn",'06. Phan tich tai chinh_RG'!B11,-99999) | D10: =IF('01. Thong tin chung'!$B$9="Rút gọn",'06. Phan tich tai chinh_RG'!C11,-99999) | E10: =IF('01. Thong tin chung'!$B$9="Rút gọn",'06. Phan tich tai chinh_RG'!D11,-99999) | F10: =IF('01. Thong tin chung'!$B$9="Rút gọn",'06. Phan tich tai chinh_RG'!G11,-99999)
A11: BS120 | B11: 1. Chứng khoán kinh doanh | C11: =IF('01. Thong tin chung'!$B$9="Rút gọn",'06. Phan tich tai chinh_RG'!B12,-99999) | D11: =IF('01. Thong tin chung'!$B$9="Rút gọn",'06. Phan tich tai chinh_RG'!C12,-99999) | E11: =IF('01. Thong tin chung'!$B$9="Rút gọn",'06. Phan tich tai chinh_RG'!D12,-99999) | F11: =IF('01. Thong tin chung'!$B$9="Rút gọn",'06. Phan tich tai chinh_RG'!G12,-99999)
A12: BS121 | B12: 2. Đầu tư nắm giữ đến ngày đáo hạn | C12: =IF('01. Thong tin chung'!$B$9="Rút gọn",'06. Phan tich tai chinh_RG'!B13,-99999) | D12: =IF('01. Thong tin chung'!$B$9="Rút gọn",'06. Phan tich tai chinh_RG'!C13,-99999) | E12: =IF('01. Thong tin chung'!$B$9="Rút gọn",'06. Phan tich tai chinh_RG'!D13,-99999) | F12: =IF('01. Thong tin chung'!$B$9="Rút gọn",'06. Phan tich tai chinh_RG'!G13,-99999)
A13: BS122 | B13: 3. Đầu tư góp vốn vào đơn vị khác | C13: =IF('01. Thong tin chung'!$B$9="Rút gọn",'06. Phan tich tai chinh_RG'!B14,-99999) | D13: =IF('01. Thong tin chung'!$B$9="Rút gọn",'06. Phan tich tai chinh_RG'!C14,-99999) | E13: =IF('01. Thong tin chung'!$B$9="Rút gọn",'06. Phan tich tai chinh_RG'!D14,-99999) | F13: =IF('01. Thong tin chung'!$B$9="Rút gọn",'06. Phan tich tai chinh_RG'!G14,-99999)
A14: BS123 | B14: 4. Dự phòng tổn thất đầu tư tài chính (*) | C14: =IF('01. Thong tin chung'!$B$9="Rút gọn",'06. Phan tich tai chinh_RG'!B15,-99999) | D14: =IF('01. Thong tin chung'!$B$9="Rút gọn",'06. Phan tich tai chinh_RG'!C15,-99999) | E14: =IF('01. Thong tin chung'!$B$9="Rút gọn",'06. Phan tich tai chinh_RG'!D15,-99999) | F14: =IF('01. Thong tin chung'!$B$9="Rút gọn",'06. Phan tich tai chinh_RG'!G15,-99999)
A15: BS004 | B15: II. Các khoản đầu tư tài chính ngắn hạn | C15: =IF('01. Thong tin chung'!$B$9="Đầy đủ",'06. Phan tich tai chinh_DD'!B17,-99999) | D15: =IF('01. Thong tin chung'!$B$9="Đầy đủ",'06. Phan tich tai chinh_DD'!C17,-99999) | E15: =IF('01. Thong tin chung'!$B$9="Đầy đủ",'06. Phan tich tai chinh_DD'!D17,-99999) | F15: =IF('01. Thong tin chung'!$B$9="Đầy đủ",'06. Phan tich tai chinh_DD'!G17,-99999)
A16: BS027 | B16: 1. Chứng khoán đầu tư ngắn hạn | C16: =IF('01. Thong tin chung'!$B$9="Đầy đủ",'06. Phan tich tai chinh_DD'!B18,-99999) | D16: =IF('01. Thong tin chung'!$B$9="Đầy đủ",'06. Phan tich tai chinh_DD'!C18,-99999) | E16: =IF('01. Thong tin chung'!$B$9="Đầy đủ",'06. Phan tich tai chinh_DD'!D18,-99999) | F16: =IF('01. Thong tin chung'!$B$9="Đầy đủ",'06. Phan tich tai chinh_DD'!G18,-99999)
A17: BS028 | B17: 2. Đầu tư ngắn hạn khác | C17: =IF('01. Thong tin chung'!$B$9="Đầy đủ",'06. Phan tich tai chinh_DD'!B19,-99999) | D17: =IF('01. Thong tin chung'!$B$9="Đầy đủ",'06. Phan tich tai chinh_DD'!C19,-99999) | E17: =IF('01. Thong tin chung'!$B$9="Đầy đủ",'06. Phan tich tai chinh_DD'!D19,-99999) | F17: =IF('01. Thong tin chung'!$B$9="Đầy đủ",'06. Phan tich tai chinh_DD'!G19,-99999)
A18: BS029 | B18: 3. Dự phòng giảm giá đầu tư ngắn hạn | C18: =IF('01. Thong tin chung'!$B$9="Đầy đủ",'06. Phan tich tai chinh_DD'!B20,-99999) | D18: =IF('01. Thong tin chung'!$B$9="Đầy đủ",'06. Phan tich tai chinh_DD'!C20,-99999) | E18: =IF('01. Thong tin chung'!$B$9="Đầy đủ",'06. Phan tich tai chinh_DD'!D20,-99999) | F18: =IF('01. Thong tin chung'!$B$9="Đầy đủ",'06. Phan tich tai chinh_DD'!G20,-99999)
A19: BS030 | B19: 4. Đầu tư tài chính ngắn hạn (trong trường hợp báo cáo không có thông tin) | C19: =IF('01. Thong tin chung'!$B$9="Đầy đủ",'06. Phan tich tai chinh_DD'!B21,-99999) | D19: =IF('01. Thong tin chung'!$B$9="Đầy đủ",'06. Phan tich tai chinh_DD'!C21,-99999) | E19: =IF('01. Thong tin chung'!$B$9="Đầy đủ",'06. Phan tich tai chinh_DD'!D21,-99999) | F19: =IF('01. Thong tin chung'!$B$9="Đầy đủ",'06. Phan tich tai chinh_DD'!G21,-99999)
A20: BS124 | B20: III. Các khoản phải thu | C20: =IF('01. Thong tin chung'!$B$9="Rút gọn",'06. Phan tich tai chinh_RG'!B16,-99999) | D20: =IF('01. Thong tin chung'!$B$9="Rút gọn",'06. Phan tich tai chinh_RG'!C16,-99999) | E20: =IF('01. Thong tin chung'!$B$9="Rút gọn",'06. Phan tich tai chinh_RG'!D16,-99999) | F20: =IF('01. Thong tin chung'!$B$9="Rút gọn",'06. Phan tich tai chinh_RG'!G16,-99999)
A21: BS125 | B21: 1. Phải thu của khách hàng | C21: =IF('01. Thong tin chung'!$B$9="Rút gọn",'06. Phan tich tai chinh_RG'!B17,-99999) | D21: =IF('01. Thong tin chung'!$B$9="Rút gọn",'06. Phan tich tai chinh_RG'!C17,-99999) | E21: =IF('01. Thong tin chung'!$B$9="Rút gọn",'06. Phan tich tai chinh_RG'!D17,-99999) | F21: =IF('01. Thong tin chung'!$B$9="Rút gọn",'06. Phan tich tai chinh_RG'!G17,-99999)
A22: BS126 | B22: 2. Trả trước cho người bán | C22: =IF('01. Thong tin chung'!$B$9="Rút gọn",'06. Phan tich tai chinh_RG'!B18,-99999) | D22: =IF('01. Thong tin chung'!$B$9="Rút gọn",'06. Phan tich tai chinh_RG'!C18,-99999) | E22: =IF('01. Thong tin chung'!$B$9="Rút gọn",'06. Phan tich tai chinh_RG'!D18,-99999) | F22: =IF('01. Thong tin chung'!$B$9="Rút gọn",'06. Phan tich tai chinh_RG'!G18,-99999)
A23: BS127 | B23: 3. Vốn kinh doanh ở đơn vị trực thuộc | C23: =IF('01. Thong tin chung'!$B$9="Rút gọn",'06. Phan tich tai chinh_RG'!B19,-99999) | D23: =IF('01. Thong tin chung'!$B$9="Rút gọn",'06. Phan tich tai chinh_RG'!C19,-99999) | E23: =IF('01. Thong tin chung'!$B$9="Rút gọn",'06. Phan tich tai chinh_RG'!D19,-99999) | F23: =IF('01. Thong tin chung'!$B$9="Rút gọn",'06. Phan tich tai chinh_RG'!G19,-99999)
A24: BS128 | B24: 4. Phải thu khác | C24: =IF('01. Thong tin chung'!$B$9="Rút gọn",'06. Phan tich tai chinh_RG'!B20,-99999) | D24: =IF('01. Thong tin chung'!$B$9="Rút gọn",'06. Phan tich tai chinh_RG'!C20,-99999) | E24: =IF('01. Thong tin chung'!$B$9="Rút gọn",'06. Phan tich tai chinh_RG'!D20,-99999) | F24: =IF('01. Thong tin chung'!$B$9="Rút gọn",'06. Phan tich tai chinh_RG'!G20,-99999)
A25: BS129 | B25: 5. Tài sản thiếu chờ xử lý | C25: =IF('01. Thong tin chung'!$B$9="Rút gọn",'06. Phan tich tai chinh_RG'!B21,-99999) | D25: =IF('01. Thong tin chung'!$B$9="Rút gọn",'06. Phan tich tai chinh_RG'!C21,-99999) | E25: =IF('01. Thong tin chung'!$B$9="Rút gọn",'06. Phan tich tai chinh_RG'!D21,-99999) | F25: =IF('01. Thong tin chung'!$B$9="Rút gọn",'06. Phan tich tai chinh_RG'!G21,-99999)
A26: BS130 | B26: 6. Dự phòng phải thu khó đòi (*) | C26: =IF('01. Thong tin chung'!$B$9="Rút gọn",'06. Phan tich tai chinh_RG'!B22,-99999) | D26: =IF('01. Thong tin chung'!$B$9="Rút gọn",'06. Phan tich tai chinh_RG'!C22,-99999) | E26: =IF('01. Thong tin chung'!$B$9="Rút gọn",'06. Phan tich tai chinh_RG'!D22,-99999) | F26: =IF('01. Thong tin chung'!$B$9="Rút gọn",'06. Phan tich tai chinh_RG'!G22,-99999)
A27: BS005 | B27: III. Các khoản phải thu ngắn hạn | C27: =IF('01. Thong tin chung'!$B$9="Đầy đủ",'06. Phan tich tai chinh_DD'!B22,-99999) | D27: =IF('01. Thong tin chung'!$B$9="Đầy đủ",'06. Phan tich tai chinh_DD'!C22,-99999) | E27: =IF('01. Thong tin chung'!$B$9="Đầy đủ",'06. Phan tich tai chinh_DD'!D22,-99999) | F27: =IF('01. Thong tin chung'!$B$9="Đầy đủ",'06. Phan tich tai chinh_DD'!G22,-99999)
A28: BS031 | B28: 1. Phải thu khách hàng | C28: =IF('01. Thong tin chung'!$B$9="Đầy đủ",'06. Phan tich tai chinh_DD'!B23,-99999) | D28: =IF('01. Thong tin chung'!$B$9="Đầy đủ",'06. Phan tich tai chinh_DD'!C23,-99999) | E28: =IF('01. Thong tin chung'!$B$9="Đầy đủ",'06. Phan tich tai chinh_DD'!D23,-99999) | F28: =IF('01. Thong tin chung'!$B$9="Đầy đủ",'06. Phan tich tai chinh_DD'!G23,-99999)
A29: BS032 | B29: 2. Trả trước cho người bán | C29: =IF('01. Thong tin chung'!$B$9="Đầy đủ",'06. Phan tich tai chinh_DD'!B24,-99999) | D29: =IF('01. Thong tin chung'!$B$9="Đầy đủ",'06. Phan tich tai chinh_DD'!C24,-99999) | E29: =IF('01. Thong tin chung'!$B$9="Đầy đủ",'06. Phan tich tai chinh_DD'!D24,-99999) | F29: =IF('01. Thong tin chung'!$B$9="Đầy đủ",'06. Phan tich tai chinh_DD'!G24,-99999)
A30: BS033 | B30: 3. Phải thu nội bộ ngắn hạn | C30: =IF('01. Thong tin chung'!$B$9="Đầy đủ",'06. Phan tich tai chinh_DD'!B25,-99999) | D30: =IF('01. Thong tin chung'!$B$9="Đầy đủ",'06. Phan tich tai chinh_DD'!C25,-99999) | E30: =IF('01. Thong tin chung'!$B$9="Đầy đủ",'06. Phan tich tai chinh_DD'!D25,-99999) | F30: =IF('01. Thong tin chung'!$B$9="Đầy đủ",'06. Phan tich tai chinh_DD'!G25,-99999)
A31: BS034 | B31: 4. Phải thu theo tiến độ kế hoạch hợp đồng xây dựng | C31: =IF('01. Thong tin chung'!$B$9="Đầy đủ",'06. Phan tich tai chinh_DD'!B26,-99999) | D31: =IF('01. Thong tin chung'!$B$9="Đầy đủ",'06. Phan tich tai chinh_DD'!C26,-99999) | E31: =IF('01. Thong tin chung'!$B$9="Đầy đủ",'06. Phan tich tai chinh_DD'!D26,-99999) | F31: =IF('01. Thong tin chung'!$B$9="Đầy đủ",'06. Phan tich tai chinh_DD'!G26,-99999)
A32: BS035 | B32: 5. Các khoản phải thu khác | C32: =IF('01. Thong tin chung'!$B$9="Đầy đủ",'06. Phan tich tai chinh_DD'!B27,-99999) | D32: =IF('01. Thong tin chung'!$B$9="Đầy đủ",'06. Phan tich tai chinh_DD'!C27,-99999) | E32: =IF('01. Thong tin chung'!$B$9="Đầy đủ",'06. Phan tich tai chinh_DD'!D27,-99999) | F32: =IF('01. Thong tin chung'!$B$9="Đầy đủ",'06. Phan tich tai chinh_DD'!G27,-99999)
A33: BS036 | B33: 6. Dự phòng phải thu ngắn hạn khó đòi | C33: =IF('01. Thong tin chung'!$B$9="Đầy đủ",'06. Phan tich tai chinh_DD'!B28,-99999) | D33: =IF('01. Thong tin chung'!$B$9="Đầy đủ",'06. Phan tich tai chinh_DD'!C28,-99999) | E33: =IF('01. Thong tin chung'!$B$9="Đầy đủ",'06. Phan tich tai chinh_DD'!D28,-99999) | F33: =IF('01. Thong tin chung'!$B$9="Đầy đủ",'06. Phan tich tai chinh_DD'!G28,-99999)
A34: BS006 | B34: IV. Hàng tồn kho | C34: =IF('01. Thong tin chung'!$B$9="Đầy đủ", IF(ISBLANK('06. Phan tich tai chinh_DD'!B29),0,'06. Phan tich tai chinh_DD'!B29),IF(ISBLANK('06. Phan tich tai chinh_RG'!B23),0,'06. Phan tich tai chinh_RG'!B23)) | D34: =IF('01. Thong tin chung'!$B$9="Đầy đủ", IF(ISBLANK('06. Phan tich tai chinh_DD'!C29),0,'06. Phan tich tai chinh_DD'!C29),IF(ISBLANK('06. Phan tich tai chinh_RG'!C23),0,'06. Phan tich tai chinh_RG'!C23)) | E34: =IF('01. Thong tin chung'!$B$9="Đầy đủ", IF(ISBLANK('06. Phan tich tai chinh_DD'!D29),0,'06. Phan tich tai chinh_DD'!D29),IF(ISBLANK('06. Phan tich tai chinh_RG'!D23),0,'06. Phan tich tai chinh_RG'!D23)) | F34: =IF('01. Thong tin chung'!$B$9="Đầy đủ", IF(ISBLANK('06. Phan tich tai chinh_DD'!G29),0,'06. Phan tich tai chinh_DD'!G29),IF(ISBLANK('06. Phan tich tai chinh_RG'!G23),0,'06. Phan tich tai chinh_RG'!G23))
A35: BS037 | B35: 1. Hàng mua đang đi đường | C35: =IF('01. Thong tin chung'!$B$9="Đầy đủ",'06. Phan tich tai chinh_DD'!B30,-99999) | D35: =IF('01. Thong tin chung'!$B$9="Đầy đủ",'06. Phan tich tai chinh_DD'!C30,-99999) | E35: =IF('01. Thong tin chung'!$B$9="Đầy đủ",'06. Phan tich tai chinh_DD'!D30,-99999) | F35: =IF('01. Thong tin chung'!$B$9="Đầy đủ",'06. Phan tich tai chinh_DD'!G30,-99999)
A36: BS038 | B36: 2. Nguyên liệu, vật liệu | C36: =IF('01. Thong tin chung'!$B$9="Đầy đủ",'06. Phan tich tai chinh_DD'!B31,-99999) | D36: =IF('01. Thong tin chung'!$B$9="Đầy đủ",'06. Phan tich tai chinh_DD'!C31,-99999) | E36: =IF('01. Thong tin chung'!$B$9="Đầy đủ",'06. Phan tich tai chinh_DD'!D31,-99999) | F36: =IF('01. Thong tin chung'!$B$9="Đầy đủ",'06. Phan tich tai chinh_DD'!G31,-99999)
A37: BS039 | B37: 3. Công cụ, dụng cụ | C37: =IF('01. Thong tin chung'!$B$9="Đầy đủ",'06. Phan tich tai chinh_DD'!B32,-99999) | D37: =IF('01. Thong tin chung'!$B$9="Đầy đủ",'06. Phan tich tai chinh_DD'!C32,-99999) | E37: =IF('01. Thong tin chung'!$B$9="Đầy đủ",'06. Phan tich tai chinh_DD'!D32,-99999) | F37: =IF('01. Thong tin chung'!$B$9="Đầy đủ",'06. Phan tich tai chinh_DD'!G32,-99999)
A38: BS040 | B38: 4. Chi phí SX, KD dở dang | C38: =IF('01. Thong tin chung'!$B$9="Đầy đủ",'06. Phan tich tai chinh_DD'!B33,-99999) | D38: =IF('01. Thong tin chung'!$B$9="Đầy đủ",'06. Phan tich tai chinh_DD'!C33,-99999) | E38: =IF('01. Thong tin chung'!$B$9="Đầy đủ",'06. Phan tich tai chinh_DD'!D33,-99999) | F38: =IF('01. Thong tin chung'!$B$9="Đầy đủ",'06. Phan tich tai chinh_DD'!G33,-99999)
A39: BS041 | B39: 5. Thành phẩm | C39: =IF('01. Thong tin chung'!$B$9="Đầy đủ",'06. Phan tich tai chinh_DD'!B34,-99999) | D39: =IF('01. Thong tin chung'!$B$9="Đầy đủ",'06. Phan tich tai chinh_DD'!C34,-99999) | E39: =IF('01. Thong tin chung'!$B$9="Đầy đủ",'06. Phan tich tai chinh_DD'!D34,-99999) | F39: =IF('01. Thong tin chung'!$B$9="Đầy đủ",'06. Phan tich tai chinh_DD'!G34,-99999)
A40: BS042 | B40: 6. Hàng hóa | C40: =IF('01. Thong tin chung'!$B$9="Đầy đủ",'06. Phan tich tai chinh_DD'!B35,-99999) | D40: =IF('01. Thong tin chung'!$B$9="Đầy đủ",'06. Phan tich tai chinh_DD'!C35,-99999) | E40: =IF('01. Thong tin chung'!$B$9="Đầy đủ",'06. Phan tich tai chinh_DD'!D35,-99999) | F40: =IF('01. Thong tin chung'!$B$9="Đầy đủ",'06. Phan tich tai chinh_DD'!G35,-99999)
A41: BS043 | B41: 7. Hàng gửi đi bán | C41: =IF('01. Thong tin chung'!$B$9="Đầy đủ",'06. Phan tich tai chinh_DD'!B36,-99999) | D41: =IF('01. Thong tin chung'!$B$9="Đầy đủ",'06. Phan tich tai chinh_DD'!C36,-99999) | E41: =IF('01. Thong tin chung'!$B$9="Đầy đủ",'06. Phan tich tai chinh_DD'!D36,-99999) | F41: =IF('01. Thong tin chung'!$B$9="Đầy đủ",'06. Phan tich tai chinh_DD'!G36,-99999)
A42: BS044 | B42: 8. Hàng hóa kho bảo thuế | C42: =IF('01. Thong tin chung'!$B$9="Đầy đủ",'06. Phan tich tai chinh_DD'!B37,-99999) | D42: =IF('01. Thong tin chung'!$B$9="Đầy đủ",'06. Phan tich tai chinh_DD'!C37,-99999) | E42: =IF('01. Thong tin chung'!$B$9="Đầy đủ",'06. Phan tich tai chinh_DD'!D37,-99999) | F42: =IF('01. Thong tin chung'!$B$9="Đầy đủ",'06. Phan tich tai chinh_DD'!G37,-99999)
A43: BS045 | B43: 9. Hàng hóa bất động sản | C43: =IF('01. Thong tin chung'!$B$9="Đầy đủ",'06. Phan tich tai chinh_DD'!B38,-99999) | D43: =IF('01. Thong tin chung'!$B$9="Đầy đủ",'06. Phan tich tai chinh_DD'!C38,-99999) | E43: =IF('01. Thong tin chung'!$B$9="Đầy đủ",'06. Phan tich tai chinh_DD'!D38,-99999) | F43: =IF('01. Thong tin chung'!$B$9="Đầy đủ",'06. Phan tich tai chinh_DD'!G38,-99999)
A44: BS046 | B44: 10. Dự phòng giảm giá hàng tồn kho | C44: =IF('01. Thong tin chung'!$B$9="Đầy đủ", IF(ISBLANK('06. Phan tich tai chinh_DD'!B39),0,'06. Phan tich tai chinh_DD'!B39),IF(ISBLANK('06. Phan tich tai chinh_RG'!B25),0,'06. Phan tich tai chinh_RG'!B25)) | D44: =IF('01. Thong tin chung'!$B$9="Đầy đủ", IF(ISBLANK('06. Phan tich tai chinh_DD'!C39),0,'06. Phan tich tai chinh_DD'!C39),IF(ISBLANK('06. Phan tich tai chinh_RG'!C25),0,'06. Phan tich tai chinh_RG'!C25)) | E44: =IF('01. Thong tin chung'!$B$9="Đầy đủ", IF(ISBLANK('06. Phan tich tai chinh_DD'!D39),0,'06. Phan tich tai chinh_DD'!D39),IF(ISBLANK('06. Phan tich tai chinh_RG'!D25),0,'06. Phan tich tai chinh_RG'!D25)) | F44: =IF('01. Thong tin chung'!$B$9="Đầy đủ", IF(ISBLANK('06. Phan tich tai chinh_DD'!G39),0,'06. Phan tich tai chinh_DD'!G39),IF(ISBLANK('06. Phan tich tai chinh_RG'!G25),0,'06. Phan tich tai chinh_RG'!G25))
A45: BS047 | B45: 11. Hàng tồn kho (trong trường hợp báo cáo không có thông tin chi tiết) | C45: =IF('01. Thong tin chung'!$B$9="Đầy đủ", IF(ISBLANK('06. Phan tich tai chinh_DD'!B40),0,'06. Phan tich tai chinh_DD'!B40),IF(ISBLANK('06. Phan tich tai chinh_RG'!B24),0,'06. Phan tich tai chinh_RG'!B24)) | D45: =IF('01. Thong tin chung'!$B$9="Đầy đủ", IF(ISBLANK('06. Phan tich tai chinh_DD'!C40),0,'06. Phan tich tai chinh_DD'!C40),IF(ISBLANK('06. Phan tich tai chinh_RG'!C24),0,'06. Phan tich tai chinh_RG'!C24)) | E45: =IF('01. Thong tin chung'!$B$9="Đầy đủ", IF(ISBLANK('06. Phan tich tai chinh_DD'!D40),0,'06. Phan tich tai chinh_DD'!D40),IF(ISBLANK('06. Phan tich tai chinh_RG'!D24),0,'06. Phan tich tai chinh_RG'!D24)) | F45: =IF('01. Thong tin chung'!$B$9="Đầy đủ", IF(ISBLANK('06. Phan tich tai chinh_DD'!G40),0,'06. Phan tich tai chinh_DD'!G40),IF(ISBLANK('06. Phan tich tai chinh_RG'!G24),0,'06. Phan tich tai chinh_RG'!G24))
A46: BS007 | B46: V. Tài sản ngắn hạn khác | C46: =IF('01. Thong tin chung'!$B$9="Đầy đủ",'06. Phan tich tai chinh_DD'!B41,-99999) | D46: =IF('01. Thong tin chung'!$B$9="Đầy đủ",'06. Phan tich tai chinh_DD'!C41,-99999) | E46: =IF('01. Thong tin chung'!$B$9="Đầy đủ",'06. Phan tich tai chinh_DD'!D41,-99999) | F46: =IF('01. Thong tin chung'!$B$9="Đầy đủ",'06. Phan tich tai chinh_DD'!G41,-99999)
A47: BS048 | B47: 1. Chi phí trả trước ngắn hạn | C47: =IF('01. Thong tin chung'!$B$9="Đầy đủ",'06. Phan tich tai chinh_DD'!B42,-99999) | D47: =IF('01. Thong tin chung'!$B$9="Đầy đủ",'06. Phan tich tai chinh_DD'!C42,-99999) | E47: =IF('01. Thong tin chung'!$B$9="Đầy đủ",'06. Phan tich tai chinh_DD'!D42,-99999) | F47: =IF('01. Thong tin chung'!$B$9="Đầy đủ",'06. Phan tich tai chinh_DD'!G42,-99999)
A48: BS049 | B48: 2. Thuế GTGT được khấu trừ | C48: =IF('01. Thong tin chung'!$B$9="Đầy đủ",'06. Phan tich tai chinh_DD'!B43,-99999) | D48: =IF('01. Thong tin chung'!$B$9="Đầy đủ",'06. Phan tich tai chinh_DD'!C43,-99999) | E48: =IF('01. Thong tin chung'!$B$9="Đầy đủ",'06. Phan tich tai chinh_DD'!D43,-99999) | F48: =IF('01. Thong tin chung'!$B$9="Đầy đủ",'06. Phan tich tai chinh_DD'!G43,-99999)
A49: BS050 | B49: 3. Thuế và các khoản khác phải thu Nhà nước | C49: =IF('01. Thong tin chung'!$B$9="Đầy đủ",'06. Phan tich tai chinh_DD'!B44,-99999) | D49: =IF('01. Thong tin chung'!$B$9="Đầy đủ",'06. Phan tich tai chinh_DD'!C44,-99999) | E49: =IF('01. Thong tin chung'!$B$9="Đầy đủ",'06. Phan tich tai chinh_DD'!D44,-99999) | F49: =IF('01. Thong tin chung'!$B$9="Đầy đủ",'06. Phan tich tai chinh_DD'!G44,-99999)
A50: BS051 | B50: 4. Giao dịch mua bán lại trái phiếu chính phủ | C50: =IF('01. Thong tin chung'!$B$9="Đầy đủ",'06. Phan tich tai chinh_DD'!B45,-99999) | D50: =IF('01. Thong tin chung'!$B$9="Đầy đủ",'06. Phan tich tai chinh_DD'!C45,-99999) | E50: =IF('01. Thong tin chung'!$B$9="Đầy đủ",'06. Phan tich tai chinh_DD'!D45,-99999) | F50: =IF('01. Thong tin chung'!$B$9="Đầy đủ",'06. Phan tich tai chinh_DD'!G45,-99999)
A51: BS052 | B51: 5. Tài sản ngắn hạn khác | C51: =IF('01. Thong tin chung'!$B$9="Đầy đủ",'06. Phan tich tai chinh_DD'!B46,-99999) | D51: =IF('01. Thong tin chung'!$B$9="Đầy đủ",'06. Phan tich tai chinh_DD'!C46,-99999) | E51: =IF('01. Thong tin chung'!$B$9="Đầy đủ",'06. Phan tich tai chinh_DD'!D46,-99999) | F51: =IF('01. Thong tin chung'!$B$9="Đầy đủ",'06. Phan tich tai chinh_DD'!G46,-99999)
A52: BS008 | B52: B. TÀI SẢN DÀI HẠN | C52: =IF('01. Thong tin chung'!$B$9="Đầy đủ",'06. Phan tich tai chinh_DD'!B47,-99999) | D52: =IF('01. Thong tin chung'!$B$9="Đầy đủ",'06. Phan tich tai chinh_DD'!C47,-99999) | E52: =IF('01. Thong tin chung'!$B$9="Đầy đủ",'06. Phan tich tai chinh_DD'!D47,-99999) | F52: =IF('01. Thong tin chung'!$B$9="Đầy đủ",'06. Phan tich tai chinh_DD'!G47,-99999)
A53: BS009 | B53: I. Các khoản phải thu dài hạn | C53: =IF('01. Thong tin chung'!$B$9="Đầy đủ",'06. Phan tich tai chinh_DD'!B48,-99999) | D53: =IF('01. Thong tin chung'!$B$9="Đầy đủ",'06. Phan tich tai chinh_DD'!C48,-99999) | E53: =IF('01. Thong tin chung'!$B$9="Đầy đủ",'06. Phan tich tai chinh_DD'!D48,-99999) | F53: =IF('01. Thong tin chung'!$B$9="Đầy đủ",'06. Phan tich tai chinh_DD'!G48,-99999)
A54: BS053 | B54: 1. Phải thu dài hạn của khách hàng | C54: =IF('01. Thong tin chung'!$B$9="Đầy đủ",'06. Phan tich tai chinh_DD'!B49,-99999) | D54: =IF('01. Thong tin chung'!$B$9="Đầy đủ",'06. Phan tich tai chinh_DD'!C49,-99999) | E54: =IF('01. Thong tin chung'!$B$9="Đầy đủ",'06. Phan tich tai chinh_DD'!D49,-99999) | F54: =IF('01. Thong tin chung'!$B$9="Đầy đủ",'06. Phan tich tai chinh_DD'!G49,-99999)
A55: BS054 | B55: 2. Vốn kinh doanh ở đơn vị trực thuộc | C55: =IF('01. Thong tin chung'!$B$9="Đầy đủ",'06. Phan tich tai chinh_DD'!B50,-99999) | D55: =IF('01. Thong tin chung'!$B$9="Đầy đủ",'06. Phan tich tai chinh_DD'!C50,-99999) | E55: =IF('01. Thong tin chung'!$B$9="Đầy đủ",'06. Phan tich tai chinh_DD'!D50,-99999) | F55: =IF('01. Thong tin chung'!$B$9="Đầy đủ",'06. Phan tich tai chinh_DD'!G50,-99999)
A56: BS055 | B56: 3. Phải thu dài hạn nội bộ | C56: =IF('01. Thong tin chung'!$B$9="Đầy đủ",'06. Phan tich tai chinh_DD'!B51,-99999) | D56: =IF('01. Thong tin chung'!$B$9="Đầy đủ",'06. Phan tich tai chinh_DD'!C51,-99999) | E56: =IF('01. Thong tin chung'!$B$9="Đầy đủ",'06. Phan tich tai chinh_DD'!D51,-99999) | F56: =IF('01. Thong tin chung'!$B$9="Đầy đủ",'06. Phan tich tai chinh_DD'!G51,-99999)
A57: BS056 | B57: 4. Phải thu dài hạn khác | C57: =IF('01. Thong tin chung'!$B$9="Đầy đủ",'06. Phan tich tai chinh_DD'!B52,-99999) | D57: =IF('01. Thong tin chung'!$B$9="Đầy đủ",'06. Phan tich tai chinh_DD'!C52,-99999) | E57: =IF('01. Thong tin chung'!$B$9="Đầy đủ",'06. Phan tich tai chinh_DD'!D52,-99999) | F57: =IF('01. Thong tin chung'!$B$9="Đầy đủ",'06. Phan tich tai chinh_DD'!G52,-99999)
A58: BS057 | B58: 5. Dự phòng phải thu dài hạn khó đòi | C58: =IF('01. Thong tin chung'!$B$9="Đầy đủ",'06. Phan tich tai chinh_DD'!B53,-99999) | D58: =IF('01. Thong tin chung'!$B$9="Đầy đủ",'06. Phan tich tai chinh_DD'!C53,-99999) | E58: =IF('01. Thong tin chung'!$B$9="Đầy đủ",'06. Phan tich tai chinh_DD'!D53,-99999) | F58: =IF('01. Thong tin chung'!$B$9="Đầy đủ",'06. Phan tich tai chinh_DD'!G53,-99999)
A59: BS010 | B59: II. Tài sản cố định | C59: =IF('01. Thong tin chung'!$B$9="Đầy đủ", IF(ISBLANK('06. Phan tich tai chinh_DD'!B54),0,'06. Phan tich tai chinh_DD'!B54),IF(ISBLANK('06. Phan tich tai chinh_RG'!B26),0,'06. Phan tich tai chinh_RG'!B26)) | D59: =IF('01. Thong tin chung'!$B$9="Đầy đủ", IF(ISBLANK('06. Phan tich tai chinh_DD'!C54),0,'06. Phan tich tai chinh_DD'!C54),IF(ISBLANK('06. Phan tich tai chinh_RG'!C26),0,'06. Phan tich tai chinh_RG'!C26)) | E59: =IF('01. Thong tin chung'!$B$9="Đầy đủ", IF(ISBLANK('06. Phan tich tai chinh_DD'!D54),0,'06. Phan tich tai chinh_DD'!D54),IF(ISBLANK('06. Phan tich tai chinh_RG'!D26),0,'06. Phan tich tai chinh_RG'!D26)) | F59: =IF('01. Thong tin chung'!$B$9="Đầy đủ", IF(ISBLANK('06. Phan tich tai chinh_DD'!G54),0,'06. Phan tich tai chinh_DD'!G54),IF(ISBLANK('06. Phan tich tai chinh_RG'!G26),0,'06. Phan tich tai chinh_RG'!G26))
A60: BS058 | B60: 1. Tài sản cố định hữu hình | C60: =IF('01. Thong tin chung'!$B$9="Đầy đủ",'06. Phan tich tai chinh_DD'!B55,-99999) | D60: =IF('01. Thong tin chung'!$B$9="Đầy đủ",'06. Phan tich tai chinh_DD'!C55,-99999) | E60: =IF('01. Thong tin chung'!$B$9="Đầy đủ",'06. Phan tich tai chinh_DD'!D55,-99999) | F60: =IF('01. Thong tin chung'!$B$9="Đầy đủ",'06. Phan tich tai chinh_DD'!G55,-99999)
A61: BS059 | B61: - Nguyên giá | C61: =IF('01. Thong tin chung'!$B$9="Đầy đủ", IF(ISBLANK('06. Phan tich tai chinh_DD'!B56),0,'06. Phan tich tai chinh_DD'!B56),IF(ISBLANK('06. Phan tich tai chinh_RG'!B27),0,'06. Phan tich tai chinh_RG'!B27)) | D61: =IF('01. Thong tin chung'!$B$9="Đầy đủ", IF(ISBLANK('06. Phan tich tai chinh_DD'!C56),0,'06. Phan tich tai chinh_DD'!C56),IF(ISBLANK('06. Phan tich tai chinh_RG'!C27),0,'06. Phan tich tai chinh_RG'!C27)) | E61: =IF('01. Thong tin chung'!$B$9="Đầy đủ", IF(ISBLANK('06. Phan tich tai chinh_DD'!D56),0,'06. Phan tich tai chinh_DD'!D56),IF(ISBLANK('06. Phan tich tai chinh_RG'!D27),0,'06. Phan tich tai chinh_RG'!D27)) | F61: =IF('01. Thong tin chung'!$B$9="Đầy đủ", IF(ISBLANK('06. Phan tich tai chinh_DD'!G56),0,'06. Phan tich tai chinh_DD'!G56),IF(ISBLANK('06. Phan tich tai chinh_RG'!G27),0,'06. Phan tich tai chinh_RG'!G27))
A62: BS060 | B62: - Giá trị hao mòn lũy kế | C62: =IF('01. Thong tin chung'!$B$9="Đầy đủ", IF(ISBLANK('06. Phan tich tai chinh_DD'!B57),0,'06. Phan tich tai chinh_DD'!B57),IF(ISBLANK('06. Phan tich tai chinh_RG'!B28),0,'06. Phan tich tai chinh_RG'!B28)) | D62: =IF('01. Thong tin chung'!$B$9="Đầy đủ", IF(ISBLANK('06. Phan tich tai chinh_DD'!C57),0,'06. Phan tich tai chinh_DD'!C57),IF(ISBLANK('06. Phan tich tai chinh_RG'!C28),0,'06. Phan tich tai chinh_RG'!C28)) | E62: =IF('01. Thong tin chung'!$B$9="Đầy đủ", IF(ISBLANK('06. Phan tich tai chinh_DD'!D57),0,'06. Phan tich tai chinh_DD'!D57),IF(ISBLANK('06. Phan tich tai chinh_RG'!D28),0,'06. Phan tich tai chinh_RG'!D28)) | F62: =IF('01. Thong tin chung'!$B$9="Đầy đủ", IF(ISBLANK('06. Phan tich tai chinh_DD'!G57),0,'06. Phan tich tai chinh_DD'!G57),IF(ISBLANK('06. Phan tich tai chinh_RG'!G28),0,'06. Phan tich tai chinh_RG'!G28))
A63: BS061 | B63: 2. Tài sản cố định thuê tài chính | C63: =IF('01. Thong tin chung'!$B$9="Đầy đủ",'06. Phan tich tai chinh_DD'!B58,-99999) | D63: =IF('01. Thong tin chung'!$B$9="Đầy đủ",'06. Phan tich tai chinh_DD'!C58,-99999) | E63: =IF('01. Thong tin chung'!$B$9="Đầy đủ",'06. Phan tich tai chinh_DD'!D58,-99999) | F63: =IF('01. Thong tin chung'!$B$9="Đầy đủ",'06. Phan tich tai chinh_DD'!G58,-99999)
A64: BS062 | B64: - Nguyên giá | C64: =IF('01. Thong tin chung'!$B$9="Đầy đủ",'06. Phan tich tai chinh_DD'!B59,-99999) | D64: =IF('01. Thong tin chung'!$B$9="Đầy đủ",'06. Phan tich tai chinh_DD'!C59,-99999) | E64: =IF('01. Thong tin chung'!$B$9="Đầy đủ",'06. Phan tich tai chinh_DD'!D59,-99999) | F64: =IF('01. Thong tin chung'!$B$9="Đầy đủ",'06. Phan tich tai chinh_DD'!G59,-99999)
A65: BS063 | B65: - Giá trị hao mòn lũy kế | C65: =IF('01. Thong tin chung'!$B$9="Đầy đủ",'06. Phan tich tai chinh_DD'!B60,-99999) | D65: =IF('01. Thong tin chung'!$B$9="Đầy đủ",'06. Phan tich tai chinh_DD'!C60,-99999) | E65: =IF('01. Thong tin chung'!$B$9="Đầy đủ",'06. Phan tich tai chinh_DD'!D60,-99999) | F65: =IF('01. Thong tin chung'!$B$9="Đầy đủ",'06. Phan tich tai chinh_DD'!G60,-99999)
A66: BS064 | B66: 3. Tài sản cố định vô hình | C66: =IF('01. Thong tin chung'!$B$9="Đầy đủ",'06. Phan tich tai chinh_DD'!B61,-99999) | D66: =IF('01. Thong tin chung'!$B$9="Đầy đủ",'06. Phan tich tai chinh_DD'!C61,-99999) | E66: =IF('01. Thong tin chung'!$B$9="Đầy đủ",'06. Phan tich tai chinh_DD'!D61,-99999) | F66: =IF('01. Thong tin chung'!$B$9="Đầy đủ",'06. Phan tich tai chinh_DD'!G61,-99999)
A67: BS065 | B67: - Nguyên giá | C67: =IF('01. Thong tin chung'!$B$9="Đầy đủ",'06. Phan tich tai chinh_DD'!B62,-99999) | D67: =IF('01. Thong tin chung'!$B$9="Đầy đủ",'06. Phan tich tai chinh_DD'!C62,-99999) | E67: =IF('01. Thong tin chung'!$B$9="Đầy đủ",'06. Phan tich tai chinh_DD'!D62,-99999) | F67: =IF('01. Thong tin chung'!$B$9="Đầy đủ",'06. Phan tich tai chinh_DD'!G62,-99999)
A68: BS066 | B68: - Giá trị hao mòn lũy kế | C68: =IF('01. Thong tin chung'!$B$9="Đầy đủ",'06. Phan tich tai chinh_DD'!B63,-99999) | D68: =IF('01. Thong tin chung'!$B$9="Đầy đủ",'06. Phan tich tai chinh_DD'!C63,-99999) | E68: =IF('01. Thong tin chung'!$B$9="Đầy đủ",'06. Phan tich tai chinh_DD'!D63,-99999) | F68: =IF('01. Thong tin chung'!$B$9="Đầy đủ",'06. Phan tich tai chinh_DD'!G63,-99999)
A69: BS067 | B69: 4. Chi phí xây dựng cơ bản dở dang | C69: =IF('01. Thong tin chung'!$B$9="Đầy đủ", IF(ISBLANK('06. Phan tich tai chinh_DD'!B64),0,'06. Phan tich tai chinh_DD'!B64),IF(ISBLANK('06. Phan tich tai chinh_RG'!B32),0,'06. Phan tich tai chinh_RG'!B32)) | D69: =IF('01. Thong tin chung'!$B$9="Đầy đủ", IF(ISBLANK('06. Phan tich tai chinh_DD'!C64),0,'06. Phan tich tai chinh_DD'!C64),IF(ISBLANK('06. Phan tich tai chinh_RG'!C32),0,'06. Phan tich tai chinh_RG'!C32)) | E69: =IF('01. Thong tin chung'!$B$9="Đầy đủ", IF(ISBLANK('06. Phan tich tai chinh_DD'!D64),0,'06. Phan tich tai chinh_DD'!D64),IF(ISBLANK('06. Phan tich tai chinh_RG'!D32),0,'06. Phan tich tai chinh_RG'!D32)) | F69: =IF('01. Thong tin chung'!$B$9="Đầy đủ", IF(ISBLANK('06. Phan tich tai chinh_DD'!G64),0,'06. Phan tich tai chinh_DD'!G64),IF(ISBLANK('06. Phan tich tai chinh_RG'!G32),0,'06. Phan tich tai chinh_RG'!G32))
A70: BS011 | B70: III. Bất động sản đầu tư | C70: =IF('01. Thong tin chung'!$B$9="Đầy đủ", IF(ISBLANK('06. Phan tich tai chinh_DD'!B65),0,'06. Phan tich tai chinh_DD'!B65),IF(ISBLANK('06. Phan tich tai chinh_RG'!B29),0,'06. Phan tich tai chinh_RG'!B29)) | D70: =IF('01. Thong tin chung'!$B$9="Đầy đủ", IF(ISBLANK('06. Phan tich tai chinh_DD'!C65),0,'06. Phan tich tai chinh_DD'!C65),IF(ISBLANK('06. Phan tich tai chinh_RG'!C29),0,'06. Phan tich tai chinh_RG'!C29)) | E70: =IF('01. Thong tin chung'!$B$9="Đầy đủ", IF(ISBLANK('06. Phan tich tai chinh_DD'!D65),0,'06. Phan tich tai chinh_DD'!D65),IF(ISBLANK('06. Phan tich tai chinh_RG'!D29),0,'06. Phan tich tai chinh_RG'!D29)) | F70: =IF('01. Thong tin chung'!$B$9="Đầy đủ", IF(ISBLANK('06. Phan tich tai chinh_DD'!G65),0,'06. Phan tich tai chinh_DD'!G65),IF(ISBLANK('06. Phan tich tai chinh_RG'!G29),0,'06. Phan tich tai chinh_RG'!G29))
A71: BS068 | B71: - Nguyên giá | C71: =IF('01. Thong tin chung'!$B$9="Đầy đủ", IF(ISBLANK('06. Phan tich tai chinh_DD'!B66),0,'06. Phan tich tai chinh_DD'!B66),IF(ISBLANK('06. Phan tich tai chinh_RG'!B30),0,'06. Phan tich tai chinh_RG'!B30)) | D71: =IF('01. Thong tin chung'!$B$9="Đầy đủ", IF(ISBLANK('06. Phan tich tai chinh_DD'!C66),0,'06. Phan tich tai chinh_DD'!C66),IF(ISBLANK('06. Phan tich tai chinh_RG'!C30),0,'06. Phan tich tai chinh_RG'!C30)) | E71: =IF('01. Thong tin chung'!$B$9="Đầy đủ", IF(ISBLANK('06. Phan tich tai chinh_DD'!D66),0,'06. Phan tich tai chinh_DD'!D66),IF(ISBLANK('06. Phan tich tai chinh_RG'!D30),0,'06. Phan tich tai chinh_RG'!D30)) | F71: =IF('01. Thong tin chung'!$B$9="Đầy đủ", IF(ISBLANK('06. Phan tich tai chinh_DD'!G66),0,'06. Phan tich tai chinh_DD'!G66),IF(ISBLANK('06. Phan tich tai chinh_RG'!G30),0,'06. Phan tich tai chinh_RG'!G30))
A72: BS069 | B72: - Giá trị hao mòn lũy kế | C72: =IF('01. Thong tin chung'!$B$9="Đầy đủ", IF(ISBLANK('06. Phan tich tai chinh_DD'!B67),0,'06. Phan tich tai chinh_DD'!B67),IF(ISBLANK('06. Phan tich tai chinh_RG'!B31),0,'06. Phan tich tai chinh_RG'!B31)) | D72: =IF('01. Thong tin chung'!$B$9="Đầy đủ", IF(ISBLANK('06. Phan tich tai chinh_DD'!C67),0,'06. Phan tich tai chinh_DD'!C67),IF(ISBLANK('06. Phan tich tai chinh_RG'!C31),0,'06. Phan tich tai chinh_RG'!C31)) | E72: =IF('01. Thong tin chung'!$B$9="Đầy đủ", IF(ISBLANK('06. Phan tich tai chinh_DD'!D67),0,'06. Phan tich tai chinh_DD'!D67),IF(ISBLANK('06. Phan tich tai chinh_RG'!D31),0,'06. Phan tich tai chinh_RG'!D31)) | F72: =IF('01. Thong tin chung'!$B$9="Đầy đủ", IF(ISBLANK('06. Phan tich tai chinh_DD'!G67),0,'06. Phan tich tai chinh_DD'!G67),IF(ISBLANK('06. Phan tich tai chinh_RG'!G31),0,'06. Phan tich tai chinh_RG'!G31))
A73: BS012 | B73: IV. Các khoản đầu tư tài chính dài hạn | C73: =IF('01. Thong tin chung'!$B$9="Đầy đủ",'06. Phan tich tai chinh_DD'!B68,-99999) | D73: =IF('01. Thong tin chung'!$B$9="Đầy đủ",'06. Phan tich tai chinh_DD'!C68,-99999) | E73: =IF('01. Thong tin chung'!$B$9="Đầy đủ",'06. Phan tich tai chinh_DD'!D68,-99999) | F73: =IF('01. Thong tin chung'!$B$9="Đầy đủ",'06. Phan tich tai chinh_DD'!G68,-99999)
A74: BS070 | B74: 1. Đầu tư vào công ty con | C74: =IF('01. Thong tin chung'!$B$9="Đầy đủ",'06. Phan tich tai chinh_DD'!B69,-99999) | D74: =IF('01. Thong tin chung'!$B$9="Đầy đủ",'06. Phan tich tai chinh_DD'!C69,-99999) | E74: =IF('01. Thong tin chung'!$B$9="Đầy đủ",'06. Phan tich tai chinh_DD'!D69,-99999) | F74: =IF('01. Thong tin chung'!$B$9="Đầy đủ",'06. Phan tich tai chinh_DD'!G69,-99999)
A75: BS071 | B75: 2. Đầu tư vào công ty liên kết, liên doanh | C75: =IF('01. Thong tin chung'!$B$9="Đầy đủ",'06. Phan tich tai chinh_DD'!B70,-99999) | D75: =IF('01. Thong tin chung'!$B$9="Đầy đủ",'06. Phan tich tai chinh_DD'!C70,-99999) | E75: =IF('01. Thong tin chung'!$B$9="Đầy đủ",'06. Phan tich tai chinh_DD'!D70,-99999) | F75: =IF('01. Thong tin chung'!$B$9="Đầy đủ",'06. Phan tich tai chinh_DD'!G70,-99999)
A76: BS072 | B76: 3. Đầu tư dài hạn khác | C76: =IF('01. Thong tin chung'!$B$9="Đầy đủ",'06. Phan tich tai chinh_DD'!B71,-99999) | D76: =IF('01. Thong tin chung'!$B$9="Đầy đủ",'06. Phan tich tai chinh_DD'!C71,-99999) | E76: =IF('01. Thong tin chung'!$B$9="Đầy đủ",'06. Phan tich tai chinh_DD'!D71,-99999) | F76: =IF('01. Thong tin chung'!$B$9="Đầy đủ",'06. Phan tich tai chinh_DD'!G71,-99999)
A77: BS073 | B77: 4. Dự phòng giảm giá đầu tư tài chính dài hạn | C77: =IF('01. Thong tin chung'!$B$9="Đầy đủ",'06. Phan tich tai chinh_DD'!B72,-99999) | D77: =IF('01. Thong tin chung'!$B$9="Đầy đủ",'06. Phan tich tai chinh_DD'!C72,-99999) | E77: =IF('01. Thong tin chung'!$B$9="Đầy đủ",'06. Phan tich tai chinh_DD'!D72,-99999) | F77: =IF('01. Thong tin chung'!$B$9="Đầy đủ",'06. Phan tich tai chinh_DD'!G72,-99999)
A78: BS074 | B78: 5. Đầu tư tài chính dài hạn (trong trường hợp báo cáo không có thông tin) | C78: =IF('01. Thong tin chung'!$B$9="Đầy đủ",'06. Phan tich tai chinh_DD'!B73,-99999) | D78: =IF('01. Thong tin chung'!$B$9="Đầy đủ",'06. Phan tich tai chinh_DD'!C73,-99999) | E78: =IF('01. Thong tin chung'!$B$9="Đầy đủ",'06. Phan tich tai chinh_DD'!D73,-99999) | F78: =IF('01. Thong tin chung'!$B$9="Đầy đủ",'06. Phan tich tai chinh_DD'!G73,-99999)
A79: BS131 | B79: VIII. Tài sản khác | C79: =IF('01. Thong tin chung'!$B$9="Rút gọn",'06. Phan tich tai chinh_RG'!B33,-99999) | D79: =IF('01. Thong tin chung'!$B$9="Rút gọn",'06. Phan tich tai chinh_RG'!C33,-99999) | E79: =IF('01. Thong tin chung'!$B$9="Rút gọn",'06. Phan tich tai chinh_RG'!D33,-99999) | F79: =IF('01. Thong tin chung'!$B$9="Rút gọn",'06. Phan tich tai chinh_RG'!G33,-99999)
A80: BS132 | B80: 1. Thuế GTGT được khấu trừ | C80: =IF('01. Thong tin chung'!$B$9="Rút gọn",'06. Phan tich tai chinh_RG'!B34,-99999) | D80: =IF('01. Thong tin chung'!$B$9="Rút gọn",'06. Phan tich tai chinh_RG'!C34,-99999) | E80: =IF('01. Thong tin chung'!$B$9="Rút gọn",'06. Phan tich tai chinh_RG'!D34,-99999) | F80: =IF('01. Thong tin chung'!$B$9="Rút gọn",'06. Phan tich tai chinh_RG'!G34,-99999)
A81: BS133 | B81: 2. Tài sản khác | C81: =IF('01. Thong tin chung'!$B$9="Rút gọn",'06. Phan tich tai chinh_RG'!B35,-99999) | D81: =IF('01. Thong tin chung'!$B$9="Rút gọn",'06. Phan tich tai chinh_RG'!C35,-99999) | E81: =IF('01. Thong tin chung'!$B$9="Rút gọn",'06. Phan tich tai chinh_RG'!D35,-99999) | F81: =IF('01. Thong tin chung'!$B$9="Rút gọn",'06. Phan tich tai chinh_RG'!G35,-99999)
A82: BS013 | B82: V. Tài sản dài hạn khác | C82: =IF('01. Thong tin chung'!$B$9="Đầy đủ",'06. Phan tich tai chinh_DD'!B74,-99999) | D82: =IF('01. Thong tin chung'!$B$9="Đầy đủ",'06. Phan tich tai chinh_DD'!C74,-99999) | E82: =IF('01. Thong tin chung'!$B$9="Đầy đủ",'06. Phan tich tai chinh_DD'!D74,-99999) | F82: =IF('01. Thong tin chung'!$B$9="Đầy đủ",'06. Phan tich tai chinh_DD'!G74,-99999)
A83: BS075 | B83: 1. Chi phí trả trước dài hạn | C83: =IF('01. Thong tin chung'!$B$9="Đầy đủ",'06. Phan tich tai chinh_DD'!B75,-99999) | D83: =IF('01. Thong tin chung'!$B$9="Đầy đủ",'06. Phan tich tai chinh_DD'!C75,-99999) | E83: =IF('01. Thong tin chung'!$B$9="Đầy đủ",'06. Phan tich tai chinh_DD'!D75,-99999) | F83: =IF('01. Thong tin chung'!$B$9="Đầy đủ",'06. Phan tich tai chinh_DD'!G75,-99999)
A84: BS076 | B84: 2. Tài sản thuế thu nhập hoãn lại | C84: =IF('01. Thong tin chung'!$B$9="Đầy đủ",'06. Phan tich tai chinh_DD'!B76,-99999) | D84: =IF('01. Thong tin chung'!$B$9="Đầy đủ",'06. Phan tich tai chinh_DD'!C76,-99999) | E84: =IF('01. Thong tin chung'!$B$9="Đầy đủ",'06. Phan tich tai chinh_DD'!D76,-99999) | F84: =IF('01. Thong tin chung'!$B$9="Đầy đủ",'06. Phan tich tai chinh_DD'!G76,-99999)
A85: BS077 | B85: 3. Phải thu dài hạn | C85: =IF('01. Thong tin chung'!$B$9="Đầy đủ",'06. Phan tich tai chinh_DD'!B77,-99999) | D85: =IF('01. Thong tin chung'!$B$9="Đầy đủ",'06. Phan tich tai chinh_DD'!C77,-99999) | E85: =IF('01. Thong tin chung'!$B$9="Đầy đủ",'06. Phan tich tai chinh_DD'!D77,-99999) | F85: =IF('01. Thong tin chung'!$B$9="Đầy đủ",'06. Phan tich tai chinh_DD'!G77,-99999)
A86: BS078 | B86: 4. Tài sản dài hạn khác | C86: =IF('01. Thong tin chung'!$B$9="Đầy đủ",'06. Phan tich tai chinh_DD'!B78,-99999) | D86: =IF('01. Thong tin chung'!$B$9="Đầy đủ",'06. Phan tich tai chinh_DD'!C78,-99999) | E86: =IF('01. Thong tin chung'!$B$9="Đầy đủ",'06. Phan tich tai chinh_DD'!D78,-99999) | F86: =IF('01. Thong tin chung'!$B$9="Đầy đủ",'06. Phan tich tai chinh_DD'!G78,-99999)
A87: BS079 | B87: 5. Dự phòng phải thu dài hạn khó đòi | C87: =IF('01. Thong tin chung'!$B$9="Đầy đủ",'06. Phan tich tai chinh_DD'!B79,-99999) | D87: =IF('01. Thong tin chung'!$B$9="Đầy đủ",'06. Phan tich tai chinh_DD'!C79,-99999) | E87: =IF('01. Thong tin chung'!$B$9="Đầy đủ",'06. Phan tich tai chinh_DD'!D79,-99999) | F87: =IF('01. Thong tin chung'!$B$9="Đầy đủ",'06. Phan tich tai chinh_DD'!G79,-99999)
A88: BS014 | B88: VI. Lợi thế thương mại | C88: =IF('01. Thong tin chung'!$B$9="Đầy đủ",'06. Phan tich tai chinh_DD'!B80,-99999) | D88: =IF('01. Thong tin chung'!$B$9="Đầy đủ",'06. Phan tich tai chinh_DD'!C80,-99999) | E88: =IF('01. Thong tin chung'!$B$9="Đầy đủ",'06. Phan tich tai chinh_DD'!D80,-99999) | F88: =IF('01. Thong tin chung'!$B$9="Đầy đủ",'06. Phan tich tai chinh_DD'!G80,-99999)
A89: BS015 | B89: TỔNG NGUỒN VỐN | C89: =IF('01. Thong tin chung'!$B$9="Đầy đủ", IF(ISBLANK('06. Phan tich tai chinh_DD'!B81),0,'06. Phan tich tai chinh_DD'!B81),IF(ISBLANK('06. Phan tich tai chinh_RG'!B36),0,'06. Phan tich tai chinh_RG'!B36)) | D89: =IF('01. Thong tin chung'!$B$9="Đầy đủ", IF(ISBLANK('06. Phan tich tai chinh_DD'!C81),0,'06. Phan tich tai chinh_DD'!C81),IF(ISBLANK('06. Phan tich tai chinh_RG'!C36),0,'06. Phan tich tai chinh_RG'!C36)) | E89: =IF('01. Thong tin chung'!$B$9="Đầy đủ", IF(ISBLANK('06. Phan tich tai chinh_DD'!D81),0,'06. Phan tich tai chinh_DD'!D81),IF(ISBLANK('06. Phan tich tai chinh_RG'!D36),0,'06. Phan tich tai chinh_RG'!D36)) | F89: =IF('01. Thong tin chung'!$B$9="Đầy đủ", IF(ISBLANK('06. Phan tich tai chinh_DD'!G81),0,'06. Phan tich tai chinh_DD'!G81),IF(ISBLANK('06. Phan tich tai chinh_RG'!G36),0,'06. Phan tich tai chinh_RG'!G36))
A90: BS016 | B90: A. NỢ PHẢI TRẢ | C90: =IF('01. Thong tin chung'!$B$9="Đầy đủ", IF(ISBLANK('06. Phan tich tai chinh_DD'!B82),0,'06. Phan tich tai chinh_DD'!B82),IF(ISBLANK('06. Phan tich tai chinh_RG'!B37),0,'06. Phan tich tai chinh_RG'!B37)) | D90: =IF('01. Thong tin chung'!$B$9="Đầy đủ", IF(ISBLANK('06. Phan tich tai chinh_DD'!C82),0,'06. Phan tich tai chinh_DD'!C82),IF(ISBLANK('06. Phan tich tai chinh_RG'!C37),0,'06. Phan tich tai chinh_RG'!C37)) | E90: =IF('01. Thong tin chung'!$B$9="Đầy đủ", IF(ISBLANK('06. Phan tich tai chinh_DD'!D82),0,'06. Phan tich tai chinh_DD'!D82),IF(ISBLANK('06. Phan tich tai chinh_RG'!D37),0,'06. Phan tich tai chinh_RG'!D37)) | F90: =IF('01. Thong tin chung'!$B$9="Đầy đủ", IF(ISBLANK('06. Phan tich tai chinh_DD'!G82),0,'06. Phan tich tai chinh_DD'!G82),IF(ISBLANK('06. Phan tich tai chinh_RG'!G37),0,'06. Phan tich tai chinh_RG'!G37))
A91: BS134 | B91: 1. Phải trả người bán | C91: =IF('01. Thong tin chung'!$B$9="Rút gọn",'06. Phan tich tai chinh_RG'!B38,-99999) | D91: =IF('01. Thong tin chung'!$B$9="Rút gọn",'06. Phan tich tai chinh_RG'!C38,-99999) | E91: =IF('01. Thong tin chung'!$B$9="Rút gọn",'06. Phan tich tai chinh_RG'!D38,-99999) | F91: =IF('01. Thong tin chung'!$B$9="Rút gọn",'06. Phan tich tai chinh_RG'!G38,-99999)
A92: BS135 | B92: 2. Người mua trả tiền trước | C92: =IF('01. Thong tin chung'!$B$9="Rút gọn",'06. Phan tich tai chinh_RG'!B39,-99999) | D92: =IF('01. Thong tin chung'!$B$9="Rút gọn",'06. Phan tich tai chinh_RG'!C39,-99999) | E92: =IF('01. Thong tin chung'!$B$9="Rút gọn",'06. Phan tich tai chinh_RG'!D39,-99999) | F92: =IF('01. Thong tin chung'!$B$9="Rút gọn",'06. Phan tich tai chinh_RG'!G39,-99999)
A93: BS136 | B93: 3. Thuế và các khoản phải nộp Nhà nước | C93: =IF('01. Thong tin chung'!$B$9="Rút gọn",'06. Phan tich tai chinh_RG'!B40,-99999) | D93: =IF('01. Thong tin chung'!$B$9="Rút gọn",'06. Phan tich tai chinh_RG'!C40,-99999) | E93: =IF('01. Thong tin chung'!$B$9="Rút gọn",'06. Phan tich tai chinh_RG'!D40,-99999) | F93: =IF('01. Thong tin chung'!$B$9="Rút gọn",'06. Phan tich tai chinh_RG'!G40,-99999)
A94: BS137 | B94: 4. Phải trả người lao động | C94: =IF('01. Thong tin chung'!$B$9="Rút gọn",'06. Phan tich tai chinh_RG'!B41,-99999) | D94: =IF('01. Thong tin chung'!$B$9="Rút gọn",'06. Phan tich tai chinh_RG'!C41,-99999) | E94: =IF('01. Thong tin chung'!$B$9="Rút gọn",'06. Phan tich tai chinh_RG'!D41,-99999) | F94: =IF('01. Thong tin chung'!$B$9="Rút gọn",'06. Phan tich tai chinh_RG'!G41,-99999)
A95: BS138 | B95: 5. Phải trả khác | C95: =IF('01. Thong tin chung'!$B$9="Rút gọn",'06. Phan tich tai chinh_RG'!B42,-99999) | D95: =IF('01. Thong tin chung'!$B$9="Rút gọn",'06. Phan tich tai chinh_RG'!C42,-99999) | E95: =IF('01. Thong tin chung'!$B$9="Rút gọn",'06. Phan tich tai chinh_RG'!D42,-99999) | F95: =IF('01. Thong tin chung'!$B$9="Rút gọn",'06. Phan tich tai chinh_RG'!G42,-99999)
A96: BS139 | B96: 6. Vay và nợ thuê tài chính | C96: =IF('01. Thong tin chung'!$B$9="Rút gọn",'06. Phan tich tai chinh_RG'!B43,-99999) | D96: =IF('01. Thong tin chung'!$B$9="Rút gọn",'06. Phan tich tai chinh_RG'!C43,-99999) | E96: =IF('01. Thong tin chung'!$B$9="Rút gọn",'06. Phan tich tai chinh_RG'!D43,-99999) | F96: =IF('01. Thong tin chung'!$B$9="Rút gọn",'06. Phan tich tai chinh_RG'!G43,-99999)
A97: BS140 | B97: 7. Phải trả nội bộ về vốn kinh doanh | C97: =IF('01. Thong tin chung'!$B$9="Rút gọn",'06. Phan tich tai chinh_RG'!B44,-99999) | D97: =IF('01. Thong tin chung'!$B$9="Rút gọn",'06. Phan tich tai chinh_RG'!C44,-99999) | E97: =IF('01. Thong tin chung'!$B$9="Rút gọn",'06. Phan tich tai chinh_RG'!D44,-99999) | F97: =IF('01. Thong tin chung'!$B$9="Rút gọn",'06. Phan tich tai chinh_RG'!G44,-99999)
A98: BS141 | B98: 8. Dự phòng phải trả | C98: =IF('01. Thong tin chung'!$B$9="Rút gọn",'06. Phan tich tai chinh_RG'!B45,-99999) | D98: =IF('01. Thong tin chung'!$B$9="Rút gọn",'06. Phan tich tai chinh_RG'!C45,-99999) | E98: =IF('01. Thong tin chung'!$B$9="Rút gọn",'06. Phan tich tai chinh_RG'!D45,-99999) | F98: =IF('01. Thong tin chung'!$B$9="Rút gọn",'06. Phan tich tai chinh_RG'!G45,-99999)
A99: BS142 | B99: 9. Quỹ khen thưởng, phúc lợi | C99: =IF('01. Thong tin chung'!$B$9="Rút gọn",'06. Phan tich tai chinh_RG'!B46,-99999) | D99: =IF('01. Thong tin chung'!$B$9="Rút gọn",'06. Phan tich tai chinh_RG'!C46,-99999) | E99: =IF('01. Thong tin chung'!$B$9="Rút gọn",'06. Phan tich tai chinh_RG'!D46,-99999) | F99: =IF('01. Thong tin chung'!$B$9="Rút gọn",'06. Phan tich tai chinh_RG'!G46,-99999)
A100: BS143 | B100: 10. Quỹ phát triển khoa học và công nghệ | C100: =IF('01. Thong tin chung'!$B$9="Rút gọn",'06. Phan tich tai chinh_RG'!B47,-99999) | D100: =IF('01. Thong tin chung'!$B$9="Rút gọn",'06. Phan tich tai chinh_RG'!C47,-99999) | E100: =IF('01. Thong tin chung'!$B$9="Rút gọn",'06. Phan tich tai chinh_RG'!D47,-99999) | F100: =IF('01. Thong tin chung'!$B$9="Rút gọn",'06. Phan tich tai chinh_RG'!G47,-99999)
...

Sheet Droplist
A1: VND | C1: Loại BCTC | D1: =IF('01. Thong tin chung'!B9="Đầy đủ",1, IF('01. Thong tin chung'!B9="Rút gọn",2,0))
A2: Triệu VND

Sheet 0. Huong dan

Sheet 01. Thong tin chung
A1: Template BCTC - Hiệu lực từ 05/11/2023
A2: Thông tin chung về khách hàng
A3: Tên Công ty: | B3: CÔNG TY CỔ PHẦN KẾT CẤU THÉP STEELTECH
A4: Mã số thuế (Tax code) | B4: 0319777888
A5: Mã khách hàng (số CIF) | B5: 5162308
A6: Đơn vị tiền tệ sử dụng trong Báo cáo Tài chính: | B6: VND
A7: Năm Tài chính gần nhất: | B7: 2025
A8: Thời điểm tài chính gần nhất | B8: 46022
A9: Loại BCTC | B9: Đầy đủ
A10: CountBlank | B10: =COUNTIF(B3:B9,"")

Sheet 02. Nhap lieu tai chinh_RG
B1: NHẬP SỐ LIỆU VỀ TÀI CHÍNH CỦA KHÁCH HÀNG | I1: Check thông tin báo cáo tài chính
D2: Lưu ý: bắt buộc điền sheet 01. Thông tin chung | F2: Đơn vị: | G2: =IF('01. Thong tin chung'!B6="","",'01. Thong tin chung'!B6) | O2: CountNegProvision | P2: =COUNTIF(D17:H17,">0")+COUNTIF(D24:H24,">0")+COUNTIF(D27:H27,">0")+COUNTIF(D30:H30,">0")+COUNTIF(D33:H33,">0")
B3: I. Bảng cân đối kế toán
D4: =IF(D11<>D38,"Chưa cân số","") | E4: =IF(E11<>E38,"Chưa cân số","") | F4: =IF(F11<>F38,"Chưa cân số","") | G4: =IF(G11<>G38,"Chưa cân số","") | H4: =IF(H11<>H38,"Chưa cân số","")
B5: Chỉ tiêu | C5: Mã số | D5: N-3 | E5: N-2 | F5: N-1 | G5: Thời điểm hiện tại | H5: Dự tính N
B6: Mã số thuế | D6: ='01. Thong tin chung'!$B$4 | E6: ='01. Thong tin chung'!$B$4 | F6: ='01. Thong tin chung'!$B$4 | G6: ='01. Thong tin chung'!$B$4 | H6: ='01. Thong tin chung'!$B$4 | I6: =D6='03. Dulieutaichinhlamsach_RG'!D6 | J6: =E6='03. Dulieutaichinhlamsach_RG'!E6 | K6: =F6='03. Dulieutaichinhlamsach_RG'!F6 | L6: =G6='03. Dulieutaichinhlamsach_RG'!G6 | M6: =H6='03. Dulieutaichinhlamsach_RG'!H6
B7: Năm | I7: =D7='03. Dulieutaichinhlamsach_RG'!D7 | J7: =E7='03. Dulieutaichinhlamsach_RG'!E7 | K7: =F7='03. Dulieutaichinhlamsach_RG'!F7 | L7: =G7='03. Dulieutaichinhlamsach_RG'!G7 | M7: =H7='03. Dulieutaichinhlamsach_RG'!H7
B8: Quý | I8: =D8='03. Dulieutaichinhlamsach_RG'!D8 | J8: =E8='03. Dulieutaichinhlamsach_RG'!E8 | K8: =F8='03. Dulieutaichinhlamsach_RG'!F8 | L8: =G8='03. Dulieutaichinhlamsach_RG'!G8 | M8: =H8='03. Dulieutaichinhlamsach_RG'!H8
B9: Tháng | I9: =D9='03. Dulieutaichinhlamsach_RG'!D9 | J9: =E9='03. Dulieutaichinhlamsach_RG'!E9 | K9: =F9='03. Dulieutaichinhlamsach_RG'!F9 | L9: =G9='03. Dulieutaichinhlamsach_RG'!G9 | M9: =H9='03. Dulieutaichinhlamsach_RG'!H9
B10: Đơn vị tính | D10: =$G$2 | E10: =$G$2 | F10: =$G$2 | G10: =$G$2 | H10: =$G$2 | I10: =D10='03. Dulieutaichinhlamsach_RG'!D10 | J10: =E10='03. Dulieutaichinhlamsach_RG'!E10 | K10: =F10='03. Dulieutaichinhlamsach_RG'!F10 | L10: =G10='03. Dulieutaichinhlamsach_RG'!G10 | M10: =H10='03. Dulieutaichinhlamsach_RG'!H10
B11: TỔNG CỘNG TÀI SẢN | I11: =D11='03. Dulieutaichinhlamsach_RG'!D11 | J11: =E11='03. Dulieutaichinhlamsach_RG'!E11 | K11: =F11='03. Dulieutaichinhlamsach_RG'!F11 | L11: =G11='03. Dulieutaichinhlamsach_RG'!G11 | M11: =H11='03. Dulieutaichinhlamsach_RG'!H11
B12: I. Tiền và các khoản tương đương tiền | I12: =D12='03. Dulieutaichinhlamsach_RG'!D12 | J12: =E12='03. Dulieutaichinhlamsach_RG'!E12 | K12: =F12='03. Dulieutaichinhlamsach_RG'!F12 | L12: =G12='03. Dulieutaichinhlamsach_RG'!G12 | M12: =H12='03. Dulieutaichinhlamsach_RG'!H12
B13: II. Đầu tư tài chính | I13: =D13='03. Dulieutaichinhlamsach_RG'!D13 | J13: =E13='03. Dulieutaichinhlamsach_RG'!E13 | K13: =F13='03. Dulieutaichinhlamsach_RG'!F13 | L13: =G13='03. Dulieutaichinhlamsach_RG'!G13 | M13: =H13='03. Dulieutaichinhlamsach_RG'!H13
B14: 1. Chứng khoán kinh doanh | I14: =D14='03. Dulieutaichinhlamsach_RG'!D14 | J14: =E14='03. Dulieutaichinhlamsach_RG'!E14 | K14: =F14='03. Dulieutaichinhlamsach_RG'!F14 | L14: =G14='03. Dulieutaichinhlamsach_RG'!G14 | M14: =H14='03. Dulieutaichinhlamsach_RG'!H14
B15: 2. Đầu tư nắm giữ đến ngày đáo hạn | I15: =D15='03. Dulieutaichinhlamsach_RG'!D15 | J15: =E15='03. Dulieutaichinhlamsach_RG'!E15 | K15: =F15='03. Dulieutaichinhlamsach_RG'!F15 | L15: =G15='03. Dulieutaichinhlamsach_RG'!G15 | M15: =H15='03. Dulieutaichinhlamsach_RG'!H15
B16: 3. Đầu tư góp vốn vào đơn vị khác | I16: =D16='03. Dulieutaichinhlamsach_RG'!D16 | J16: =E16='03. Dulieutaichinhlamsach_RG'!E16 | K16: =F16='03. Dulieutaichinhlamsach_RG'!F16 | L16: =G16='03. Dulieutaichinhlamsach_RG'!G16 | M16: =H16='03. Dulieutaichinhlamsach_RG'!H16
B17: 4. Dự phòng tổn thất đầu tư tài chính (*) | I17: =D17='03. Dulieutaichinhlamsach_RG'!D17 | J17: =E17='03. Dulieutaichinhlamsach_RG'!E17 | K17: =F17='03. Dulieutaichinhlamsach_RG'!F17 | L17: =G17='03. Dulieutaichinhlamsach_RG'!G17 | M17: =H17='03. Dulieutaichinhlamsach_RG'!H17
B18: III. Các khoản phải thu | I18: =D18='03. Dulieutaichinhlamsach_RG'!D18 | J18: =E18='03. Dulieutaichinhlamsach_RG'!E18 | K18: =F18='03. Dulieutaichinhlamsach_RG'!F18 | L18: =G18='03. Dulieutaichinhlamsach_RG'!G18 | M18: =H18='03. Dulieutaichinhlamsach_RG'!H18
B19: 1. Phải thu của khách hàng | I19: =D19='03. Dulieutaichinhlamsach_RG'!D19 | J19: =E19='03. Dulieutaichinhlamsach_RG'!E19 | K19: =F19='03. Dulieutaichinhlamsach_RG'!F19 | L19: =G19='03. Dulieutaichinhlamsach_RG'!G19 | M19: =H19='03. Dulieutaichinhlamsach_RG'!H19
B20: 2. Trả trước cho người bán | I20: =D20='03. Dulieutaichinhlamsach_RG'!D20 | J20: =E20='03. Dulieutaichinhlamsach_RG'!E20 | K20: =F20='03. Dulieutaichinhlamsach_RG'!F20 | L20: =G20='03. Dulieutaichinhlamsach_RG'!G20 | M20: =H20='03. Dulieutaichinhlamsach_RG'!H20
B21: 3. Vốn kinh doanh ở đơn vị trực thuộc | I21: =D21='03. Dulieutaichinhlamsach_RG'!D21 | J21: =E21='03. Dulieutaichinhlamsach_RG'!E21 | K21: =F21='03. Dulieutaichinhlamsach_RG'!F21 | L21: =G21='03. Dulieutaichinhlamsach_RG'!G21 | M21: =H21='03. Dulieutaichinhlamsach_RG'!H21
B22: 4. Phải thu khác | I22: =D22='03. Dulieutaichinhlamsach_RG'!D22 | J22: =E22='03. Dulieutaichinhlamsach_RG'!E22 | K22: =F22='03. Dulieutaichinhlamsach_RG'!F22 | L22: =G22='03. Dulieutaichinhlamsach_RG'!G22 | M22: =H22='03. Dulieutaichinhlamsach_RG'!H22
... B58: II. Báo cáo kết quả hoạt động SXKD | I58: =D58='03. Dulieutaichinhlamsach_RG'!D58 | J58: =E58='03. Dulieutaichinhlamsach_RG'!E58 | K58: =F58='03. Dulieutaichinhlamsach_RG'!F58 | L58: =G58='03. Dulieutaichinhlamsach_RG'!G58 | M58: =H58='03. Dulieutaichinhlamsach_RG'!H58
B59: Doanh thu bán hàng và cung cấp dịch vụ | I59: =D59='03. Dulieutaichinhlamsach_RG'!D72 | J59: =E59='03. Dulieutaichinhlamsach_RG'!E72 | K59: =F59='03. Dulieutaichinhlamsach_RG'!F72 | L59: =G59='03. Dulieutaichinhlamsach_RG'!G72 | M59: =H59='03. Dulieutaichinhlamsach_RG'!H72
B60: Các khoản giảm trừ doanh thu | I60: =D60='03. Dulieutaichinhlamsach_RG'!D73 | J60: =E60='03. Dulieutaichinhlamsach_RG'!E73 | K60: =F60='03. Dulieutaichinhlamsach_RG'!F73 | L60: =G60='03. Dulieutaichinhlamsach_RG'!G73 | M60: =H60='03. Dulieutaichinhlamsach_RG'!H73
B61: - Chiết khấu | I61: =D61='03. Dulieutaichinhlamsach_RG'!D74 | J61: =E61='03. Dulieutaichinhlamsach_RG'!E74 | K61: =F61='03. Dulieutaichinhlamsach_RG'!F74 | L61: =G61='03. Dulieutaichinhlamsach_RG'!G74 | M61: =H61='03. Dulieutaichinhlamsach_RG'!H74
B62: - Giảm giá | I62: =D62='03. Dulieutaichinhlamsach_RG'!D75 | J62: =E62='03. Dulieutaichinhlamsach_RG'!E75 | K62: =F62='03. Dulieutaichinhlamsach_RG'!F75 | L62: =G62='03. Dulieutaichinhlamsach_RG'!G75 | M62: =H62='03. Dulieutaichinhlamsach_RG'!H75
B63: - Hàng bán bị trả lại | I63: =D63='03. Dulieutaichinhlamsach_RG'!D76 | J63: =E63='03. Dulieutaichinhlamsach_RG'!E76 | K63: =F63='03. Dulieutaichinhlamsach_RG'!F76 | L63: =G63='03. Dulieutaichinhlamsach_RG'!G76 | M63: =H63='03. Dulieutaichinhlamsach_RG'!H76
B64: - Thuế VAT, thuế xuất khẩu | I64: =D64='03. Dulieutaichinhlamsach_RG'!D77 | J64: =E64='03. Dulieutaichinhlamsach_RG'!E77 | K64: =F64='03. Dulieutaichinhlamsach_RG'!F77 | L64: =G64='03. Dulieutaichinhlamsach_RG'!G77 | M64: =H64='03. Dulieutaichinhlamsach_RG'!H77
B65: Doanh thu thuần về bán hàng và cung cấp dịch vụ | I65: =D65='03. Dulieutaichinhlamsach_RG'!D78 | J65: =E65='03. Dulieutaichinhlamsach_RG'!E78 | K65: =F65='03. Dulieutaichinhlamsach_RG'!F78 | L65: =G65='03. Dulieutaichinhlamsach_RG'!G78 | M65: =H65='03. Dulieutaichinhlamsach_RG'!H78
B66: Giá vốn hàng bán | I66: =D66='03. Dulieutaichinhlamsach_RG'!D79 | J66: =E66='03. Dulieutaichinhlamsach_RG'!E79 | K66: =F66='03. Dulieutaichinhlamsach_RG'!F79 | L66: =G66='03. Dulieutaichinhlamsach_RG'!G79 | M66: =H66='03. Dulieutaichinhlamsach_RG'!H79
B67: - Tr/đó: Khấu hao trong giá vốn hàng bán | I67: =D67='03. Dulieutaichinhlamsach_RG'!D80 | J67: =E67='03. Dulieutaichinhlamsach_RG'!E80 | K67: =F67='03. Dulieutaichinhlamsach_RG'!F80 | L67: =G67='03. Dulieutaichinhlamsach_RG'!G80 | M67: =H67='03. Dulieutaichinhlamsach_RG'!H80
B68: Lợi nhuận gộp về bán hàng và cung cấp dịch vụ | I68: =D68='03. Dulieutaichinhlamsach_RG'!D81 | J68: =E68='03. Dulieutaichinhlamsach_RG'!E81 | K68: =F68='03. Dulieutaichinhlamsach_RG'!F81 | L68: =G68='03. Dulieutaichinhlamsach_RG'!G81 | M68: =H68='03. Dulieutaichinhlamsach_RG'!H81
B69: Doanh thu hoạt động tài chính | I69: =D69='03. Dulieutaichinhlamsach_RG'!D82 | J69: =E69='03. Dulieutaichinhlamsach_RG'!E82 | K69: =F69='03. Dulieutaichinhlamsach_RG'!F82 | L69: =G69='03. Dulieutaichinhlamsach_RG'!G82 | M69: =H69='03. Dulieutaichinhlamsach_RG'!H82
B70: Chi phí tài chính | I70: =D70='03. Dulieutaichinhlamsach_RG'!D83 | J70: =E70='03. Dulieutaichinhlamsach_RG'!E83 | K70: =F70='03. Dulieutaichinhlamsach_RG'!F83 | L70: =G70='03. Dulieutaichinhlamsach_RG'!G83 | M70: =H70='03. Dulieutaichinhlamsach_RG'!H83
... B80: Lãi cơ bản trên cổ phiếu | I80: =D80='03. Dulieutaichinhlamsach_RG'!D93 | J80: =E80='03. Dulieutaichinhlamsach_RG'!E93 | K80: =F80='03. Dulieutaichinhlamsach_RG'!F93 | L80: =G80='03. Dulieutaichinhlamsach_RG'!G93 | M80: =H80='03. Dulieutaichinhlamsach_RG'!H93

Sheet 03. Dulieutaichinhlamsach_RG
B1: NHẬP SỐ LIỆU VỀ TÀI CHÍNH CỦA KHÁCH HÀNG
C2: =IF(OR(E11=0,F11=0),"Đề nghị nhấp số liệu tối thiểu 2 năm gần nhất"," ") | F2: Đơn vị: | G2: ='01. Thong tin chung'!B6 | H2: =G2 | J2: CountBlankBCTC | K2: =COUNTIF(D4:G4,"Chưa cân số") + COUNTIF(G2,"")
B3: I. Bảng cân đối kế toán
D4: =IF(D11<>D38,"Chưa cân số", " ") | E4: =IF(E11<>E38,"Chưa cân số", " ") | F4: =IF(F11<>F38,"Chưa cân số", " ") | G4: =IF(G11<>G38,"Chưa cân số", " ") | H4: =IF(H11<>H38,"Chưa cân số", " ")
B5: Chỉ tiêu | C5: Mã số | D5: =E5-1 | E5: =F5-1 | F5: ='01. Thong tin chung'!B7 | G5: ='01. Thong tin chung'!B8 | H5: ="Dự tính " &F5+1
B6: Mã số thuế | D6: ='02. Nhap lieu tai chinh_RG'!D6 | E6: ='02. Nhap lieu tai chinh_RG'!E6 | F6: ='02. Nhap lieu tai chinh_RG'!F6 | G6: ='02. Nhap lieu tai chinh_RG'!G6 | H6: ='02. Nhap lieu tai chinh_RG'!H6
B7: Năm | D7: ='02. Nhap lieu tai chinh_RG'!D7 | E7: ='02. Nhap lieu tai chinh_RG'!E7 | F7: ='02. Nhap lieu tai chinh_RG'!F7 | G7: ='02. Nhap lieu tai chinh_RG'!G7 | H7: ='02. Nhap lieu tai chinh_RG'!H7
B8: Quý | D8: ='02. Nhap lieu tai chinh_RG'!D8 | E8: ='02. Nhap lieu tai chinh_RG'!E8 | F8: ='02. Nhap lieu tai chinh_RG'!F8 | G8: ='02. Nhap lieu tai chinh_RG'!G8 | H8: ='02. Nhap lieu tai chinh_RG'!H8
B9: Tháng | D9: ='02. Nhap lieu tai chinh_RG'!D9 | E9: ='02. Nhap lieu tai chinh_RG'!E9 | F9: ='02. Nhap lieu tai chinh_RG'!F9 | G9: ='02. Nhap lieu tai chinh_RG'!G9 | H9: ='02. Nhap lieu tai chinh_RG'!H9
B10: Đơn vị tính | D10: ='02. Nhap lieu tai chinh_RG'!D10 | E10: ='02. Nhap lieu tai chinh_RG'!E10 | F10: ='02. Nhap lieu tai chinh_RG'!F10 | G10: ='02. Nhap lieu tai chinh_RG'!G10 | H10: ='02. Nhap lieu tai chinh_RG'!H10
B11: TỔNG TÀI SẢN | D11: =D12+D13+D18+D25+D28+D31+D34+D35 | E11: =E12+E13+E18+E25+E28+E31+E34+E35 | F11: =F12+F13+F18+F25+F28+F31+F34+F35 | G11: =G12+G13+G18+G25+G28+G31+G34+G35 | H11: =H12+H13+H18+H25+H28+H31+H34+H35
B12: I. Tiền và các khoản tương đương tiền | D12: ='02. Nhap lieu tai chinh_RG'!D12 | E12: ='02. Nhap lieu tai chinh_RG'!E12 | F12: ='02. Nhap lieu tai chinh_RG'!F12 | G12: ='02. Nhap lieu tai chinh_RG'!G12 | H12: ='02. Nhap lieu tai chinh_RG'!H12
B13: II. Đầu tư tài chính | D13: =SUM(D14:D17) | E13: =SUM(E14:E17) | F13: =SUM(F14:F17) | G13: =SUM(G14:G17) | H13: =SUM(H14:H17)
B14: 1. Chứng khoán kinh doanh | D14: ='02. Nhap lieu tai chinh_RG'!D14 | E14: ='02. Nhap lieu tai chinh_RG'!E14 | F14: ='02. Nhap lieu tai chinh_RG'!F14 | G14: ='02. Nhap lieu tai chinh_RG'!G14 | H14: ='02. Nhap lieu tai chinh_RG'!H14
B15: 2. Đầu tư nắm giữ đến ngày đáo hạn | D15: ='02. Nhap lieu tai chinh_RG'!D15 | E15: ='02. Nhap lieu tai chinh_RG'!E15 | F15: ='02. Nhap lieu tai chinh_RG'!F15 | G15: ='02. Nhap lieu tai chinh_RG'!G15 | H15: ='02. Nhap lieu tai chinh_RG'!H15
B16: 3. Đầu tư góp vốn vào đơn vị khác | D16: ='02. Nhap lieu tai chinh_RG'!D16 | E16: ='02. Nhap lieu tai chinh_RG'!E16 | F16: ='02. Nhap lieu tai chinh_RG'!F16 | G16: ='02. Nhap lieu tai chinh_RG'!G16 | H16: ='02. Nhap lieu tai chinh_RG'!H16
B17: 4. Dự phòng tổn thất đầu tư tài chính (*) | D17: ='02. Nhap lieu tai chinh_RG'!D17 | E17: ='02. Nhap lieu tai chinh_RG'!E17 | F17: ='02. Nhap lieu tai chinh_RG'!F17 | G17: ='02. Nhap lieu tai chinh_RG'!G17 | H17: ='02. Nhap lieu tai chinh_RG'!H17
B18: III. Các khoản phải thu | D18: =SUM(D19:D24) | E18: =SUM(E19:E24) | F18: =SUM(F19:F24) | G18: =SUM(G19:G24) | H18: =SUM(H19:H24)
B19: 1. Phải thu của khách hàng | D19: ='02. Nhap lieu tai chinh_RG'!D19 | E19: ='02. Nhap lieu tai chinh_RG'!E19 | F19: ='02. Nhap lieu tai chinh_RG'!F19 | G19: ='02. Nhap lieu tai chinh_RG'!G19 | H19: ='02. Nhap lieu tai chinh_RG'!H19
B20: 2. Trả trước cho người bán | D20: ='02. Nhap lieu tai chinh_RG'!D20 | E20: ='02. Nhap lieu tai chinh_RG'!E20 | F20: ='02. Nhap lieu tai chinh_RG'!F20 | G20: ='02. Nhap lieu tai chinh_RG'!G20 | H20: ='02. Nhap lieu tai chinh_RG'!H20
B21: 3. Vốn kinh doanh ở đơn vị trực thuộc | D21: ='02. Nhap lieu tai chinh_RG'!D21 | E21: ='02. Nhap lieu tai chinh_RG'!E21 | F21: ='02. Nhap lieu tai chinh_RG'!F21 | G21: ='02. Nhap lieu tai chinh_RG'!G21 | H21: ='02. Nhap lieu tai chinh_RG'!H21
B22: 4. Phải thu khác | D22: ='02. Nhap lieu tai chinh_RG'!D22 | E22: ='02. Nhap lieu tai chinh_RG'!E22 | F22: ='02. Nhap lieu tai chinh_RG'!F22 | G22: ='02. Nhap lieu tai chinh_RG'!G22 | H22: ='02. Nhap lieu tai chinh_RG'!H22
B23: 5. Tài sản thiếu chờ xử lý | D23: ='02. Nhap lieu tai chinh_RG'!D23 | E23: ='02. Nhap lieu tai chinh_RG'!E23 | F23: ='02. Nhap lieu tai chinh_RG'!F23 | G23: ='02. Nhap lieu tai chinh_RG'!G23 | H23: ='02. Nhap lieu tai chinh_RG'!H23
B24: 6. Dự phòng phải thu khó đòi (*) | D24: ='02. Nhap lieu tai chinh_RG'!D24 | E24: ='02. Nhap lieu tai chinh_RG'!E24 | F24: ='02. Nhap lieu tai chinh_RG'!F24 | G24: ='02. Nhap lieu tai chinh_RG'!G24 | H24: ='02. Nhap lieu tai chinh_RG'!H24
B25: IV. Hàng tồn kho | D25: =SUM(D26:D27) | E25: =SUM(E26:E27) | F25: =SUM(F26:F27) | G25: =SUM(G26:G27) | H25: =SUM(H26:H27)
B26: 1. Hàng tồn kho | D26: ='02. Nhap lieu tai chinh_RG'!D26 | E26: ='02. Nhap lieu tai chinh_RG'!E26 | F26: ='02. Nhap lieu tai chinh_RG'!F26 | G26: ='02. Nhap lieu tai chinh_RG'!G26 | H26: ='02. Nhap lieu tai chinh_RG'!H26
B27: 2. Dự phòng giảm giả hàng tồn kho (*) | D27: ='02. Nhap lieu tai chinh_RG'!D27 | E27: ='02. Nhap lieu tai chinh_RG'!E27 | F27: ='02. Nhap lieu tai chinh_RG'!F27 | G27: ='02. Nhap lieu tai chinh_RG'!G27 | H27: ='02. Nhap lieu tai chinh_RG'!H27
B28: V. Tài sản cố định | D28: =SUM(D29:D30) | E28: =SUM(E29:E30) | F28: =SUM(F29:F30) | G28: =SUM(G29:G30) | H28: =SUM(H29:H30)
B29: - Nguyên giá | D29: ='02. Nhap lieu tai chinh_RG'!D29 | E29: ='02. Nhap lieu tai chinh_RG'!E29 | F29: ='02. Nhap lieu tai chinh_RG'!F29 | G29: ='02. Nhap lieu tai chinh_RG'!G29 | H29: ='02. Nhap lieu tai chinh_RG'!H29
B30: - Giá trị hao mòn lũy kế | D30: ='02. Nhap lieu tai chinh_RG'!D30 | E30: ='02. Nhap lieu tai chinh_RG'!E30 | F30: ='02. Nhap lieu tai chinh_RG'!F30 | G30: ='02. Nhap lieu tai chinh_RG'!G30 | H30: ='02. Nhap lieu tai chinh_RG'!H30
B31: VI. Bất động sản đầu tư | D31: =SUM(D32:D33) | E31: =SUM(E32:E33) | F31: =SUM(F32:F33) | G31: =SUM(G32:G33) | H31: =SUM(H32:H33)
B32: - Nguyên giá | D32: ='02. Nhap lieu tai chinh_RG'!D32 | E32: ='02. Nhap lieu tai chinh_RG'!E32 | F32: ='02. Nhap lieu tai chinh_RG'!F32 | G32: ='02. Nhap lieu tai chinh_RG'!G32 | H32: ='02. Nhap lieu tai chinh_RG'!H32
B33: - Giá trị hao mòn lũy kế (*) | D33: ='02. Nhap lieu tai chinh_RG'!D33 | E33: ='02. Nhap lieu tai chinh_RG'!E33 | F33: ='02. Nhap lieu tai chinh_RG'!F33 | G33: ='02. Nhap lieu tai chinh_RG'!G33 | H33: ='02. Nhap lieu tai chinh_RG'!H33
B34: VII. XDCB dở dang | D34: ='02. Nhap lieu tai chinh_RG'!D34 | E34: ='02. Nhap lieu tai chinh_RG'!E34 | F34: ='02. Nhap lieu tai chinh_RG'!F34 | G34: ='02. Nhap lieu tai chinh_RG'!G34 | H34: ='02. Nhap lieu tai chinh_RG'!H34
B35: VIII. Tài sản khác | D35: =SUM(D36:D37) | E35: =SUM(E36:E37) | F35: =SUM(F36:F37) | G35: =SUM(G36:G37) | H35: =SUM(H36:H37)
B36: 1. Thuế GTGT được khấu trừ | D36: ='02. Nhap lieu tai chinh_RG'!D36 | E36: ='02. Nhap lieu tai chinh_RG'!E36 | F36: ='02. Nhap lieu tai chinh_RG'!F36 | G36: ='02. Nhap lieu tai chinh_RG'!G36 | H36: ='02. Nhap lieu tai chinh_RG'!H36
B37: 2. Tài sản khác | D37: ='02. Nhap lieu tai chinh_RG'!D37 | E37: ='02. Nhap lieu tai chinh_RG'!E37 | F37: ='02. Nhap lieu tai chinh_RG'!F37 | G37: ='02. Nhap lieu tai chinh_RG'!G37 | H37: ='02. Nhap lieu tai chinh_RG'!H37
B38: TỔNG NGUỒN VỐN | D38: =D39+D50 | E38: =E39+E50 | F38: =F39+F50 | G38: =G39+G50 | H38: =H39+H50
B39: I. Nợ phải trả | D39: =SUM(D40:D49) | E39: =SUM(E40:E49) | F39: =SUM(F40:F49) | G39: =SUM(G40:G49) | H39: =SUM(H40:H49)
B40: 1. Phải trả người bán | D40: ='02. Nhap lieu tai chinh_RG'!D40 | E40: ='02. Nhap lieu tai chinh_RG'!E40 | F40: ='02. Nhap lieu tai chinh_RG'!F40 | G40: ='02. Nhap lieu tai chinh_RG'!G40 | H40: ='02. Nhap lieu tai chinh_RG'!H40
B41: 2. Người mua trả tiền trước | D41: ='02. Nhap lieu tai chinh_RG'!D41 | E41: ='02. Nhap lieu tai chinh_RG'!E41 | F41: ='02. Nhap lieu tai chinh_RG'!F41 | G41: ='02. Nhap lieu tai chinh_RG'!G41 | H41: ='02. Nhap lieu tai chinh_RG'!H41
B42: 3. Thuế và các khoản phải nộp Nhà nước | D42: ='02. Nhap lieu tai chinh_RG'!D42 | E42: ='02. Nhap lieu tai chinh_RG'!E42 | F42: ='02. Nhap lieu tai chinh_RG'!F42 | G42: ='02. Nhap lieu tai chinh_RG'!G42 | H42: ='02. Nhap lieu tai chinh_RG'!H42
B43: 4. Phải trả người lao động | D43: ='02. Nhap lieu tai chinh_RG'!D43 | E43: ='02. Nhap lieu tai chinh_RG'!E43 | F43: ='02. Nhap lieu tai chinh_RG'!F43 | G43: ='02. Nhap lieu tai chinh_RG'!G43 | H43: ='02. Nhap lieu tai chinh_RG'!H43
B44: 5. Phải trả khác | D44: ='02. Nhap lieu tai chinh_RG'!D44 | E44: ='02. Nhap lieu tai chinh_RG'!E44 | F44: ='02. Nhap lieu tai chinh_RG'!F44 | G44: ='02. Nhap lieu tai chinh_RG'!G44 | H44: ='02. Nhap lieu tai chinh_RG'!H44
B45: 6. Vay và nợ thuê tài chính | D45: ='02. Nhap lieu tai chinh_RG'!D45 | E45: ='02. Nhap lieu tai chinh_RG'!E45 | F45: ='02. Nhap lieu tai chinh_RG'!F45 | G45: ='02. Nhap lieu tai chinh_RG'!G45 | H45: ='02. Nhap lieu tai chinh_RG'!H45
B46: 7. Phải trả nội bộ về vốn kinh doanh | D46: ='02. Nhap lieu tai chinh_RG'!D46 | E46: ='02. Nhap lieu tai chinh_RG'!E46 | F46: ='02. Nhap lieu tai chinh_RG'!F46 | G46: ='02. Nhap lieu tai chinh_RG'!G46 | H46: ='02. Nhap lieu tai chinh_RG'!H46
B47: 8. Dự phòng phải trả | D47: ='02. Nhap lieu tai chinh_RG'!D47 | E47: ='02. Nhap lieu tai chinh_RG'!E47 | F47: ='02. Nhap lieu tai chinh_RG'!F47 | G47: ='02. Nhap lieu tai chinh_RG'!G47 | H47: ='02. Nhap lieu tai chinh_RG'!H47
B48: 9. Quỹ khen thưởng, phúc lợi | D48: ='02. Nhap lieu tai chinh_RG'!D48 | E48: ='02. Nhap lieu tai chinh_RG'!E48 | F48: ='02. Nhap lieu tai chinh_RG'!F48 | G48: ='02. Nhap lieu tai chinh_RG'!G48 | H48: ='02. Nhap lieu tai chinh_RG'!H48
B49: 10. Quỹ phát triển khoa học và công nghệ | D49: ='02. Nhap lieu tai chinh_RG'!D49 | E49: ='02. Nhap lieu tai chinh_RG'!E49 | F49: ='02. Nhap lieu tai chinh_RG'!F49 | G49: ='02. Nhap lieu tai chinh_RG'!G49 | H49: ='02. Nhap lieu tai chinh_RG'!H49
B50: II. Vốn chủ sở hữu | D50: =SUM(D51:D57) | E50: =SUM(E51:E57) | F50: =SUM(F51:F57) | G50: =SUM(G51:G57) | H50: =SUM(H51:H57)
B51: 1. Vốn góp của chủ sở hữu | D51: ='02. Nhap lieu tai chinh_RG'!D51 | E51: ='02. Nhap lieu tai chinh_RG'!E51 | F51: ='02. Nhap lieu tai chinh_RG'!F51 | G51: ='02. Nhap lieu tai chinh_RG'!G51 | H51: ='02. Nhap lieu tai chinh_RG'!H51
B52: 2. Thặng dư vốn cổ phần | D52: ='02. Nhap lieu tai chinh_RG'!D52 | E52: ='02. Nhap lieu tai chinh_RG'!E52 | F52: ='02. Nhap lieu tai chinh_RG'!F52 | G52: ='02. Nhap lieu tai chinh_RG'!G52 | H52: ='02. Nhap lieu tai chinh_RG'!H52
B53: 3. Vốn khác của chủ sở hữu | D53: ='02. Nhap lieu tai chinh_RG'!D53 | E53: ='02. Nhap lieu tai chinh_RG'!E53 | F53: ='02. Nhap lieu tai chinh_RG'!F53 | G53: ='02. Nhap lieu tai chinh_RG'!G53 | H53: ='02. Nhap lieu tai chinh_RG'!H53
B54: 4. Cổ phiếu quỹ (*) | D54: ='02. Nhap lieu tai chinh_RG'!D54 | E54: ='02. Nhap lieu tai chinh_RG'!E54 | F54: ='02. Nhap lieu tai chinh_RG'!F54 | G54: ='02. Nhap lieu tai chinh_RG'!G54 | H54: ='02. Nhap lieu tai chinh_RG'!H54
B55: 5. Chênh lệch tỷ giá hối đoái | D55: ='02. Nhap lieu tai chinh_RG'!D55 | E55: ='02. Nhap lieu tai chinh_RG'!E55 | F55: ='02. Nhap lieu tai chinh_RG'!F55 | G55: ='02. Nhap lieu tai chinh_RG'!G55 | H55: ='02. Nhap lieu tai chinh_RG'!H55
B56: 6. Các quỹ thuộc vốn chủ sở hữu | D56: ='02. Nhap lieu tai chinh_RG'!D56 | E56: ='02. Nhap lieu tai chinh_RG'!E56 | F56: ='02. Nhap lieu tai chinh_RG'!F56 | G56: ='02. Nhap lieu tai chinh_RG'!G56 | H56: ='02. Nhap lieu tai chinh_RG'!H56
B57: 7. Lợi nhuận sau thuế chưa phân phối | D57: ='02. Nhap lieu tai chinh_RG'!D57 | E57: ='02. Nhap lieu tai chinh_RG'!E57 | F57: ='02. Nhap lieu tai chinh_RG'!F57 | G57: ='02. Nhap lieu tai chinh_RG'!G57 | H57: ='02. Nhap lieu tai chinh_RG'!H57
B59: II. Các chỉ tiêu ngoài bảng cân đối kế toán (nếu có)
B61: Chỉ tiêu | D61: =D5 | E61: =E5 | F61: =F5 | G61: =G5 | H61: =H5
B62: Tài sản thuê ngoài
B63: Vật tư, hàng hóa nhận giữ hộ, nhận gia công
B64: Vật tư, hàng hóa nhận bán hộ, nhận ký gửi, ký cược
B65: Nợ khó đòi đã xử lý
B66: Ngoại tệ các loại
B67: Dự toán chi phí sự nghiệp dự án
B69: III. Báo cáo kết quả hoạt động SXKD
B71: Chỉ tiêu | D71: =D5 | E71: =E5 | F71: =F5 | G71: =+G5 | H71: =+H5
B72: Doanh thu bán hàng và cung cấp dịch vụ | D72: ='02. Nhap lieu tai chinh_RG'!D59 | E72: ='02. Nhap lieu tai chinh_RG'!E59 | F72: ='02. Nhap lieu tai chinh_RG'!F59 | G72: ='02. Nhap lieu tai chinh_RG'!G59 | H72: ='02. Nhap lieu tai chinh_RG'!H59
B73: Các khoản giảm trừ doanh thu | D73: ='02. Nhap lieu tai chinh_RG'!D60 | E73: ='02. Nhap lieu tai chinh_RG'!E60 | F73: ='02. Nhap lieu tai chinh_RG'!F60 | G73: ='02. Nhap lieu tai chinh_RG'!G60 | H73: ='02. Nhap lieu tai chinh_RG'!H60
B74: - Chiết khấu | D74: ='02. Nhap lieu tai chinh_RG'!D61 | E74: ='02. Nhap lieu tai chinh_RG'!E61 | F74: ='02. Nhap lieu tai chinh_RG'!F61 | G74: ='02. Nhap lieu tai chinh_RG'!G61 | H74: ='02. Nhap lieu tai chinh_RG'!H61
B75: - Giảm giá | D75: ='02. Nhap lieu tai chinh_RG'!D62 | E75: ='02. Nhap lieu tai chinh_RG'!E62 | F75: ='02. Nhap lieu tai chinh_RG'!F62 | G75: ='02. Nhap lieu tai chinh_RG'!G62 | H75: ='02. Nhap lieu tai chinh_RG'!H62
B76: - Hàng bán bị trả lại | D76: ='02. Nhap lieu tai chinh_RG'!D63 | E76: ='02. Nhap lieu tai chinh_RG'!E63 | F76: ='02. Nhap lieu tai chinh_RG'!F63 | G76: ='02. Nhap lieu tai chinh_RG'!G63 | H76: ='02. Nhap lieu tai chinh_RG'!H63
B77: - Thuế VAT, thuế xuất khẩu | D77: ='02. Nhap lieu tai chinh_RG'!D64 | E77: ='02. Nhap lieu tai chinh_RG'!E64 | F77: ='02. Nhap lieu tai chinh_RG'!F64 | G77: ='02. Nhap lieu tai chinh_RG'!G64 | H77: ='02. Nhap lieu tai chinh_RG'!H64
B78: Doanh thu thuần về bán hàng và cung cấp dịch vụ | D78: =D72-D73 | E78: =E72-E73 | F78: =F72-F73 | G78: =G72-G73 | H78: =H72-H73
B79: Giá vốn hàng bán | D79: ='02. Nhap lieu tai chinh_RG'!D66 | E79: ='02. Nhap lieu tai chinh_RG'!E66 | F79: ='02. Nhap lieu tai chinh_RG'!F66 | G79: ='02. Nhap lieu tai chinh_RG'!G66 | H79: ='02. Nhap lieu tai chinh_RG'!H66
B80: - Tr/đó: Khấu hao trong giá vốn hàng bán | D80: ='02. Nhap lieu tai chinh_RG'!D67 | E80: ='02. Nhap lieu tai chinh_RG'!E67 | F80: ='02. Nhap lieu tai chinh_RG'!F67 | G80: ='02. Nhap lieu tai chinh_RG'!G67 | H80: ='02. Nhap lieu tai chinh_RG'!H67
B81: Lợi nhuận gộp về bán hàng và cung cấp dịch vụ | D81: =D78-D79 | E81: =E78-E79 | F81: =F78-F79 | G81: =G78-G79 | H81: =H78-H79
B82: Doanh thu hoạt động tài chính | D82: ='02. Nhap lieu tai chinh_RG'!D69 | E82: ='02. Nhap lieu tai chinh_RG'!E69 | F82: ='02. Nhap lieu tai chinh_RG'!F69 | G82: ='02. Nhap lieu tai chinh_RG'!G69 | H82: ='02. Nhap lieu tai chinh_RG'!H69
B83: Chi phí tài chính | D83: ='02. Nhap lieu tai chinh_RG'!D70 | E83: ='02. Nhap lieu tai chinh_RG'!E70 | F83: ='02. Nhap lieu tai chinh_RG'!F70 | G83: ='02. Nhap lieu tai chinh_RG'!G70 | H83: ='02. Nhap lieu tai chinh_RG'!H70
B84: - Tr/đó: Chi phí lãi vay | D84: ='02. Nhap lieu tai chinh_RG'!D71 | E84: ='02. Nhap lieu tai chinh_RG'!E71 | F84: ='02. Nhap lieu tai chinh_RG'!F71 | G84: ='02. Nhap lieu tai chinh_RG'!G71 | H84: ='02. Nhap lieu tai chinh_RG'!H71
B85: Chi phí quản lý kinh doanh | D85: ='02. Nhap lieu tai chinh_RG'!D72 | E85: ='02. Nhap lieu tai chinh_RG'!E72 | F85: ='02. Nhap lieu tai chinh_RG'!F72 | G85: ='02. Nhap lieu tai chinh_RG'!G72 | H85: ='02. Nhap lieu tai chinh_RG'!H72
B86: Lợi nhuận thuần từ HĐKD | D86: =D81+D82-D83-D85 | E86: =E81+E82-E83-E85 | F86: =F81+F82-F83-F85 | G86: =G81+G82-G83-G85 | H86: =H81+H82-H83-H85
B87: Thu nhập khác | D87: ='02. Nhap lieu tai chinh_RG'!D74 | E87: ='02. Nhap lieu tai chinh_RG'!E74 | F87: ='02. Nhap lieu tai chinh_RG'!F74 | G87: ='02. Nhap lieu tai chinh_RG'!G74 | H87: ='02. Nhap lieu tai chinh_RG'!H74
B88: Chi phí khác | D88: ='02. Nhap lieu tai chinh_RG'!D75 | E88: ='02. Nhap lieu tai chinh_RG'!E75 | F88: ='02. Nhap lieu tai chinh_RG'!F75 | G88: ='02. Nhap lieu tai chinh_RG'!G75 | H88: ='02. Nhap lieu tai chinh_RG'!H75
B89: Lợi nhuận khác | D89: =D87-D88 | E89: =E87-E88 | F89: =F87-F88 | G89: =G87-G88 | H89: =H87-H88
B90: Tổng lợi nhuận kế toán trước thuế | D90: =D86+D89 | E90: =E86+E89 | F90: =F86+F89 | G90: =G86+G89 | H90: =H86+H89
B91: Chi phí thuế TNDN | D91: ='02. Nhap lieu tai chinh_RG'!D78 | E91: ='02. Nhap lieu tai chinh_RG'!E78 | F91: ='02. Nhap lieu tai chinh_RG'!F78 | G91: ='02. Nhap lieu tai chinh_RG'!G78 | H91: ='02. Nhap lieu tai chinh_RG'!H78
B92: Lợi nhuận sau thuế TNDN | D92: =D90-D91 | E92: =E90-E91 | F92: =F90-F91 | G92: =G90-G91 | H92: =H90-H91
B93: Lãi cơ bản trên cổ phiếu | D93: ='02. Nhap lieu tai chinh_RG'!D80 | E93: ='02. Nhap lieu tai chinh_RG'!E80 | F93: ='02. Nhap lieu tai chinh_RG'!F80 | G93: ='02. Nhap lieu tai chinh_RG'!G80
B95: IV. Kết quả tính các chỉ số phân tích
B97: Chỉ tiêu | D97: =D71 | E97: =E71 | F97: =F5 | G97: =G5 | H97: =H5 | J97: Trong trường hợp các chỉ giá trị ở mẫu số bằng 0, chương trình tự động cộng thêm 1 vào mẫu số | N97: Năm N-2 so với TB ngành | O97: Năm N-1 so với TB ngành | P97: Năm N so với TB ngành | R97: Năm N+1 so với TB ngành
B98: Chỉ tiêu thanh khoản
B99: 1.Khả năng thanh toán hiện hành (lần) | C99: Ko áp dụng | N99: =IF(D99>$G$220,">",IF(D99=$G$220,"=","<")) | O99: =IF(E99>G145,">",IF(E99=G145,"=","<")) | P99: =IF(F99>G145,">",IF(F99=G145,"=","<")) | Q99: =IF(G99>$G$220,">",IF(G99=$G$220,"=","<")) | R99: =IF(H99>G145,">",IF(H99=G145,"=","<"))
B100: 2. Khả năng thanh toán nhanh (lần) | C100: Ko áp dụng | N100: =IF(D100>$G$220,">",IF(D100=$G$220,"=","<")) | O100: =IF(E100>G146,">",IF(E100=G146,"=","<")) | P100: =IF(F100>G146,">",IF(F100=G146,"=","<")) | R100: =IF(H100>G146,">",IF(H100=G146,"=","<"))
B101: 3. Khả năng thanh toán tức thời (lần) | C101: Ko áp dụng | N101: =IF(D101>$G$220,">",IF(D101=$G$220,"=","<")) | O101: =IF(E101>G147,">",IF(E101=G147,"=","<")) | P101: =IF(F101>G147,">",IF(F101=G147,"=","<")) | R101: =IF(H101>G147,">",IF(H101=G147,"=","<"))
B102: Chỉ tiêu hoạt động
B103: 4. Vòng quay vốn lưu động (vòng) | C103: Ko áp dụng | N103: =IF(D103>G149,">",IF(D103=G149,"=","<")) | O103: =IF(E103>G149,">",IF(E103=G149,"=","<")) | P103: =IF(F103>G149,">",IF(F103=G149,"=","<")) | R103: =IF(H103>G149,">",IF(H103=G149,"=","<"))
B104: 5. Vòng quay hàng tồn kho (vòng) - Q2a | D104: =IF(D25<>0,D79/D25,-99999) | E104: =IF(E25<>0,E79/E25,-99999) | F104: =IF(F25<>0,F79/F25,-99999) | G104: =IF(G25<>0,G79/G25,-99999) | H104: =IF(H25<>0,H79/H25,-99999) | N104: =IF(D104>G150,">",IF(D104=G150,"=","<")) | O104: =IF(E104>G150,">",IF(E104=G150,"=","<")) | P104: =IF(F104>G150,">",IF(F104=G150,"=","<")) | R104: =IF(H104>G150,">",IF(H104=G150,"=","<"))
B105: 6. Vòng quay các khoản phải thu (vòng) - Q2b | C105: Ko áp dụng | N105: =IF(D105>G151,">",IF(D105=G151,"=","<")) | O105: =IF(E105>G151,">",IF(E105=G151,"=","<")) | P105: =IF(F105>G151,">",IF(F105=G151,"=","<")) | R105: =IF(H105>G151,">",IF(H105=G151,"=","<"))
B106: 7. Vòng quay khoản phải trả (Payables Turnover) - Q2c | C106: Ko áp dụng | P106: =IF(F106>G152,">",IF(F106=G152,"=","<"))
...

Sheet 06. Phan tich tai chinh_RG
J1: MSB
D2: =IF('01. Thong tin chung'!B9="Đầy đủ",IF(ISBLANK('06. Phan tich tai chinh_DD'!B9),0,'06. Phan tich tai chinh_DD'!B9),IF(ISBLANK('06. Phan tich tai chinh_RG'!B9),0,'06. Phan tich tai chinh_RG'!B9)) | J2: TNR Tower, 54A Nguyễn Chí Thanh, Đống Đa, Hà Nội
A4: PHỤ LỤC: PHÂN TÍCH TÀI CHÍNH
A5: (Kèm theo Tờ trình số ngày / / )
A7: ='01. Thong tin chung'!B3 | B7: ='03. Dulieutaichinhlamsach_RG'!D5 | C7: ='03. Dulieutaichinhlamsach_RG'!E5 | D7: ='03. Dulieutaichinhlamsach_RG'!F5 | G7: ='03. Dulieutaichinhlamsach_RG'!G5 | I7: ="Dự kiến năm "&'03. Dulieutaichinhlamsach_RG'!F5+1 | J7: Nội dung phân tích (nếu có)
A8: ="Đơn vị tính: "&'01. Thong tin chung'!B6 | B8: =IF(OR(B9-B36>1,B9-B36<-1),"Chưa cân số","") | C8: =IF(OR(C9-C36>1,C9-C36<-1),"Chưa cân số","") | D8: =IF(OR(D9-D36>1,D9-D36<-1),"Chưa cân số","") | E8: Tỷ trọng | F8: Tăng trưởng | G8: =IF(OR(G9-G36>1,G9-G36<-1),"Chưa cân số","") | H8: Tỷ trọng | I8: =IF(OR(I9-I36>1,I9-I36<-1),"Chưa cân số","")
A9: TỔNG TÀI SẢN | B9: =B10+B11+B16+B23+B26+B32+B33 | C9: =C10+C11+C16+C23+C26+C32+C33 | D9: =D10+D11+D16+D23+D26+D32+D33 | E9: =IF($D$9<>0,D9/$D$9,"") | F9: =IF(C9<>0,(D9-C9)/C9,"") | G9: =G10+G11+G16+G23+G26+G32+G33 | H9: =IF($G$9<>0,G9/$G$9,"") | I9: =I10+I11+I16+I23+I26+I32+I33
A10: I. Tiền và các khoản tương đương tiền | B10: =IF(TRIM('03. Dulieutaichinhlamsach_RG'!$G$2)="VND",'03. Dulieutaichinhlamsach_RG'!D12/10^6,'03. Dulieutaichinhlamsach_RG'!D12) | C10: =IF(TRIM('03. Dulieutaichinhlamsach_RG'!$G$2)="VND",'03. Dulieutaichinhlamsach_RG'!E12/10^6,'03. Dulieutaichinhlamsach_RG'!E12) | D10: =IF(TRIM('03. Dulieutaichinhlamsach_RG'!$G$2)="VND",'03. Dulieutaichinhlamsach_RG'!F12/10^6,'03. Dulieutaichinhlamsach_RG'!F12) | E10: =IF($D$9<>0,D10/$D$9,"") | F10: =IF(C10<>0,(D10-C10)/C10,"") | G10: =IF(TRIM('03. Dulieutaichinhlamsach_RG'!$G$2)="VND",'03. Dulieutaichinhlamsach_RG'!I12/10^6,'03. Dulieutaichinhlamsach_RG'!I12) | H10: =IF($G$9<>0,G10/$G$9,"") | I10: =IF(TRIM('03. Dulieutaichinhlamsach_RG'!$G$2)="VND",'03. Dulieutaichinhlamsach_RG'!K12/10^6,'03. Dulieutaichinhlamsach_RG'!K12)
A11: II. Đầu tư tài chính | B11: =SUM(B12:B15) | C11: =SUM(C12:C15) | D11: =SUM(D12:D15) | E11: =IF($D$9<>0,D11/$D$9,"") | F11: =IF(C11<>0,(D11-C11)/C11,"") | G11: =SUM(G12:G15) | H11: =IF($G$10<>0,G11/$G$10," ") | I11: =SUM(I12:I15)
A12: 1. Chứng khoán kinh doanh | B12: =IF(TRIM('03. Dulieutaichinhlamsach_RG'!$G$2)="VND",'03. Dulieutaichinhlamsach_RG'!D14/10^6,'03. Dulieutaichinhlamsach_RG'!D14) | C12: =IF(TRIM('03. Dulieutaichinhlamsach_RG'!$G$2)="VND",'03. Dulieutaichinhlamsach_RG'!E14/10^6,'03. Dulieutaichinhlamsach_RG'!E14) | D12: =IF(TRIM('03. Dulieutaichinhlamsach_RG'!$G$2)="VND",'03. Dulieutaichinhlamsach_RG'!F14/10^6,'03. Dulieutaichinhlamsach_RG'!F14) | E12: =IF($D$9<>0,D12/$D$9,"") | F12: =IF(C12<>0,(D12-C12)/C12,"") | G12: =IF(TRIM('03. Dulieutaichinhlamsach_RG'!$G$2)="VND",'03. Dulieutaichinhlamsach_RG'!I14/10^6,'03. Dulieutaichinhlamsach_RG'!I14) | H12: =IF($G$10<>0,G12/$G$10," ") | I12: =IF(TRIM('03. Dulieutaichinhlamsach_RG'!$G$2)="VND",'03. Dulieutaichinhlamsach_RG'!H14/10^6,'03. Dulieutaichinhlamsach_RG'!H14)
A13: 2. Đầu tư nắm giữ đến ngày đáo hạn | B13: =IF(TRIM('03. Dulieutaichinhlamsach_RG'!$G$2)="VND",'03. Dulieutaichinhlamsach_RG'!D15/10^6,'03. Dulieutaichinhlamsach_RG'!D15) | C13: =IF(TRIM('03. Dulieutaichinhlamsach_RG'!$G$2)="VND",'03. Dulieutaichinhlamsach_RG'!E15/10^6,'03. Dulieutaichinhlamsach_RG'!E15) | D13: =IF(TRIM('03. Dulieutaichinhlamsach_RG'!$G$2)="VND",'03. Dulieutaichinhlamsach_RG'!F15/10^6,'03. Dulieutaichinhlamsach_RG'!F15) | E13: =IF($D$9<>0,D13/$D$9,"") | F13: =IF(C13<>0,(D13-C13)/C13,"") | G13: =IF(TRIM('03. Dulieutaichinhlamsach_RG'!$G$2)="VND",'03. Dulieutaichinhlamsach_RG'!I15/10^6,'03. Dulieutaichinhlamsach_RG'!I15) | H13: =IF($G$10<>0,G13/$G$10," ") | I13: =IF(TRIM('03. Dulieutaichinhlamsach_RG'!$G$2)="VND",'03. Dulieutaichinhlamsach_RG'!H15/10^6,'03. Dulieutaichinhlamsach_RG'!H15)
A14: 3. Đầu tư góp vốn vào đơn vị khác | B14: =IF(TRIM('03. Dulieutaichinhlamsach_RG'!$G$2)="VND",'03. Dulieutaichinhlamsach_RG'!D16/10^6,'03. Dulieutaichinhlamsach_RG'!D16) | C14: =IF(TRIM('03. Dulieutaichinhlamsach_RG'!$G$2)="VND",'03. Dulieutaichinhlamsach_RG'!E16/10^6,'03. Dulieutaichinhlamsach_RG'!E16) | D14: =IF(TRIM('03. Dulieutaichinhlamsach_RG'!$G$2)="VND",'03. Dulieutaichinhlamsach_RG'!F16/10^6,'03. Dulieutaichinhlamsach_RG'!F16) | E14: =IF($D$9<>0,D14/$D$9,"") | F14: =IF(C14<>0,(D14-C14)/C14,"") | G14: =IF(TRIM('03. Dulieutaichinhlamsach_RG'!$G$2)="VND",'03. Dulieutaichinhlamsach_RG'!I16/10^6,'03. Dulieutaichinhlamsach_RG'!I16) | H14: =IF($G$10<>0,G14/$G$10," ") | I14: =IF(TRIM('03. Dulieutaichinhlamsach_RG'!$G$2)="VND",'03. Dulieutaichinhlamsach_RG'!H16/10^6,'03. Dulieutaichinhlamsach_RG'!H16)
A15: 4. Dự phòng tổn thất đầu tư tài chính (*) | B15: =IF(TRIM('03. Dulieutaichinhlamsach_RG'!$G$2)="VND",'03. Dulieutaichinhlamsach_RG'!D17/10^6,'03. Dulieutaichinhlamsach_RG'!D17) | C15: =IF(TRIM('03. Dulieutaichinhlamsach_RG'!$G$2)="VND",'03. Dulieutaichinhlamsach_RG'!E17/10^6,'03. Dulieutaichinhlamsach_RG'!E17) | D15: =IF(TRIM('03. Dulieutaichinhlamsach_RG'!$G$2)="VND",'03. Dulieutaichinhlamsach_RG'!F17/10^6,'03. Dulieutaichinhlamsach_RG'!F17) | E15: =IF($D$9<>0,D15/$D$9,"") | F15: =IF(C15<>0,(D15-C15)/C15,"") | G15: =IF(TRIM('03. Dulieutaichinhlamsach_RG'!$G$2)="VND",'03. Dulieutaichinhlamsach_RG'!I17/10^6,'03. Dulieutaichinhlamsach_RG'!I17) | H15: =IF($G$10<>0,G15/$G$10," ") | I15: =IF(TRIM('03. Dulieutaichinhlamsach_RG'!$G$2)="VND",'03. Dulieutaichinhlamsach_RG'!H17/10^6,'03. Dulieutaichinhlamsach_RG'!H17)
A16: III. Các khoản phải thu | B16: =SUM(B17:B22) | C16: =SUM(C17:C22) | D16: =SUM(D17:D22) | E16: =IF($D$10<>0,D16/$D$10," ") | F16: =IF(C16<>0,(D16-C16)/C16,"") | G16: =SUM(G17:G22) | H16: =IF($G$10<>0,G16/$G$10," ") | I16: =IF(TRIM('03. Dulieutaichinhlamsach_RG'!$G$2)="VND",'03. Dulieutaichinhlamsach_RG'!H18/10^6,'03. Dulieutaichinhlamsach_RG'!H18)
A17: 1. Phải thu của khách hàng | B17: =IF(TRIM('03. Dulieutaichinhlamsach_RG'!$G$2)="VND",'03. Dulieutaichinhlamsach_RG'!D19/10^6,'03. Dulieutaichinhlamsach_RG'!D19) | C17: =IF(TRIM('03. Dulieutaichinhlamsach_RG'!$G$2)="VND",'03. Dulieutaichinhlamsach_RG'!E19/10^6,'03. Dulieutaichinhlamsach_RG'!E19) | D17: =IF(TRIM('03. Dulieutaichinhlamsach_RG'!$G$2)="VND",'03. Dulieutaichinhlamsach_RG'!F19/10^6,'03. Dulieutaichinhlamsach_RG'!F19) | E17: =IF($D$10<>0,D17/$D$10," ") | F17: =IF(C17<>0,(D17-C17)/C17,"") | G17: =IF(TRIM('03. Dulieutaichinhlamsach_RG'!$G$2)="VND",'03. Dulieutaichinhlamsach_RG'!I19/10^6,'03. Dulieutaichinhlamsach_RG'!I19) | H17: =IF($G$10<>0,G17/$G$10," ") | I17: =IF(TRIM('03. Dulieutaichinhlamsach_RG'!$G$2)="VND",'03. Dulieutaichinhlamsach_RG'!K19/10^6,'03. Dulieutaichinhlamsach_RG'!K19)
A18: 2. Trả trước cho người bán | B18: =IF(TRIM('03. Dulieutaichinhlamsach_RG'!$G$2)="VND",'03. Dulieutaichinhlamsach_RG'!D20/10^6,'03. Dulieutaichinhlamsach_RG'!D20) | C18: =IF(TRIM('03. Dulieutaichinhlamsach_RG'!$G$2)="VND",'03. Dulieutaichinhlamsach_RG'!E20/10^6,'03. Dulieutaichinhlamsach_RG'!E20) | D18: =IF(TRIM('03. Dulieutaichinhlamsach_RG'!$G$2)="VND",'03. Dulieutaichinhlamsach_RG'!F20/10^6,'03. Dulieutaichinhlamsach_RG'!F20) | E18: =IF($D$10<>0,D18/$D$10," ") | F18: =IF(C18<>0,(D18-C18)/C18,"") | G18: =IF(TRIM('03. Dulieutaichinhlamsach_RG'!$G$2)="VND",'03. Dulieutaichinhlamsach_RG'!I20/10^6,'03. Dulieutaichinhlamsach_RG'!I20) | H18: =IF($G$10<>0,G18/$G$10," ") | I18: =IF(TRIM('03. Dulieutaichinhlamsach_RG'!$G$2)="VND",'03. Dulieutaichinhlamsach_RG'!K20/10^6,'03. Dulieutaichinhlamsach_RG'!K20)
A19: 3. Vốn kinh doanh ở đơn vị trực thuộc | B19: =IF(TRIM('03. Dulieutaichinhlamsach_RG'!$G$2)="VND",'03. Dulieutaichinhlamsach_RG'!D21/10^6,'03. Dulieutaichinhlamsach_RG'!D21) | C19: =IF(TRIM('03. Dulieutaichinhlamsach_RG'!$G$2)="VND",'03. Dulieutaichinhlamsach_RG'!E21/10^6,'03. Dulieutaichinhlamsach_RG'!E21) | D19: =IF(TRIM('03. Dulieutaichinhlamsach_RG'!$G$2)="VND",'03. Dulieutaichinhlamsach_RG'!F21/10^6,'03. Dulieutaichinhlamsach_RG'!F21) | E19: =IF($D$10<>0,D19/$D$10," ") | F19: =IF(C19<>0,(D19-C19)/C19,"") | G19: =IF(TRIM('03. Dulieutaichinhlamsach_RG'!$G$2)="VND",'03. Dulieutaichinhlamsach_RG'!I21/10^6,'03. Dulieutaichinhlamsach_RG'!I21) | H19: =IF($G$10<>0,G19/$G$10," ") | I19: =IF(TRIM('03. Dulieutaichinhlamsach_RG'!$G$2)="VND",'03. Dulieutaichinhlamsach_RG'!K21/10^6,'03. Dulieutaichinhlamsach_RG'!K21)
A20: 4. Phải thu khác | B20: =IF(TRIM('03. Dulieutaichinhlamsach_RG'!$G$2)="VND",'03. Dulieutaichinhlamsach_RG'!D22/10^6,'03. Dulieutaichinhlamsach_RG'!D22) | C20: =IF(TRIM('03. Dulieutaichinhlamsach_RG'!$G$2)="VND",'03. Dulieutaichinhlamsach_RG'!E22/10^6,'03. Dulieutaichinhlamsach_RG'!E22) | D20: =IF(TRIM('03. Dulieutaichinhlamsach_RG'!$G$2)="VND",'03. Dulieutaichinhlamsach_RG'!F22/10^6,'03. Dulieutaichinhlamsach_RG'!F22) | E20: =IF($D$10<>0,D20/$D$10," ") | F20: =IF(C20<>0,(D20-C20)/C20,"") | G20: =IF(TRIM('03. Dulieutaichinhlamsach_RG'!$G$2)="VND",'03. Dulieutaichinhlamsach_RG'!I22/10^6,'03. Dulieutaichinhlamsach_RG'!I22) | H20: =IF($G$10<>0,G20/$G$10," ") | I20: =IF(TRIM('03. Dulieutaichinhlamsach_RG'!$G$2)="VND",'03. Dulieutaichinhlamsach_RG'!K22/10^6,'03. Dulieutaichinhlamsach_RG'!K22)
A21: 5. Tài sản thiếu chờ xử lý | B21: =IF(TRIM('03. Dulieutaichinhlamsach_RG'!$G$2)="VND",'03. Dulieutaichinhlamsach_RG'!D23/10^6,'03. Dulieutaichinhlamsach_RG'!D23) | C21: =IF(TRIM('03. Dulieutaichinhlamsach_RG'!$G$2)="VND",'03. Dulieutaichinhlamsach_RG'!E23/10^6,'03. Dulieutaichinhlamsach_RG'!E23) | D21: =IF(TRIM('03. Dulieutaichinhlamsach_RG'!$G$2)="VND",'03. Dulieutaichinhlamsach_RG'!F23/10^6,'03. Dulieutaichinhlamsach_RG'!F23) | E21: =IF($D$10<>0,D21/$D$10," ") | F21: =IF(C21<>0,(D21-C21)/C21,"") | G21: =IF(TRIM('03. Dulieutaichinhlamsach_RG'!$G$2)="VND",'03. Dulieutaichinhlamsach_RG'!I23/10^6,'03. Dulieutaichinhlamsach_RG'!I23) | H21: =IF($G$10<>0,G21/$G$10," ") | I21: =IF(TRIM('03. Dulieutaichinhlamsach_RG'!$G$2)="VND",'03. Dulieutaichinhlamsach_RG'!K23/10^6,'03. Dulieutaichinhlamsach_RG'!K23)
A22: 6. Dự phòng phải thu khó đòi (*) | B22: =IF(TRIM('03. Dulieutaichinhlamsach_RG'!$G$2)="VND",'03. Dulieutaichinhlamsach_RG'!D24/10^6,'03. Dulieutaichinhlamsach_RG'!D24) | C22: =IF(TRIM('03. Dulieutaichinhlamsach_RG'!$G$2)="VND",'03. Dulieutaichinhlamsach_RG'!E24/10^6,'03. Dulieutaichinhlamsach_RG'!E24) | D22: =IF(TRIM('03. Dulieutaichinhlamsach_RG'!$G$2)="VND",'03. Dulieutaichinhlamsach_RG'!F24/10^6,'03. Dulieutaichinhlamsach_RG'!F24) | E22: =IF($D$10<>0,D22/$D$10," ") | F22: =IF(C22<>0,(D22-C22)/C22,"") | G22: =IF(TRIM('03. Dulieutaichinhlamsach_RG'!$G$2)="VND",'03. Dulieutaichinhlamsach_RG'!I24/10^6,'03. Dulieutaichinhlamsach_RG'!I24) | H22: =IF($G$10<>0,G22/$G$10," ") | I22: =IF(TRIM('03. Dulieutaichinhlamsach_RG'!$G$2)="VND",'03. Dulieutaichinhlamsach_RG'!K24/10^6,'03. Dulieutaichinhlamsach_RG'!K24)
A23: IV. Hàng tồn kho | B23: =SUM(B24:B25) | C23: =SUM(C24:C25) | D23: =SUM(D24:D25) | E23: =IF($D$10<>0,D23/$D$10," ") | F23: =IF(C23<>0,(D23-C23)/C23,"") | G23: =IF(TRIM('03. Dulieutaichinhlamsach_RG'!$G$2)="VND",'03. Dulieutaichinhlamsach_RG'!I25/10^6,'03. Dulieutaichinhlamsach_RG'!I25) | H23: =IF($G$10<>0,G23/$G$10," ") | I23: =IF(TRIM('03. Dulieutaichinhlamsach_RG'!$G$2)="VND",'03. Dulieutaichinhlamsach_RG'!K25/10^6,'03. Dulieutaichinhlamsach_RG'!K25)
A24: 1. Hàng tồn kho | B24: =IF(TRIM('03. Dulieutaichinhlamsach_RG'!$G$2)="VND",'03. Dulieutaichinhlamsach_RG'!D26/10^6,'03. Dulieutaichinhlamsach_RG'!D26) | C24: =IF(TRIM('03. Dulieutaichinhlamsach_RG'!$G$2)="VND",'03. Dulieutaichinhlamsach_RG'!E26/10^6,'03. Dulieutaichinhlamsach_RG'!E26) | D24: =IF(TRIM('03. Dulieutaichinhlamsach_RG'!$G$2)="VND",'03. Dulieutaichinhlamsach_RG'!F26/10^6,'03. Dulieutaichinhlamsach_RG'!F26) | E24: =IF($D$10<>0,D24/$D$10," ") | F24: =IF(C24<>0,(D24-C24)/C24,"") | G24: =IF(TRIM('03. Dulieutaichinhlamsach_RG'!$G$2)="VND",'03. Dulieutaichinhlamsach_RG'!I26/10^6,'03. Dulieutaichinhlamsach_RG'!I26) | H24: =IF($G$10<>0,G24/$G$10," ") | I24: =IF(TRIM('03. Dulieutaichinhlamsach_RG'!$G$2)="VND",'03. Dulieutaichinhlamsach_RG'!K26/10^6,'03. Dulieutaichinhlamsach_RG'!K26)
A25: 2. Dự phòng giảm giả hàng tồn kho (*) | B25: =IF(TRIM('03. Dulieutaichinhlamsach_RG'!$G$2)="VND",'03. Dulieutaichinhlamsach_RG'!D27/10^6,'03. Dulieutaichinhlamsach_RG'!D27) | C25: =IF(TRIM('03. Dulieutaichinhlamsach_RG'!$G$2)="VND",'03. Dulieutaichinhlamsach_RG'!E27/10^6,'03. Dulieutaichinhlamsach_RG'!E27) | D25: =IF(TRIM('03. Dulieutaichinhlamsach_RG'!$G$2)="VND",'03. Dulieutaichinhlamsach_RG'!F27/10^6,'03. Dulieutaichinhlamsach_RG'!F27) | E25: =IF($D$10<>0,D25/$D$10," ") | F25: =IF(C25<>0,(D25-C25)/C25,"") | G25: =IF(TRIM('03. Dulieutaichinhlamsach_RG'!$G$2)="VND",'03. Dulieutaichinhlamsach_RG'!I27/10^6,'03. Dulieutaichinhlamsach_RG'!I27) | H25: =IF($G$10<>0,G25/$G$10," ") | I25: =IF(TRIM('03. Dulieutaichinhlamsach_RG'!$G$2)="VND",'03. Dulieutaichinhlamsach_RG'!K27/10^6,'03. Dulieutaichinhlamsach_RG'!K27)
A26: V. Tài sản cố định | B26: =SUM(B27:B28) | C26: =SUM(C27:C28) | D26: =SUM(D27:D28) | E26: =IF($D$10<>0,D26/$D$10," ") | F26: =IF(C26<>0,(D26-C26)/C26,"") | G26: =IF(TRIM('03. Dulieutaichinhlamsach_RG'!$G$2)="VND",'03. Dulieutaichinhlamsach_RG'!I28/10^6,'03. Dulieutaichinhlamsach_RG'!I28) | H26: =IF($G$10<>0,G26/$G$10," ") | I26: =IF(TRIM('03. Dulieutaichinhlamsach_RG'!$G$2)="VND",'03. Dulieutaichinhlamsach_RG'!K28/10^6,'03. Dulieutaichinhlamsach_RG'!K28)
A27: - Nguyên giá | B27: =IF(TRIM('03. Dulieutaichinhlamsach_RG'!$G$2)="VND",'03. Dulieutaichinhlamsach_RG'!D29/10^6,'03. Dulieutaichinhlamsach_RG'!D29) | C27: =IF(TRIM('03. Dulieutaichinhlamsach_RG'!$G$2)="VND",'03. Dulieutaichinhlamsach_RG'!E29/10^6,'03. Dulieutaichinhlamsach_RG'!E29) | D27: =IF(TRIM('03. Dulieutaichinhlamsach_RG'!$G$2)="VND",'03. Dulieutaichinhlamsach_RG'!F29/10^6,'03. Dulieutaichinhlamsach_RG'!F29) | E27: =IF($D$10<>0,D27/$D$10," ") | F27: =IF(C27<>0,(D27-C27)/C27,"") | G27: =IF(TRIM('03. Dulieutaichinhlamsach_RG'!$G$2)="VND",'03. Dulieutaichinhlamsach_RG'!I29/10^6,'03. Dulieutaichinhlamsach_RG'!I29) | H27: =IF($G$10<>0,G27/$G$10," ") | I27: =IF(TRIM('03. Dulieutaichinhlamsach_RG'!$G$2)="VND",'03. Dulieutaichinhlamsach_RG'!K29/10^6,'03. Dulieutaichinhlamsach_RG'!K29)
A28: - Giá trị hao mòn lũy kế | B28: =IF(TRIM('03. Dulieutaichinhlamsach_RG'!$G$2)="VND",'03. Dulieutaichinhlamsach_RG'!D30/10^6,'03. Dulieutaichinhlamsach_RG'!D30) | C28: =IF(TRIM('03. Dulieutaichinhlamsach_RG'!$G$2)="VND",'03. Dulieutaichinhlamsach_RG'!E30/10^6,'03. Dulieutaichinhlamsach_RG'!E30) | D28: =IF(TRIM('03. Dulieutaichinhlamsach_RG'!$G$2)="VND",'03. Dulieutaichinhlamsach_RG'!F30/10^6,'03. Dulieutaichinhlamsach_RG'!F30) | E28: =IF($D$10<>0,D28/$D$10," ") | F28: =IF(C28<>0,(D28-C28)/C28,"") | G28: =IF(TRIM('03. Dulieutaichinhlamsach_RG'!$G$2)="VND",'03. Dulieutaichinhlamsach_RG'!I30/10^6,'03. Dulieutaichinhlamsach_RG'!I30) | H28: =IF($G$10<>0,G28/$G$10," ") | I28: =IF(TRIM('03. Dulieutaichinhlamsach_RG'!$G$2)="VND",'03. Dulieutaichinhlamsach_RG'!K30/10^6,'03. Dulieutaichinhlamsach_RG'!K30)
A29: VI. Bất động sản đầu tư | B29: =SUM(B30:B31) | C29: =SUM(C30:C31) | D29: =SUM(D30:D31) | E29: =IF($D$10<>0,D29/$D$10," ") | F29: =IF(C29<>0,(D29-C29)/C29,"") | G29: =IF(TRIM('03. Dulieutaichinhlamsach_RG'!$G$2)="VND",'03. Dulieutaichinhlamsach_RG'!I31/10^6,'03. Dulieutaichinhlamsach_RG'!I31) | H29: =IF($G$10<>0,G29/$G$10," ") | I29: =IF(TRIM('03. Dulieutaichinhlamsach_RG'!$G$2)="VND",'03. Dulieutaichinhlamsach_RG'!K31/10^6,'03. Dulieutaichinhlamsach_RG'!K31)
A30: - Nguyên giá | B30: =IF(TRIM('03. Dulieutaichinhlamsach_RG'!$G$2)="VND",'03. Dulieutaichinhlamsach_RG'!D32/10^6,'03. Dulieutaichinhlamsach_RG'!D32) | C30: =IF(TRIM('03. Dulieutaichinhlamsach_RG'!$G$2)="VND",'03. Dulieutaichinhlamsach_RG'!E32/10^6,'03. Dulieutaichinhlamsach_RG'!E32) | D30: =IF(TRIM('03. Dulieutaichinhlamsach_RG'!$G$2)="VND",'03. Dulieutaichinhlamsach_RG'!F32/10^6,'03. Dulieutaichinhlamsach_RG'!F32) | E30: =IF($D$10<>0,D30/$D$10," ") | F30: =IF(C30<>0,(D30-C30)/C30,"") | G30: =IF(TRIM('03. Dulieutaichinhlamsach_RG'!$G$2)="VND",'03. Dulieutaichinhlamsach_RG'!I32/10^6,'03. Dulieutaichinhlamsach_RG'!I32) | H30: =IF($G$10<>0,G30/$G$10," ") | I30: =IF(TRIM('03. Dulieutaichinhlamsach_RG'!$G$2)="VND",'03. Dulieutaichinhlamsach_RG'!K32/10^6,'03. Dulieutaichinhlamsach_RG'!K32)
A31: - Giá trị hao mòn lũy kế (*) | B31: =IF(TRIM('03. Dulieutaichinhlamsach_RG'!$G$2)="VND",'03. Dulieutaichinhlamsach_RG'!D33/10^6,'03. Dulieutaichinhlamsach_RG'!D33) | C31: =IF(TRIM('03. Dulieutaichinhlamsach_RG'!$G$2)="VND",'03. Dulieutaichinhlamsach_RG'!E33/10^6,'03. Dulieutaichinhlamsach_RG'!E33) | D31: =IF(TRIM('03. Dulieutaichinhlamsach_RG'!$G$2)="VND",'03. Dulieutaichinhlamsach_RG'!F33/10^6,'03. Dulieutaichinhlamsach_RG'!F33) | E31: =IF($D$10<>0,D31/$D$10," ") | F31: =IF(C31<>0,(D31-C31)/C31,"") | G31: =IF(TRIM('03. Dulieutaichinhlamsach_RG'!$G$2)="VND",'03. Dulieutaichinhlamsach_RG'!I33/10^6,'03. Dulieutaichinhlamsach_RG'!I33) | H31: =IF($G$10<>0,G31/$G$10," ") | I31: =IF(TRIM('03. Dulieutaichinhlamsach_RG'!$G$2)="VND",'03. Dulieutaichinhlamsach_RG'!K33/10^6,'03. Dulieutaichinhlamsach_RG'!K33)
A32: VII. XDCB dở dang | B32: =IF(TRIM('03. Dulieutaichinhlamsach_RG'!$G$2)="VND",'03. Dulieutaichinhlamsach_RG'!D34/10^6,'03. Dulieutaichinhlamsach_RG'!D34) | C32: =IF(TRIM('03. Dulieutaichinhlamsach_RG'!$G$2)="VND",'03. Dulieutaichinhlamsach_RG'!E34/10^6,'03. Dulieutaichinhlamsach_RG'!E34) | D32: =IF(TRIM('03. Dulieutaichinhlamsach_RG'!$G$2)="VND",'03. Dulieutaichinhlamsach_RG'!F34/10^6,'03. Dulieutaichinhlamsach_RG'!F34) | E32: =IF($D$10<>0,D32/$D$10," ") | F32: =IF(C32<>0,(D32-C32)/C32,"") | G32: =IF(TRIM('03. Dulieutaichinhlamsach_RG'!$G$2)="VND",'03. Dulieutaichinhlamsach_RG'!I34/10^6,'03. Dulieutaichinhlamsach_RG'!I34) | H32: =IF($G$10<>0,G32/$G$10," ") | I32: =IF(TRIM('03. Dulieutaichinhlamsach_RG'!$G$2)="VND",'03. Dulieutaichinhlamsach_RG'!K34/10^6,'03. Dulieutaichinhlamsach_RG'!K34)
A33: VIII. Tài sản khác | B33: =SUM(B34:B35) | C33: =SUM(C34:C35) | D33: =SUM(D34:D35) | E33: =IF($D$10<>0,D33/$D$10," ") | F33: =IF(C33<>0,(D33-C33)/C33,"") | G33: =IF(TRIM('03. Dulieutaichinhlamsach_RG'!$G$2)="VND",'03. Dulieutaichinhlamsach_RG'!I35/10^6,'03. Dulieutaichinhlamsach_RG'!I35) | H33: =IF($G$10<>0,G33/$G$10," ") | I33: =IF(TRIM('03. Dulieutaichinhlamsach_RG'!$G$2)="VND",'03. Dulieutaichinhlamsach_RG'!K35/10^6,'03. Dulieutaichinhlamsach_RG'!K35)
A34: 1. Thuế GTGT được khấu trừ | B34: =IF(TRIM('03. Dulieutaichinhlamsach_RG'!$G$2)="VND",'03. Dulieutaichinhlamsach_RG'!D36/10^6,'03. Dulieutaichinhlamsach_RG'!D36) | C34: =IF(TRIM('03. Dulieutaichinhlamsach_RG'!$G$2)="VND",'03. Dulieutaichinhlamsach_RG'!E36/10^6,'03. Dulieutaichinhlamsach_RG'!E36) | D34: =IF(TRIM('03. Dulieutaichinhlamsach_RG'!$G$2)="VND",'03. Dulieutaichinhlamsach_RG'!F36/10^6,'03. Dulieutaichinhlamsach_RG'!F36) | E34: =IF($D$10<>0,D34/$D$10," ") | F34: =IF(C34<>0,(D34-C34)/C34,"") | G34: =IF(TRIM('03. Dulieutaichinhlamsach_RG'!$G$2)="VND",'03. Dulieutaichinhlamsach_RG'!I36/10^6,'03. Dulieutaichinhlamsach_RG'!I36) | H34: =IF($G$10<>0,G34/$G$10," ") | I34: =IF(TRIM('03. Dulieutaichinhlamsach_RG'!$G$2)="VND",'03. Dulieutaichinhlamsach_RG'!K36/10^6,'03. Dulieutaichinhlamsach_RG'!K36)
A35: 2. Tài sản khác | B35: =IF(TRIM('03. Dulieutaichinhlamsach_RG'!$G$2)="VND",'03. Dulieutaichinhlamsach_RG'!D37/10^6,'03. Dulieutaichinhlamsach_RG'!D37) | C35: =IF(TRIM('03. Dulieutaichinhlamsach_RG'!$G$2)="VND",'03. Dulieutaichinhlamsach_RG'!E37/10^6,'03. Dulieutaichinhlamsach_RG'!E37) | D35: =IF(TRIM('03. Dulieutaichinhlamsach_RG'!$G$2)="VND",'03. Dulieutaichinhlamsach_RG'!F37/10^6,'03. Dulieutaichinhlamsach_RG'!F37) | E35: =IF($D$10<>0,D35/$D$10," ") | F35: =IF(C35<>0,(D35-C35)/C35,"") | G35: =IF(TRIM('03. Dulieutaichinhlamsach_RG'!$G$2)="VND",'03. Dulieutaichinhlamsach_RG'!I37/10^6,'03. Dulieutaichinhlamsach_RG'!I37) | H35: =IF($G$10<>0,G35/$G$10," ") | I35: =IF(TRIM('03. Dulieutaichinhlamsach_RG'!$G$2)="VND",'03. Dulieutaichinhlamsach_RG'!K37/10^6,'03. Dulieutaichinhlamsach_RG'!K37)
A36: TỔNG NGUỒN VỐN | B36: =IF(TRIM('03. Dulieutaichinhlamsach_RG'!$G$2)="VND",'03. Dulieutaichinhlamsach_RG'!D38/10^6,'03. Dulieutaichinhlamsach_RG'!D38) | C36: =IF(TRIM('03. Dulieutaichinhlamsach_RG'!$G$2)="VND",'03. Dulieutaichinhlamsach_RG'!E38/10^6,'03. Dulieutaichinhlamsach_RG'!E38) | D36: =IF(TRIM('03. Dulieutaichinhlamsach_RG'!$G$2)="VND",'03. Dulieutaichinhlamsach_RG'!F38/10^6,'03. Dulieutaichinhlamsach_RG'!F38) | E36: =IF($D$10<>0,D36/$D$10," ") | F36: =IF(C36<>0,(D36-C36)/C36,"") | G36: =IF(TRIM('03. Dulieutaichinhlamsach_RG'!$G$2)="VND",'03. Dulieutaichinhlamsach_RG'!I38/10^6,'03. Dulieutaichinhlamsach_RG'!I38) | H36: =IF($G$10<>0,G36/$G$10," ") | I36: =IF(TRIM('03. Dulieutaichinhlamsach_RG'!$G$2)="VND",'03. Dulieutaichinhlamsach_RG'!K38/10^6,'03. Dulieutaichinhlamsach_RG'!K38)
A37: I. Nợ phải trả | B37: =IF(TRIM('03. Dulieutaichinhlamsach_RG'!$G$2)="VND",'03. Dulieutaichinhlamsach_RG'!D39/10^6,'03. Dulieutaichinhlamsach_RG'!D39) | C37: =IF(TRIM('03. Dulieutaichinhlamsach_RG'!$G$2)="VND",'03. Dulieutaichinhlamsach_RG'!E39/10^6,'03. Dulieutaichinhlamsach_RG'!E39) | D37: =IF(TRIM('03. Dulieutaichinhlamsach_RG'!$G$2)="VND",'03. Dulieutaichinhlamsach_RG'!F39/10^6,'03. Dulieutaichinhlamsach_RG'!F39) | E37: =IF($D$10<>0,D37/$D$10," ") | F37: =IF(C37<>0,(D37-C37)/C37,"") | G37: =IF(TRIM('03. Dulieutaichinhlamsach_RG'!$G$2)="VND",'03. Dulieutaichinhlamsach_RG'!I39/10^6,'03. Dulieutaichinhlamsach_RG'!I39) | H37: =IF($G$10<>0,G37/$G$10," ") | I37: =IF(TRIM('03. Dulieutaichinhlamsach_RG'!$G$2)="VND",'03. Dulieutaichinhlamsach_RG'!K39/10^6,'03. Dulieutaichinhlamsach_RG'!K39)
A38: 1. Phải trả người bán | B38: =IF(TRIM('03. Dulieutaichinhlamsach_RG'!$G$2)="VND",'03. Dulieutaichinhlamsach_RG'!D40/10^6,'03. Dulieutaichinhlamsach_RG'!D40) | C38: =IF(TRIM('03. Dulieutaichinhlamsach_RG'!$G$2)="VND",'03. Dulieutaichinhlamsach_RG'!E40/10^6,'03. Dulieutaichinhlamsach_RG'!E40) | D38: =IF(TRIM('03. Dulieutaichinhlamsach_RG'!$G$2)="VND",'03. Dulieutaichinhlamsach_RG'!F40/10^6,'03. Dulieutaichinhlamsach_RG'!F40) | E38: =IF($D$10<>0,D38/$D$10," ") | F38: =IF(C38<>0,(D38-C38)/C38,"") | G38: =IF(TRIM('03. Dulieutaichinhlamsach_RG'!$G$2)="VND",'03. Dulieutaichinhlamsach_RG'!I40/10^6,'03. Dulieutaichinhlamsach_RG'!I40) | H38: =IF($G$10<>0,G38/$G$10," ") | I38: =IF(TRIM('03. Dulieutaichinhlamsach_RG'!$G$2)="VND",'03. Dulieutaichinhlamsach_RG'!K40/10^6,'03. Dulieutaichinhlamsach_RG'!K40)
A39: 2. Người mua trả tiền trước | B39: =IF(TRIM('03. Dulieutaichinhlamsach_RG'!$G$2)="VND",'03. Dulieutaichinhlamsach_RG'!D41/10^6,'03. Dulieutaichinhlamsach_RG'!D41) | C39: =IF(TRIM('03. Dulieutaichinhlamsach_RG'!$G$2)="VND",'03. Dulieutaichinhlamsach_RG'!E41/10^6,'03. Dulieutaichinhlamsach_RG'!E41) | D39: =IF(TRIM('03. Dulieutaichinhlamsach_RG'!$G$2)="VND",'03. Dulieutaichinhlamsach_RG'!F41/10^6,'03. Dulieutaichinhlamsach_RG'!F41) | E39: =IF($D$10<>0,D39/$D$10," ") | F39: =IF(C39<>0,(D39-C39)/C39,"") | G39: =IF(TRIM('03. Dulieutaichinhlamsach_RG'!$G$2)="VND",'03. Dulieutaichinhlamsach_RG'!I41/10^6,'03. Dulieutaichinhlamsach_RG'!I41) | H39: =IF($G$10<>0,G39/$G$10," ") | I39: =IF(TRIM('03. Dulieutaichinhlamsach_RG'!$G$2)="VND",'03. Dulieutaichinhlamsach_RG'!K41/10^6,'03. Dulieutaichinhlamsach_RG'!K41)
A40: 3. Thuế và các khoản phải nộp Nhà nước | B40: =IF(TRIM('03. Dulieutaichinhlamsach_RG'!$G$2)="VND",'03. Dulieutaichinhlamsach_RG'!D42/10^6,'03. Dulieutaichinhlamsach_RG'!D42) | C40: =IF(TRIM('03. Dulieutaichinhlamsach_RG'!$G$2)="VND",'03. Dulieutaichinhlamsach_RG'!E42/10^6,'03. Dulieutaichinhlamsach_RG'!E42) | D40: =IF(TRIM('03. Dulieutaichinhlamsach_RG'!$G$2)="VND",'03. Dulieutaichinhlamsach_RG'!F42/10^6,'03. Dulieutaichinhlamsach_RG'!F42) | E40: =IF($D$10<>0,D40/$D$10," ") | F40: =IF(C40<>0,(D40-C40)/C40,"") | G40: =IF(TRIM('03. Dulieutaichinhlamsach_RG'!$G$2)="VND",'03. Dulieutaichinhlamsach_RG'!I42/10^6,'03. Dulieutaichinhlamsach_RG'!I42) | H40: =IF($G$10<>0,G40/$G$10," ") | I40: =IF(TRIM('03. Dulieutaichinhlamsach_RG'!$G$2)="VND",'03. Dulieutaichinhlamsach_RG'!K42/10^6,'03. Dulieutaichinhlamsach_RG'!K42)
A41: 4. Phải trả người lao động | B41: =IF(TRIM('03. Dulieutaichinhlamsach_RG'!$G$2)="VND",'03. Dulieutaichinhlamsach_RG'!D43/10^6,'03. Dulieutaichinhlamsach_RG'!D43) | C41: =IF(TRIM('03. Dulieutaichinhlamsach_RG'!$G$2)="VND",'03. Dulieutaichinhlamsach_RG'!E43/10^6,'03. Dulieutaichinhlamsach_RG'!E43) | D41: =IF(TRIM('03. Dulieutaichinhlamsach_RG'!$G$2)="VND",'03. Dulieutaichinhlamsach_RG'!F43/10^6,'03. Dulieutaichinhlamsach_RG'!F43) | E41: =IF($D$10<>0,D41/$D$10," ") | F41: =IF(C41<>0,(D41-C41)/C41,"") | G41: =IF(TRIM('03. Dulieutaichinhlamsach_RG'!$G$2)="VND",'03. Dulieutaichinhlamsach_RG'!I43/10^6,'03. Dulieutaichinhlamsach_RG'!I43) | H41: =IF($G$10<>0,G41/$G$10," ") | I41: =IF(TRIM('03. Dulieutaichinhlamsach_RG'!$G$2)="VND",'03. Dulieutaichinhlamsach_RG'!K43/10^6,'03. Dulieutaichinhlamsach_RG'!K43)
A42: 5. Phải trả khác | B42: =IF(TRIM('03. Dulieutaichinhlamsach_RG'!$G$2)="VND",'03. Dulieutaichinhlamsach_RG'!D44/10^6,'03. Dulieutaichinhlamsach_RG'!D44) | C42: =IF(TRIM('03. Dulieutaichinhlamsach_RG'!$G$2)="VND",'03. Dulieutaichinhlamsach_RG'!E44/10^6,'03. Dulieutaichinhlamsach_RG'!E44) | D42: =IF(TRIM('03. Dulieutaichinhlamsach_RG'!$G$2)="VND",'03. Dulieutaichinhlamsach_RG'!F44/10^6,'03. Dulieutaichinhlamsach_RG'!F44) | E42: =IF($D$10<>0,D42/$D$10," ") | F42: =IF(C42<>0,(D42-C42)/C42,"") | G42: =IF(TRIM('03. Dulieutaichinhlamsach_RG'!$G$2)="VND",'03. Dulieutaichinhlamsach_RG'!I44/10^6,'03. Dulieutaichinhlamsach_RG'!I44) | H42: =IF($G$10<>0,G42/$G$10," ") | I42: =IF(TRIM('03. Dulieutaichinhlamsach_RG'!$G$2)="VND",'03. Dulieutaichinhlamsach_RG'!K44/10^6,'03. Dulieutaichinhlamsach_RG'!K44)
A43: 6. Vay và nợ thuê tài chính | B43: =IF(TRIM('03. Dulieutaichinhlamsach_RG'!$G$2)="VND",'03. Dulieutaichinhlamsach_RG'!D45/10^6,'03. Dulieutaichinhlamsach_RG'!D45) | C43: =IF(TRIM('03. Dulieutaichinhlamsach_RG'!$G$2)="VND",'03. Dulieutaichinhlamsach_RG'!E45/10^6,'03. Dulieutaichinhlamsach_RG'!E45) | D43: =IF(TRIM('03. Dulieutaichinhlamsach_RG'!$G$2)="VND",'03. Dulieutaichinhlamsach_RG'!F45/10^6,'03. Dulieutaichinhlamsach_RG'!F45) | E43: =IF($D$10<>0,D43/$D$10," ") | F43: =IF(C43<>0,(D43-C43)/C43,"") | G43: =IF(TRIM('03. Dulieutaichinhlamsach_RG'!$G$2)="VND",'03. Dulieutaichinhlamsach_RG'!I45/10^6,'03. Dulieutaichinhlamsach_RG'!I45) | H43: =IF($G$10<>0,G43/$G$10," ") | I43: =IF(TRIM('03. Dulieutaichinhlamsach_RG'!$G$2)="VND",'03. Dulieutaichinhlamsach_RG'!K45/10^6,'03. Dulieutaichinhlamsach_RG'!K45)
A44: 7. Phải trả nội bộ về vốn kinh doanh | B44: =IF(TRIM('03. Dulieutaichinhlamsach_RG'!$G$2)="VND",'03. Dulieutaichinhlamsach_RG'!D46/10^6,'03. Dulieutaichinhlamsach_RG'!D46) | C44: =IF(TRIM('03. Dulieutaichinhlamsach_RG'!$G$2)="VND",'03. Dulieutaichinhlamsach_RG'!E46/10^6,'03. Dulieutaichinhlamsach_RG'!E46) | D44: =IF(TRIM('03. Dulieutaichinhlamsach_RG'!$G$2)="VND",'03. Dulieutaichinhlamsach_RG'!F46/10^6,'03. Dulieutaichinhlamsach_RG'!F46) | E44: =IF($D$10<>0,D44/$D$10," ") | F44: =IF(C44<>0,(D44-C44)/C44,"") | G44: =IF(TRIM('03. Dulieutaichinhlamsach_RG'!$G$2)="VND",'03. Dulieutaichinhlamsach_RG'!I46/10^6,'03. Dulieutaichinhlamsach_RG'!I46) | H44: =IF($G$10<>0,G44/$G$10," ") | I44: =IF(TRIM('03. Dulieutaichinhlamsach_RG'!$G$2)="VND",'03. Dulieutaichinhlamsach_RG'!K46/10^6,'03. Dulieutaichinhlamsach_RG'!K46)
A45: 8. Dự phòng phải trả | B45: =IF(TRIM('03. Dulieutaichinhlamsach_RG'!$G$2)="VND",'03. Dulieutaichinhlamsach_RG'!D47/10^6,'03. Dulieutaichinhlamsach_RG'!D47) | C45: =IF(TRIM('03. Dulieutaichinhlamsach_RG'!$G$2)="VND",'03. Dulieutaichinhlamsach_RG'!E47/10^6,'03. Dulieutaichinhlamsach_RG'!E47) | D45: =IF(TRIM('03. Dulieutaichinhlamsach_RG'!$G$2)="VND",'03. Dulieutaichinhlamsach_RG'!F47/10^6,'03. Dulieutaichinhlamsach_RG'!F47) | E45: =IF($D$10<>0,D45/$D$10," ") | F45: =IF(C45<>0,(D45-C45)/C45,"") | G45: =IF(TRIM('03. Dulieutaichinhlamsach_RG'!$G$2)="VND",'03. Dulieutaichinhlamsach_RG'!I47/10^6,'03. Dulieutaichinhlamsach_RG'!I47) | H45: =IF($G$10<>0,G45/$G$10," ") | I45: =IF(TRIM('03. Dulieutaichinhlamsach_RG'!$G$2)="VND",'03. Dulieutaichinhlamsach_RG'!K47/10^6,'03. Dulieutaichinhlamsach_RG'!K47)
A46: 9. Quỹ khen thưởng, phúc lợi | B46: =IF(TRIM('03. Dulieutaichinhlamsach_RG'!$G$2)="VND",'03. Dulieutaichinhlamsach_RG'!D48/10^6,'03. Dulieutaichinhlamsach_RG'!D48) | C46: =IF(TRIM('03. Dulieutaichinhlamsach_RG'!$G$2)="VND",'03. Dulieutaichinhlamsach_RG'!E48/10^6,'03. Dulieutaichinhlamsach_RG'!E48) | D46: =IF(TRIM('03. Dulieutaichinhlamsach_RG'!$G$2)="VND",'03. Dulieutaichinhlamsach_RG'!F48/10^6,'03. Dulieutaichinhlamsach_RG'!F48) | E46: =IF($D$10<>0,D46/$D$10," ") | F46: =IF(C46<>0,(D46-C46)/C46,"") | G46: =IF(TRIM('03. Dulieutaichinhlamsach_RG'!$G$2)="VND",'03. Dulieutaichinhlamsach_RG'!I48/10^6,'03. Dulieutaichinhlamsach_RG'!I48) | H46: =IF($G$10<>0,G46/$G$10," ") | I46: =IF(TRIM('03. Dulieutaichinhlamsach_RG'!$G$2)="VND",'03. Dulieutaichinhlamsach_RG'!K48/10^6,'03. Dulieutaichinhlamsach_RG'!K48)
A47: 10. Quỹ phát triển khoa học và công nghệ | B47: =IF(TRIM('03. Dulieutaichinhlamsach_RG'!$G$2)="VND",'03. Dulieutaichinhlamsach_RG'!D49/10^6,'03. Dulieutaichinhlamsach_RG'!D49) | C47: =IF(TRIM('03. Dulieutaichinhlamsach_RG'!$G$2)="VND",'03. Dulieutaichinhlamsach_RG'!E49/10^6,'03. Dulieutaichinhlamsach_RG'!E49) | D47: =IF(TRIM('03. Dulieutaichinhlamsach_RG'!$G$2)="VND",'03. Dulieutaichinhlamsach_RG'!F49/10^6,'03. Dulieutaichinhlamsach_RG'!F49) | E47: =IF($D$9<>0,D47/$D$9,"") | F47: =IF(C47<>0,(D47-C47)/C47,"") | G47: =IF(TRIM('03. Dulieutaichinhlamsach_RG'!$G$2)="VND",'03. Dulieutaichinhlamsach_RG'!I49/10^6,'03. Dulieutaichinhlamsach_RG'!I49) | H47: =IF($G$9<>0,G47/$G$9,"") | I47: =IF(TRIM('03. Dulieutaichinhlamsach_RG'!$G$2)="VND",'03. Dulieutaichinhlamsach_RG'!K49/10^6,'03. Dulieutaichinhlamsach_RG'!K49)
A48: II. Vốn chủ sở hữu | B48: =SUM(B49:B55) | C48: =SUM(C49:C55) | D48: =SUM(D49:D55) | E48: =IF($D$9<>0,D48/$D$9,"") | F48: =IF(C48<>0,(D48-C48)/C48,"") | G48: =IF(TRIM('03. Dulieutaichinhlamsach_RG'!$G$2)="VND",'03. Dulieutaichinhlamsach_RG'!I50/10^6,'03. Dulieutaichinhlamsach_RG'!I50) | H48: =IF($G$47<>0,G48/$G$47," ") | I48: =IF(TRIM('03. Dulieutaichinhlamsach_RG'!$G$2)="VND",'03. Dulieutaichinhlamsach_RG'!K50/10^6,'03. Dulieutaichinhlamsach_RG'!K50)
A49: 1. Vốn góp của chủ sở hữu | B49: =IF(TRIM('03. Dulieutaichinhlamsach_RG'!$G$2)="VND",'03. Dulieutaichinhlamsach_RG'!D51/10^6,'03. Dulieutaichinhlamsach_RG'!D51) | C49: =IF(TRIM('03. Dulieutaichinhlamsach_RG'!$G$2)="VND",'03. Dulieutaichinhlamsach_RG'!E51/10^6,'03. Dulieutaichinhlamsach_RG'!E51) | D49: =IF(TRIM('03. Dulieutaichinhlamsach_RG'!$G$2)="VND",'03. Dulieutaichinhlamsach_RG'!F51/10^6,'03. Dulieutaichinhlamsach_RG'!F51) | E49: =IF($D$10<>0,D49/$D$10," ") | F49: =IF(C49<>0,(D49-C49)/C49,"") | G49: =IF(TRIM('03. Dulieutaichinhlamsach_RG'!$G$2)="VND",'03. Dulieutaichinhlamsach_RG'!I51/10^6,'03. Dulieutaichinhlamsach_RG'!I51) | H49: =IF($G$10<>0,G49/$G$10," ") | I49: =IF(TRIM('03. Dulieutaichinhlamsach_RG'!$G$2)="VND",'03. Dulieutaichinhlamsach_RG'!K51/10^6,'03. Dulieutaichinhlamsach_RG'!K51)
A50: 2. Thặng dư vốn cổ phần | B50: =IF(TRIM('03. Dulieutaichinhlamsach_RG'!$G$2)="VND",'03. Dulieutaichinhlamsach_RG'!D52/10^6,'03. Dulieutaichinhlamsach_RG'!D52) | C50: =IF(TRIM('03. Dulieutaichinhlamsach_RG'!$G$2)="VND",'03. Dulieutaichinhlamsach_RG'!E52/10^6,'03. Dulieutaichinhlamsach_RG'!E52) | D50: =IF(TRIM('03. Dulieutaichinhlamsach_RG'!$G$2)="VND",'03. Dulieutaichinhlamsach_RG'!F52/10^6,'03. Dulieutaichinhlamsach_RG'!F52) | E50: =IF($D$10<>0,D50/$D$10," ") | F50: =IF(C50<>0,(D50-C50)/C50,"") | G50: =IF(TRIM('03. Dulieutaichinhlamsach_RG'!$G$2)="VND",'03. Dulieutaichinhlamsach_RG'!I52/10^6,'03. Dulieutaichinhlamsach_RG'!I52) | H50: =IF($G$10<>0,G50/$G$10," ") | I50: =IF(TRIM('03. Dulieutaichinhlamsach_RG'!$G$2)="VND",'03. Dulieutaichinhlamsach_RG'!K52/10^6,'03. Dulieutaichinhlamsach_RG'!K52)
A51: 3. Vốn khác của chủ sở hữu | B51: =IF(TRIM('03. Dulieutaichinhlamsach_RG'!$G$2)="VND",'03. Dulieutaichinhlamsach_RG'!D53/10^6,'03. Dulieutaichinhlamsach_RG'!D53) | C51: =IF(TRIM('03. Dulieutaichinhlamsach_RG'!$G$2)="VND",'03. Dulieutaichinhlamsach_RG'!E53/10^6,'03. Dulieutaichinhlamsach_RG'!E53) | D51: =IF(TRIM('03. Dulieutaichinhlamsach_RG'!$G$2)="VND",'03. Dulieutaichinhlamsach_RG'!F53/10^6,'03. Dulieutaichinhlamsach_RG'!F53) | E51: =IF($D$10<>0,D51/$D$10," ") | F51: =IF(C51<>0,(D51-C51)/C51,"") | G51: =IF(TRIM('03. Dulieutaichinhlamsach_RG'!$G$2)="VND",'03. Dulieutaichinhlamsach_RG'!I53/10^6,'03. Dulieutaichinhlamsach_RG'!I53) | H51: =IF($G$10<>0,G51/$G$10," ") | I51: =IF(TRIM('03. Dulieutaichinhlamsach_RG'!$G$2)="VND",'03. Dulieutaichinhlamsach_RG'!K53/10^6,'03. Dulieutaichinhlamsach_RG'!K53)
A52: 4. Cổ phiếu quỹ (*) | B52: =IF(TRIM('03. Dulieutaichinhlamsach_RG'!$G$2)="VND",'03. Dulieutaichinhlamsach_RG'!D54/10^6,'03. Dulieutaichinhlamsach_RG'!D54) | C52: =IF(TRIM('03. Dulieutaichinhlamsach_RG'!$G$2)="VND",'03. Dulieutaichinhlamsach_RG'!E54/10^6,'03. Dulieutaichinhlamsach_RG'!E54) | D52: =IF(TRIM('03. Dulieutaichinhlamsach_RG'!$G$2)="VND",'03. Dulieutaichinhlamsach_RG'!F54/10^6,'03. Dulieutaichinhlamsach_RG'!F54) | E52: =IF($D$10<>0,D52/$D$10," ") | F52: =IF(C52<>0,(D52-C52)/C52,"") | G52: =IF(TRIM('03. Dulieutaichinhlamsach_RG'!$G$2)="VND",'03. Dulieutaichinhlamsach_RG'!I54/10^6,'03. Dulieutaichinhlamsach_RG'!I54) | H52: =IF($G$10<>0,G52/$G$10," ") | I52: =IF(TRIM('03. Dulieutaichinhlamsach_RG'!$G$2)="VND",'03. Dulieutaichinhlamsach_RG'!K54/10^6,'03. Dulieutaichinhlamsach_RG'!K54)
A53: 5. Chênh lệch tỷ giá hối đoái | B53: =IF(TRIM('03. Dulieutaichinhlamsach_RG'!$G$2)="VND",'03. Dulieutaichinhlamsach_RG'!D55/10^6,'03. Dulieutaichinhlamsach_RG'!D55) | C53: =IF(TRIM('03. Dulieutaichinhlamsach_RG'!$G$2)="VND",'03. Dulieutaichinhlamsach_RG'!E55/10^6,'03. Dulieutaichinhlamsach_RG'!E55) | D53: =IF(TRIM('03. Dulieutaichinhlamsach_RG'!$G$2)="VND",'03. Dulieutaichinhlamsach_RG'!F55/10^6,'03. Dulieutaichinhlamsach_RG'!F55) | E53: =IF($D$10<>0,D53/$D$10," ") | F53: =IF(C53<>0,(D53-C53)/C53,"") | G53: =IF(TRIM('03. Dulieutaichinhlamsach_RG'!$G$2)="VND",'03. Dulieutaichinhlamsach_RG'!I55/10^6,'03. Dulieutaichinhlamsach_RG'!I55) | H53: =IF($G$10<>0,G53/$G$10," ") | I53: =IF(TRIM('03. Dulieutaichinhlamsach_RG'!$G$2)="VND",'03. Dulieutaichinhlamsach_RG'!K55/10^6,'03. Dulieutaichinhlamsach_RG'!K55)
A54: 6. Các quỹ thuộc vốn chủ sở hữu | B54: =IF(TRIM('03. Dulieutaichinhlamsach_RG'!$G$2)="VND",'03. Dulieutaichinhlamsach_RG'!D56/10^6,'03. Dulieutaichinhlamsach_RG'!D56) | C54: =IF(TRIM('03. Dulieutaichinhlamsach_RG'!$G$2)="VND",'03. Dulieutaichinhlamsach_RG'!E56/10^6,'03. Dulieutaichinhlamsach_RG'!E56) | D54: =IF(TRIM('03. Dulieutaichinhlamsach_RG'!$G$2)="VND",'03. Dulieutaichinhlamsach_RG'!F56/10^6,'03. Dulieutaichinhlamsach_RG'!F56) | E54: =IF($D$47<>0,D54/$D$47," ") | F54: =IF(C54<>0,(D54-C54)/C54,"") | G54: =IF(TRIM('03. Dulieutaichinhlamsach_RG'!$G$2)="VND",'03. Dulieutaichinhlamsach_RG'!I56/10^6,'03. Dulieutaichinhlamsach_RG'!I56) | H54: =IF($G$47<>0,G54/$G$47," ") | I54: =IF(TRIM('03. Dulieutaichinhlamsach_RG'!$G$2)="VND",'03. Dulieutaichinhlamsach_RG'!K56/10^6,'03. Dulieutaichinhlamsach_RG'!K56)
A55: 7. Lợi nhuận sau thuế chưa phân phối | B55: =IF(TRIM('03. Dulieutaichinhlamsach_RG'!$G$2)="VND",'03. Dulieutaichinhlamsach_RG'!D57/10^6,'03. Dulieutaichinhlamsach_RG'!D57) | C55: =IF(TRIM('03. Dulieutaichinhlamsach_RG'!$G$2)="VND",'03. Dulieutaichinhlamsach_RG'!E57/10^6,'03. Dulieutaichinhlamsach_RG'!E57) | D55: =IF(TRIM('03. Dulieutaichinhlamsach_RG'!$G$2)="VND",'03. Dulieutaichinhlamsach_RG'!F57/10^6,'03. Dulieutaichinhlamsach_RG'!F57) | E55: =IF($D$10<>0,D55/$D$10," ") | F55: =IF(C55<>0,(D55-C55)/C55,"") | G55: =IF(TRIM('03. Dulieutaichinhlamsach_RG'!$G$2)="VND",'03. Dulieutaichinhlamsach_RG'!I57/10^6,'03. Dulieutaichinhlamsach_RG'!I57) | H55: =IF($G$10<>0,G55/$G$10," ") | I55: =IF(TRIM('03. Dulieutaichinhlamsach_RG'!$G$2)="VND",'03. Dulieutaichinhlamsach_RG'!K57/10^6,'03. Dulieutaichinhlamsach_RG'!K57)
A56: Phần III: KẾT QUẢ KINH DOANH | B56: =$B$7 | C56: =$C$7 | D56: =$D$7 | F56: ="T/G "&D56 | G56: =G7 | I56: =I7
A57: Doanh thu bán hàng và cung cấp dịch vụ | B57: =IF(TRIM('03. Dulieutaichinhlamsach_RG'!$G$2)="VND",'03. Dulieutaichinhlamsach_RG'!D72/10^6,'03. Dulieutaichinhlamsach_RG'!D72) | C57: =IF(TRIM('03. Dulieutaichinhlamsach_RG'!$G$2)="VND",'03. Dulieutaichinhlamsach_RG'!E72/10^6,'03. Dulieutaichinhlamsach_RG'!E72) | D57: =IF(TRIM('03. Dulieutaichinhlamsach_RG'!$G$2)="VND",'03. Dulieutaichinhlamsach_RG'!F72/10^6,'03. Dulieutaichinhlamsach_RG'!F72) | F57: =IF(C57="","",IF(C57<>0,(D57-C57)/C57,"")) | G57: =IF(TRIM('03. Dulieutaichinhlamsach_RG'!$G$2)="VND",'03. Dulieutaichinhlamsach_RG'!I72/10^6,'03. Dulieutaichinhlamsach_RG'!I72) | I57: =IF(TRIM('03. Dulieutaichinhlamsach_RG'!$G$2)="VND",'03. Dulieutaichinhlamsach_RG'!K72/10^6,'03. Dulieutaichinhlamsach_RG'!K72)
A58: Các khoản giảm trừ doanh thu | B58: =IF(TRIM('03. Dulieutaichinhlamsach_RG'!$G$2)="VND",'03. Dulieutaichinhlamsach_RG'!D73/10^6,'03. Dulieutaichinhlamsach_RG'!D73) | C58: =IF(TRIM('03. Dulieutaichinhlamsach_RG'!$G$2)="VND",'03. Dulieutaichinhlamsach_RG'!E73/10^6,'03. Dulieutaichinhlamsach_RG'!E73) | D58: =IF(TRIM('03. Dulieutaichinhlamsach_RG'!$G$2)="VND",'03. Dulieutaichinhlamsach_RG'!F73/10^6,'03. Dulieutaichinhlamsach_RG'!F73) | F58: =IF(C58<>0,(D58-C58)/C58,"") | G58: =IF(TRIM('03. Dulieutaichinhlamsach_RG'!$G$2)="VND",'03. Dulieutaichinhlamsach_RG'!I73/10^6,'03. Dulieutaichinhlamsach_RG'!I73) | I58: =IF(TRIM('03. Dulieutaichinhlamsach_RG'!$G$2)="VND",'03. Dulieutaichinhlamsach_RG'!K73/10^6,'03. Dulieutaichinhlamsach_RG'!K73)
A59: - Chiết khấu | B59: =IF(TRIM('03. Dulieutaichinhlamsach_RG'!$G$2)="VND",'03. Dulieutaichinhlamsach_RG'!D74/10^6,'03. Dulieutaichinhlamsach_RG'!D74) | C59: =IF(TRIM('03. Dulieutaichinhlamsach_RG'!$G$2)="VND",'03. Dulieutaichinhlamsach_RG'!E74/10^6,'03. Dulieutaichinhlamsach_RG'!E74) | D59: =IF(TRIM('03. Dulieutaichinhlamsach_RG'!$G$2)="VND",'03. Dulieutaichinhlamsach_RG'!F74/10^6,'03. Dulieutaichinhlamsach_RG'!F74) | F59: =IF(C59<>0,(D59-C59)/C59,"") | G59: =IF(TRIM('03. Dulieutaichinhlamsach_RG'!$G$2)="VND",'03. Dulieutaichinhlamsach_RG'!I74/10^6,'03. Dulieutaichinhlamsach_RG'!I74) | I59: =IF(TRIM('03. Dulieutaichinhlamsach_RG'!$G$2)="VND",'03. Dulieutaichinhlamsach_RG'!K74/10^6,'03. Dulieutaichinhlamsach_RG'!K74)
A60: - Giảm giá | B60: =IF(TRIM('03. Dulieutaichinhlamsach_RG'!$G$2)="VND",'03. Dulieutaichinhlamsach_RG'!D75/10^6,'03. Dulieutaichinhlamsach_RG'!D75) | C60: =IF(TRIM('03. Dulieutaichinhlamsach_RG'!$G$2)="VND",'03. Dulieutaichinhlamsach_RG'!E75/10^6,'03. Dulieutaichinhlamsach_RG'!E75) | D60: =IF(TRIM('03. Dulieutaichinhlamsach_RG'!$G$2)="VND",'03. Dulieutaichinhlamsach_RG'!F75/10^6,'03. Dulieutaichinhlamsach_RG'!F75) | F60: =IF(C60<>0,(D60-C60)/C60,"") | G60: =IF(TRIM('03. Dulieutaichinhlamsach_RG'!$G$2)="VND",'03. Dulieutaichinhlamsach_RG'!I75/10^6,'03. Dulieutaichinhlamsach_RG'!I75) | I60: =IF(TRIM('03. Dulieutaichinhlamsach_RG'!$G$2)="VND",'03. Dulieutaichinhlamsach_RG'!K75/10^6,'03. Dulieutaichinhlamsach_RG'!K75)
A61: - Hàng bán bị trả lại | B61: =IF(TRIM('03. Dulieutaichinhlamsach_RG'!$G$2)="VND",'03. Dulieutaichinhlamsach_RG'!D76/10^6,'03. Dulieutaichinhlamsach_RG'!D76) | C61: =IF(TRIM('03. Dulieutaichinhlamsach_RG'!$G$2)="VND",'03. Dulieutaichinhlamsach_RG'!E76/10^6,'03. Dulieutaichinhlamsach_RG'!E76) | D61: =IF(TRIM('03. Dulieutaichinhlamsach_RG'!$G$2)="VND",'03. Dulieutaichinhlamsach_RG'!F76/10^6,'03. Dulieutaichinhlamsach_RG'!F76) | F61: =IF(C61<>0,(D61-C61)/C61,"") | G61: =IF(TRIM('03. Dulieutaichinhlamsach_RG'!$G$2)="VND",'03. Dulieutaichinhlamsach_RG'!I76/10^6,'03. Dulieutaichinhlamsach_RG'!I76) | I61: =IF(TRIM('03. Dulieutaichinhlamsach_RG'!$G$2)="VND",'03. Dulieutaichinhlamsach_RG'!K76/10^6,'03. Dulieutaichinhlamsach_RG'!K76)
A62: - Thuế VAT, thuế xuất khẩu | B62: =IF(TRIM('03. Dulieutaichinhlamsach_RG'!$G$2)="VND",'03. Dulieutaichinhlamsach_RG'!D77/10^6,'03. Dulieutaichinhlamsach_RG'!D77) | C62: =IF(TRIM('03. Dulieutaichinhlamsach_RG'!$G$2)="VND",'03. Dulieutaichinhlamsach_RG'!E77/10^6,'03. Dulieutaichinhlamsach_RG'!E77) | D62: =IF(TRIM('03. Dulieutaichinhlamsach_RG'!$G$2)="VND",'03. Dulieutaichinhlamsach_RG'!F77/10^6,'03. Dulieutaichinhlamsach_RG'!F77) | F62: =IF(C62<>0,(D62-C62)/C62,"") | G62: =IF(TRIM('03. Dulieutaichinhlamsach_RG'!$G$2)="VND",'03. Dulieutaichinhlamsach_RG'!I77/10^6,'03. Dulieutaichinhlamsach_RG'!I77) | I62: =IF(TRIM('03. Dulieutaichinhlamsach_RG'!$G$2)="VND",'03. Dulieutaichinhlamsach_RG'!K77/10^6,'03. Dulieutaichinhlamsach_RG'!K77)
A63: Doanh thu thuần về bán hàng và cung cấp dịch vụ | B63: =IF(TRIM('03. Dulieutaichinhlamsach_RG'!$G$2)="VND",'03. Dulieutaichinhlamsach_RG'!D78/10^6,'03. Dulieutaichinhlamsach_RG'!D78) | C63: =IF(TRIM('03. Dulieutaichinhlamsach_RG'!$G$2)="VND",'03. Dulieutaichinhlamsach_RG'!E78/10^6,'03. Dulieutaichinhlamsach_RG'!E78) | D63: =IF(TRIM('03. Dulieutaichinhlamsach_RG'!$G$2)="VND",'03. Dulieutaichinhlamsach_RG'!F78/10^6,'03. Dulieutaichinhlamsach_RG'!F78) | F63: =IF(C63="","",IF(C63<>0,(D63-C63)/C63,"")) | G63: =IF(TRIM('03. Dulieutaichinhlamsach_RG'!$G$2)="VND",'03. Dulieutaichinhlamsach_RG'!I78/10^6,'03. Dulieutaichinhlamsach_RG'!I78) | I63: =IF(TRIM('03. Dulieutaichinhlamsach_RG'!$G$2)="VND",'03. Dulieutaichinhlamsach_RG'!K78/10^6,'03. Dulieutaichinhlamsach_RG'!K78)
A64: Giá vốn hàng bán | B64: =IF(TRIM('03. Dulieutaichinhlamsach_RG'!$G$2)="VND",'03. Dulieutaichinhlamsach_RG'!D79/10^6,'03. Dulieutaichinhlamsach_RG'!D79) | C64: =IF(TRIM('03. Dulieutaichinhlamsach_RG'!$G$2)="VND",'03. Dulieutaichinhlamsach_RG'!E79/10^6,'03. Dulieutaichinhlamsach_RG'!E79) | D64: =IF(TRIM('03. Dulieutaichinhlamsach_RG'!$G$2)="VND",'03. Dulieutaichinhlamsach_RG'!F79/10^6,'03. Dulieutaichinhlamsach_RG'!F79) | F64: =IF(C64<>0,(D64-C64)/C64,"") | G64: =IF(TRIM('03. Dulieutaichinhlamsach_RG'!$G$2)="VND",'03. Dulieutaichinhlamsach_RG'!I79/10^6,'03. Dulieutaichinhlamsach_RG'!I79) | I64: =IF(TRIM('03. Dulieutaichinhlamsach_RG'!$G$2)="VND",'03. Dulieutaichinhlamsach_RG'!K79/10^6,'03. Dulieutaichinhlamsach_RG'!K79)
A65: - Tr/đó: Khấu hao trong giá vốn hàng bán | B65: =IF(TRIM('03. Dulieutaichinhlamsach_RG'!$G$2)="VND",'03. Dulieutaichinhlamsach_RG'!D80/10^6,'03. Dulieutaichinhlamsach_RG'!D80) | C65: =IF(TRIM('03. Dulieutaichinhlamsach_RG'!$G$2)="VND",'03. Dulieutaichinhlamsach_RG'!E80/10^6,'03. Dulieutaichinhlamsach_RG'!E80) | D65: =IF(TRIM('03. Dulieutaichinhlamsach_RG'!$G$2)="VND",'03. Dulieutaichinhlamsach_RG'!F80/10^6,'03. Dulieutaichinhlamsach_RG'!F80) | F65: =IF(C65<>0,(D65-C65)/C65,"") | G65: =IF(TRIM('03. Dulieutaichinhlamsach_RG'!$G$2)="VND",'03. Dulieutaichinhlamsach_RG'!I80/10^6,'03. Dulieutaichinhlamsach_RG'!I80) | I65: =IF(TRIM('03. Dulieutaichinhlamsach_RG'!$G$2)="VND",'03. Dulieutaichinhlamsach_RG'!H80/10^6,'03. Dulieutaichinhlamsach_RG'!H80)
A66: Lợi nhuận gộp về bán hàng và cung cấp dịch vụ | B66: =IF(TRIM('03. Dulieutaichinhlamsach_RG'!$G$2)="VND",'03. Dulieutaichinhlamsach_RG'!D81/10^6,'03. Dulieutaichinhlamsach_RG'!D81) | C66: =IF(TRIM('03. Dulieutaichinhlamsach_RG'!$G$2)="VND",'03. Dulieutaichinhlamsach_RG'!E81/10^6,'03. Dulieutaichinhlamsach_RG'!E81) | D66: =IF(TRIM('03. Dulieutaichinhlamsach_RG'!$G$2)="VND",'03. Dulieutaichinhlamsach_RG'!F81/10^6,'03. Dulieutaichinhlamsach_RG'!F81) | F66: =IF(C66="","",IF(C66<>0,(D66-C66)/C66,"")) | G66: =IF(TRIM('03. Dulieutaichinhlamsach_RG'!$G$2)="VND",'03. Dulieutaichinhlamsach_RG'!I81/10^6,'03. Dulieutaichinhlamsach_RG'!I81) | I66: =IF(TRIM('03. Dulieutaichinhlamsach_RG'!$G$2)="VND",'03. Dulieutaichinhlamsach_RG'!H81/10^6,'03. Dulieutaichinhlamsach_RG'!H81)
A67: Doanh thu hoạt động tài chính | B67: =IF(TRIM('03. Dulieutaichinhlamsach_RG'!$G$2)="VND",'03. Dulieutaichinhlamsach_RG'!D82/10^6,'03. Dulieutaichinhlamsach_RG'!D82) | C67: =IF(TRIM('03. Dulieutaichinhlamsach_RG'!$G$2)="VND",'03. Dulieutaichinhlamsach_RG'!E82/10^6,'03. Dulieutaichinhlamsach_RG'!E82) | D67: =IF(TRIM('03. Dulieutaichinhlamsach_RG'!$G$2)="VND",'03. Dulieutaichinhlamsach_RG'!F82/10^6,'03. Dulieutaichinhlamsach_RG'!F82) | F67: =IF(C67<>0,(D67-C67)/C67,"") | G67: =IF(TRIM('03. Dulieutaichinhlamsach_RG'!$G$2)="VND",'03. Dulieutaichinhlamsach_RG'!I82/10^6,'03. Dulieutaichinhlamsach_RG'!I82) | I67: =IF(TRIM('03. Dulieutaichinhlamsach_RG'!$G$2)="VND",'03. Dulieutaichinhlamsach_RG'!H82/10^6,'03. Dulieutaichinhlamsach_RG'!H82)
A68: Chi phí tài chính | B68: =IF(TRIM('03. Dulieutaichinhlamsach_RG'!$G$2)="VND",'03. Dulieutaichinhlamsach_RG'!D83/10^6,'03. Dulieutaichinhlamsach_RG'!D83) | C68: =IF(TRIM('03. Dulieutaichinhlamsach_RG'!$G$2)="VND",'03. Dulieutaichinhlamsach_RG'!E83/10^6,'03. Dulieutaichinhlamsach_RG'!E83) | D68: =IF(TRIM('03. Dulieutaichinhlamsach_RG'!$G$2)="VND",'03. Dulieutaichinhlamsach_RG'!F83/10^6,'03. Dulieutaichinhlamsach_RG'!F83) | F68: =IF(C68<>0,(D68-C68)/C68,"") | G68: =IF(TRIM('03. Dulieutaichinhlamsach_RG'!$G$2)="VND",'03. Dulieutaichinhlamsach_RG'!I83/10^6,'03. Dulieutaichinhlamsach_RG'!I83) | I68: =IF(TRIM('03. Dulieutaichinhlamsach_RG'!$G$2)="VND",'03. Dulieutaichinhlamsach_RG'!H83/10^6,'03. Dulieutaichinhlamsach_RG'!H83)
A69: - Tr/đó: Chi phí lãi vay | B69: =IF(TRIM('03. Dulieutaichinhlamsach_RG'!$G$2)="VND",'03. Dulieutaichinhlamsach_RG'!D84/10^6,'03. Dulieutaichinhlamsach_RG'!D84) | C69: =IF(TRIM('03. Dulieutaichinhlamsach_RG'!$G$2)="VND",'03. Dulieutaichinhlamsach_RG'!E84/10^6,'03. Dulieutaichinhlamsach_RG'!E84) | D69: =IF(TRIM('03. Dulieutaichinhlamsach_RG'!$G$2)="VND",'03. Dulieutaichinhlamsach_RG'!F84/10^6,'03. Dulieutaichinhlamsach_RG'!F84) | F69: =IF(C69<>0,(D69-C69)/C69,"") | G69: =IF(TRIM('03. Dulieutaichinhlamsach_RG'!$G$2)="VND",'03. Dulieutaichinhlamsach_RG'!I84/10^6,'03. Dulieutaichinhlamsach_RG'!I84) | I69: =IF(TRIM('03. Dulieutaichinhlamsach_RG'!$G$2)="VND",'03. Dulieutaichinhlamsach_RG'!H84/10^6,'03. Dulieutaichinhlamsach_RG'!H84)
A70: Chi phí quản lý kinh doanh | B70: =IF(TRIM('03. Dulieutaichinhlamsach_RG'!$G$2)="VND",'03. Dulieutaichinhlamsach_RG'!D85/10^6,'03. Dulieutaichinhlamsach_RG'!D85) | C70: =IF(TRIM('03. Dulieutaichinhlamsach_RG'!$G$2)="VND",'03. Dulieutaichinhlamsach_RG'!E85/10^6,'03. Dulieutaichinhlamsach_RG'!E85) | D70: =IF(TRIM('03. Dulieutaichinhlamsach_RG'!$G$2)="VND",'03. Dulieutaichinhlamsach_RG'!F85/10^6,'03. Dulieutaichinhlamsach_RG'!F85) | F70: =IF(C70<>0,(D70-C70)/C70,"") | G70: =IF(TRIM('03. Dulieutaichinhlamsach_RG'!$G$2)="VND",'03. Dulieutaichinhlamsach_RG'!I85/10^6,'03. Dulieutaichinhlamsach_RG'!I85) | I70: =IF(TRIM('03. Dulieutaichinhlamsach_RG'!$G$2)="VND",'03. Dulieutaichinhlamsach_RG'!H85/10^6,'03. Dulieutaichinhlamsach_RG'!H85)
A71: Lợi nhuận thuần từ HĐKD | B71: =IF(TRIM('03. Dulieutaichinhlamsach_RG'!$G$2)="VND",'03. Dulieutaichinhlamsach_RG'!D86/10^6,'03. Dulieutaichinhlamsach_RG'!D86) | C71: =IF(TRIM('03. Dulieutaichinhlamsach_RG'!$G$2)="VND",'03. Dulieutaichinhlamsach_RG'!E86/10^6,'03. Dulieutaichinhlamsach_RG'!E86) | D71: =IF(TRIM('03. Dulieutaichinhlamsach_RG'!$G$2)="VND",'03. Dulieutaichinhlamsach_RG'!F86/10^6,'03. Dulieutaichinhlamsach_RG'!F86) | F71: =IF(C71="","",IF(C71<>0,(D71-C71)/C71,"")) | G71: =IF(TRIM('03. Dulieutaichinhlamsach_RG'!$G$2)="VND",'03. Dulieutaichinhlamsach_RG'!I86/10^6,'03. Dulieutaichinhlamsach_RG'!I86) | I71: =IF(TRIM('03. Dulieutaichinhlamsach_RG'!$G$2)="VND",'03. Dulieutaichinhlamsach_RG'!H86/10^6,'03. Dulieutaichinhlamsach_RG'!H86)
A72: Thu nhập khác | B72: =IF(TRIM('03. Dulieutaichinhlamsach_RG'!$G$2)="VND",'03. Dulieutaichinhlamsach_RG'!D87/10^6,'03. Dulieutaichinhlamsach_RG'!D87) | C72: =IF(TRIM('03. Dulieutaichinhlamsach_RG'!$G$2)="VND",'03. Dulieutaichinhlamsach_RG'!E87/10^6,'03. Dulieutaichinhlamsach_RG'!E87) | D72: =IF(TRIM('03. Dulieutaichinhlamsach_RG'!$G$2)="VND",'03. Dulieutaichinhlamsach_RG'!F87/10^6,'03. Dulieutaichinhlamsach_RG'!F87) | F72: =IF(C72<>0,(D72-C72)/C72,"") | G72: =IF(TRIM('03. Dulieutaichinhlamsach_RG'!$G$2)="VND",'03. Dulieutaichinhlamsach_RG'!I87/10^6,'03. Dulieutaichinhlamsach_RG'!I87) | I72: =IF(TRIM('03. Dulieutaichinhlamsach_RG'!$G$2)="VND",'03. Dulieutaichinhlamsach_RG'!H87/10^6,'03. Dulieutaichinhlamsach_RG'!H87)
A73: Chi phí khác | B73: =IF(TRIM('03. Dulieutaichinhlamsach_RG'!$G$2)="VND",'03. Dulieutaichinhlamsach_RG'!D88/10^6,'03. Dulieutaichinhlamsach_RG'!D88) | C73: =IF(TRIM('03. Dulieutaichinhlamsach_RG'!$G$2)="VND",'03. Dulieutaichinhlamsach_RG'!E88/10^6,'03. Dulieutaichinhlamsach_RG'!E88) | D73: =IF(TRIM('03. Dulieutaichinhlamsach_RG'!$G$2)="VND",'03. Dulieutaichinhlamsach_RG'!F88/10^6,'03. Dulieutaichinhlamsach_RG'!F88) | F73: =IF(C73<>0,(D73-C73)/C73,"") | G73: =IF(TRIM('03. Dulieutaichinhlamsach_RG'!$G$2)="VND",'03. Dulieutaichinhlamsach_RG'!I88/10^6,'03. Dulieutaichinhlamsach_RG'!I88) | I73: =IF(TRIM('03. Dulieutaichinhlamsach_RG'!$G$2)="VND",'03. Dulieutaichinhlamsach_RG'!H88/10^6,'03. Dulieutaichinhlamsach_RG'!H88)
A74: Lợi nhuận khác | B74: =IF(TRIM('03. Dulieutaichinhlamsach_RG'!$G$2)="VND",'03. Dulieutaichinhlamsach_RG'!D89/10^6,'03. Dulieutaichinhlamsach_RG'!D89) | C74: =IF(TRIM('03. Dulieutaichinhlamsach_RG'!$G$2)="VND",'03. Dulieutaichinhlamsach_RG'!E89/10^6,'03. Dulieutaichinhlamsach_RG'!E89) | D74: =IF(TRIM('03. Dulieutaichinhlamsach_RG'!$G$2)="VND",'03. Dulieutaichinhlamsach_RG'!F89/10^6,'03. Dulieutaichinhlamsach_RG'!F89) | F74: =IF(C74<>0,(D74-C74)/C74,"") | G74: =IF(TRIM('03. Dulieutaichinhlamsach_RG'!$G$2)="VND",'03. Dulieutaichinhlamsach_RG'!I89/10^6,'03. Dulieutaichinhlamsach_RG'!I89) | I74: =IF(TRIM('03. Dulieutaichinhlamsach_RG'!$G$2)="VND",'03. Dulieutaichinhlamsach_RG'!H89/10^6,'03. Dulieutaichinhlamsach_RG'!H89)
A75: Tổng lợi nhuận kế toán trước thuế | B75: =IF(TRIM('03. Dulieutaichinhlamsach_RG'!$G$2)="VND",'03. Dulieutaichinhlamsach_RG'!D90/10^6,'03. Dulieutaichinhlamsach_RG'!D90) | C75: =IF(TRIM('03. Dulieutaichinhlamsach_RG'!$G$2)="VND",'03. Dulieutaichinhlamsach_RG'!E90/10^6,'03. Dulieutaichinhlamsach_RG'!E90) | D75: =IF(TRIM('03. Dulieutaichinhlamsach_RG'!$G$2)="VND",'03. Dulieutaichinhlamsach_RG'!F90/10^6,'03. Dulieutaichinhlamsach_RG'!F90) | F75: =IF(C75="","",IF(C75<>0,(D75-C75)/C75,"")) | G75: =IF(TRIM('03. Dulieutaichinhlamsach_RG'!$G$2)="VND",'03. Dulieutaichinhlamsach_RG'!I90/10^6,'03. Dulieutaichinhlamsach_RG'!I90) | I75: =IF(TRIM('03. Dulieutaichinhlamsach_RG'!$G$2)="VND",'03. Dulieutaichinhlamsach_RG'!H90/10^6,'03. Dulieutaichinhlamsach_RG'!H90)
A76: Chi phí thuế TNDN | B76: =IF(TRIM('03. Dulieutaichinhlamsach_RG'!$G$2)="VND",'03. Dulieutaichinhlamsach_RG'!D91/10^6,'03. Dulieutaichinhlamsach_RG'!D91) | C76: =IF(TRIM('03. Dulieutaichinhlamsach_RG'!$G$2)="VND",'03. Dulieutaichinhlamsach_RG'!E91/10^6,'03. Dulieutaichinhlamsach_RG'!E91) | D76: =IF(TRIM('03. Dulieutaichinhlamsach_RG'!$G$2)="VND",'03. Dulieutaichinhlamsach_RG'!F91/10^6,'03. Dulieutaichinhlamsach_RG'!F91) | F76: =IF(C76<>0,(D76-C76)/C76,"") | G76: =IF(TRIM('03. Dulieutaichinhlamsach_RG'!$G$2)="VND",'03. Dulieutaichinhlamsach_RG'!I91/10^6,'03. Dulieutaichinhlamsach_RG'!I91) | I76: =IF(TRIM('03. Dulieutaichinhlamsach_RG'!$G$2)="VND",'03. Dulieutaichinhlamsach_RG'!H91/10^6,'03. Dulieutaichinhlamsach_RG'!H91)
A77: Lợi nhuận sau thuế TNDN | B77: =IF(TRIM('03. Dulieutaichinhlamsach_RG'!$G$2)="VND",'03. Dulieutaichinhlamsach_RG'!D92/10^6,'03. Dulieutaichinhlamsach_RG'!D92) | C77: =IF(TRIM('03. Dulieutaichinhlamsach_RG'!$G$2)="VND",'03. Dulieutaichinhlamsach_RG'!E92/10^6,'03. Dulieutaichinhlamsach_RG'!E92) | D77: =IF(TRIM('03. Dulieutaichinhlamsach_RG'!$G$2)="VND",'03. Dulieutaichinhlamsach_RG'!F92/10^6,'03. Dulieutaichinhlamsach_RG'!F92) | F77: =IF(C77="","",IF(C77<>0,(D77-C77)/C77,"")) | G77: =IF(TRIM('03. Dulieutaichinhlamsach_RG'!$G$2)="VND",'03. Dulieutaichinhlamsach_RG'!I92/10^6,'03. Dulieutaichinhlamsach_RG'!I92) | I77: =IF(TRIM('03. Dulieutaichinhlamsach_RG'!$G$2)="VND",'03. Dulieutaichinhlamsach_RG'!H92/10^6,'03. Dulieutaichinhlamsach_RG'!H92)
A78: Lãi cơ bản trên cổ phiếu | B78: =IF(TRIM('03. Dulieutaichinhlamsach_RG'!$G$2)="VND",'03. Dulieutaichinhlamsach_RG'!D97/10^6,'03. Dulieutaichinhlamsach_RG'!D97) | C78: =IF(TRIM('03. Dulieutaichinhlamsach_RG'!$G$2)="VND",'03. Dulieutaichinhlamsach_RG'!E97/10^6,'03. Dulieutaichinhlamsach_RG'!E97) | D78: =IF(TRIM('03. Dulieutaichinhlamsach_RG'!$G$2)="VND",'03. Dulieutaichinhlamsach_RG'!F97/10^6,'03. Dulieutaichinhlamsach_RG'!F97) | G78: =IF(TRIM('03. Dulieutaichinhlamsach_RG'!$G$2)="VND",'03. Dulieutaichinhlamsach_RG'!G93/10^6,'03. Dulieutaichinhlamsach_RG'!G93) | I78: =IF(TRIM('03. Dulieutaichinhlamsach_RG'!$G$2)="VND",'03. Dulieutaichinhlamsach_RG'!H93/10^6,'03. Dulieutaichinhlamsach_RG'!H93)
A80: THÔNG TIN CƠ BẢN phục vụ thông tin trang 1 tờ trình | E80: =C68+C75 | G80: NHẬP ĐIỀU CHỈNH! (NẾU CÓ) | I80: CÁC CHỈ SỐ TÀI CHÍNH ĐIỀU CHỈNH CHO CSC (NĂM GẦN NHẤT)
I81: Các tham số điều chỉnh (chỉ nhập theo đơn vị Triệu đồng)
B82: =B7 | C82: =C7 | D82: =D7 | E82: =G7 | F82: =I7 | I82: Nợ phải trả | J82: =D37
I83: Nợ ngắn hạn | K83: ko áp dụng
A84: Tổng Doanh thu | B84: =B57 | C84: =C57 | D84: =D57 | E84: =G57 | F84: =I57 | I84: Nợ vay ngắn hạn | K84: ko áp dụng
A85: Tổng tài sản | B85: =B9 | C85: =C9 | D85: =D9 | E85: =G9 | F85: =I9 | I85: Vốn chủ sở hữu | J85: =D48
A86: Vốn CSH | B86: =B48 | C86: =C48 | D86: =D48 | E86: =G48 | F86: =I48 | I86: Lợi nhuận sản xuất kinh doanh | J86: =$E$142
A87: Lợi nhuận sau thuế | B87: =B77 | C87: =C77 | D87: =D77 | E87: =G77 | F87: =I77 | I87: Lợi nhuận sau thuế | J87: =$D$77
A88: Tổng vay và nợ ngắn + dài hạn | B88: =B43 | C88: =C43 | D88: =D43 | E88: =G43 | F88: =I43 | I88: Phải thu ngắn hạn khách hàng
A89: Hệ số đòn bẩy (lần) | B89: =$C$139 | C89: =$D$139 | D89: =$E$139 | E89: =$H$139 | F89: =$I$140 | I89: Tài sản ngắn hạn | K89: ko áp dụng
A90: Operating Profit | B90: =B$63-B$64-B$70 | C90: =IF(C63="","",C$63-C$64-C$70) | D90: =D$63-D$64-D$70 | E90: =G$63-G$64-G$70 | F90: =I$63-I$64-I$70 | I90: Tổng tài sản | J90: =$D$9
A91: Operating Profit Margin | B91: =B$90/B$63 | C91: =IF(C63="","",C$90/C$63) | D91: =D$90/D$63 | E91: =E$90/G$63 | F91: =F$90/I$63 | I91: Chi phí lãi vay | J91: =D69
A92: DSCR | B92: =($B$253+$B$254)/($B$255+$B$256) | C92: =IF(C253="","",($C$253+$C$254)/($C$255+$C$256)) | D92: =($D$253+$D$254)/($D$255+$D$256) | E92: =($E$253+$E$254)/($E$255+$E$256) | F92: =($F$253+$F$254)/($F$255+$F$256) | I92: Các tiêu chí điều chỉnh
A93: KNTT hiện hành (lần) | B93: ='03. Dulieutaichinhlamsach_RG'!D99 | C93: ='03. Dulieutaichinhlamsach_RG'!E99 | D93: ='03. Dulieutaichinhlamsach_RG'!F99 | E93: ='03. Dulieutaichinhlamsach_RG'!G99 | F93: ='03. Dulieutaichinhlamsach_RG'!H99 | I93: Khả năng thanh toán hiện hành | J93: =IF($J$83=0,-99999,$J$89/$J$83) | K93: ko áp dụng
A94: Vòng quay VLĐ (vòng) | C94: ='03. Dulieutaichinhlamsach_RG'!E103 | D94: ='03. Dulieutaichinhlamsach_RG'!F103 | E94: ='03. Dulieutaichinhlamsach_RG'!G103 | F94: ='03. Dulieutaichinhlamsach_RG'!H103 | I94: Khả năng thanh toán tức thời | J94: =IF($J$83=0,-99999,($D$11+$D$17)/$J$83) | K94: ko áp dụng
I95: Khả năng thực hiện nghĩa vụ trả nợ ngắn hạn | K95: ko áp dụng
I96: Tiền và tương đương tiền/Tổng tài sản | J96: =IF($J$90=0,-99999,$D$10/$J$90)
I97: Phải thu khác/Tổng tài sản | J97: =IF($D$9=0,-99999,($D$20)/$D$9)
I98: Tổng nợ/Tổng tài sản | J98: =IF($J$90=0,-99999,$J$82/$J$90)
I99: Tổng nợ/Vốn chủ sở hữu | J99: =IF($J$85=0,-99999,$J$82/$J$85)
I100: Lợi nhuận sau thuế/Tổng tài sản | J100: =IF($J$90=0,-99999,$J$87/$J$90)
I101: Doanh thu thuần/Nợ vay ngắn hạn | J101: =IF($J$84=0,-99999,$D$63/$J$84) | K101: ko áp dụng
I102: Doanh thu thuần/Tổng tài sản | J102: =IF($J$90=0,-99999,$D$63/$J$90)
I103: Doanh thu thuần/Tổng nợ | J103: =IF($J$82=0,-99999,$D$63/$J$82)
...

Sheet 02. Nhap lieu tai chinh_DD
B1: NHẬP SỐ LIỆU VỀ TÀI CHÍNH CỦA KHÁCH HÀNG | I1: Check thông tin báo cáo tài chính
D2: Lưu ý: bắt buộc điền sheet 01. Thông tin chung | F2: Đơn vị: | G2: =IF('01. Thong tin chung'!B6="","",'01. Thong tin chung'!B6) | O2: CountNegProvision | P2: =COUNTIF(D22:H22,">0")+COUNTIF(D30:H30,">0")+COUNTIF(D41:H41,">0")+COUNTIF(D55:H55,">0")+COUNTIF(D59:H59,">0")+COUNTIF(D62:H62,">0")+COUNTIF(D65:H65,">0")+COUNTIF(D69:H69,">0")+COUNTIF(D74:H74,">0")
B3: I. Bảng cân đối kế toán
D4: =IF(D11<>D83,"Chưa cân số","") | E4: =IF(E11<>E83,"Chưa cân số","") | F4: =IF(F11<>F83,"Chưa cân số","") | G4: =IF(G11<>G83,"Chưa cân số","") | H4: =IF(H11<>H83,"Chưa cân số","")
B5: Chỉ tiêu | C5: Mã số | D5: N-3 | E5: N-2 | F5: N-1 | G5: Thời điểm hiện tại | H5: Dự tính N
B6: Mã số thuế | D6: ='01. Thong tin chung'!$B$4 | E6: ='01. Thong tin chung'!$B$4 | F6: ='01. Thong tin chung'!$B$4 | G6: ='01. Thong tin chung'!$B$4 | H6: ='01. Thong tin chung'!$B$4 | I6: =D6='03. Dulieutaichinhlamsach_DD'!D6 | J6: =E6='03. Dulieutaichinhlamsach_DD'!E6 | K6: =F6='03. Dulieutaichinhlamsach_DD'!F6 | L6: =G6='03. Dulieutaichinhlamsach_DD'!G6 | M6: =H6='03. Dulieutaichinhlamsach_DD'!H6
B7: Năm | I7: =D7='03. Dulieutaichinhlamsach_DD'!D7 | J7: =E7='03. Dulieutaichinhlamsach_DD'!E7 | K7: =F7='03. Dulieutaichinhlamsach_DD'!F7 | L7: =G7='03. Dulieutaichinhlamsach_DD'!G7 | M7: =H7='03. Dulieutaichinhlamsach_DD'!H7
B8: Quý | I8: =D8='03. Dulieutaichinhlamsach_DD'!D8 | J8: =E8='03. Dulieutaichinhlamsach_DD'!E8 | K8: =F8='03. Dulieutaichinhlamsach_DD'!F8 | L8: =G8='03. Dulieutaichinhlamsach_DD'!G8 | M8: =H8='03. Dulieutaichinhlamsach_DD'!H8
B9: Tháng | I9: =D9='03. Dulieutaichinhlamsach_DD'!D9 | J9: =E9='03. Dulieutaichinhlamsach_DD'!E9 | K9: =F9='03. Dulieutaichinhlamsach_DD'!F9 | L9: =G9='03. Dulieutaichinhlamsach_DD'!G9 | M9: =H9='03. Dulieutaichinhlamsach_DD'!H9
B10: Đơn vị tính | D10: =$G$2 | E10: =$G$2 | F10: =$G$2 | G10: =$G$2 | H10: =$G$2 | I10: =D10='03. Dulieutaichinhlamsach_DD'!D10 | J10: =E10='03. Dulieutaichinhlamsach_DD'!E10 | K10: =F10='03. Dulieutaichinhlamsach_DD'!F10 | L10: =G10='03. Dulieutaichinhlamsach_DD'!G10 | M10: =H10='03. Dulieutaichinhlamsach_DD'!H10
B11: TỔNG TÀI SẢN | I11: =D11='03. Dulieutaichinhlamsach_DD'!D11 | J11: =E11='03. Dulieutaichinhlamsach_DD'!E11 | K11: =F11='03. Dulieutaichinhlamsach_DD'!F11 | L11: =G11='03. Dulieutaichinhlamsach_DD'!G11 | M11: =H11='03. Dulieutaichinhlamsach_DD'!H11
B12: A. TÀI SẢN NGẮN HẠN | I12: =D12='03. Dulieutaichinhlamsach_DD'!D12 | J12: =E12='03. Dulieutaichinhlamsach_DD'!E12 | K12: =F12='03. Dulieutaichinhlamsach_DD'!F12 | L12: =G12='03. Dulieutaichinhlamsach_DD'!G12 | M12: =H12='03. Dulieutaichinhlamsach_DD'!H12
B13: I. Tiền và các khoản tương đương tiền | I13: =D13='03. Dulieutaichinhlamsach_DD'!D13 | J13: =E13='03. Dulieutaichinhlamsach_DD'!E13 | K13: =F13='03. Dulieutaichinhlamsach_DD'!F13 | L13: =G13='03. Dulieutaichinhlamsach_DD'!G13 | M13: =H13='03. Dulieutaichinhlamsach_DD'!H13
B14: 1. Tiền mặt | I14: =D14='03. Dulieutaichinhlamsach_DD'!D14 | J14: =E14='03. Dulieutaichinhlamsach_DD'!E14 | K14: =F14='03. Dulieutaichinhlamsach_DD'!F14 | L14: =G14='03. Dulieutaichinhlamsach_DD'!G14 | M14: =H14='03. Dulieutaichinhlamsach_DD'!H14
B15: 2. Tiền gửi ngân hàng | I15: =D15='03. Dulieutaichinhlamsach_DD'!D15 | J15: =E15='03. Dulieutaichinhlamsach_DD'!E15 | K15: =F15='03. Dulieutaichinhlamsach_DD'!F15 | L15: =G15='03. Dulieutaichinhlamsach_DD'!G15 | M15: =H15='03. Dulieutaichinhlamsach_DD'!H15
B16: 3. Tiền đang chuyển | I16: =D16='03. Dulieutaichinhlamsach_DD'!D16 | J16: =E16='03. Dulieutaichinhlamsach_DD'!E16 | K16: =F16='03. Dulieutaichinhlamsach_DD'!F16 | L16: =G16='03. Dulieutaichinhlamsach_DD'!G16 | M16: =H16='03. Dulieutaichinhlamsach_DD'!H16
B17: 4. Tiền (trong trường hợp Báo cáo không có 3 thông tin trên) | D17: 5906481705 | E17: 3391437136 | F17: 1931416104 | I17: =D17='03. Dulieutaichinhlamsach_DD'!D17 | J17: =E17='03. Dulieutaichinhlamsach_DD'!E17 | K17: =F17='03. Dulieutaichinhlamsach_DD'!F17 | L17: =G17='03. Dulieutaichinhlamsach_DD'!G17 | M17: =H17='03. Dulieutaichinhlamsach_DD'!H17
B18: 5. Các khoản tương đương tiền | I18: =D18='03. Dulieutaichinhlamsach_DD'!D18 | J18: =E18='03. Dulieutaichinhlamsach_DD'!E18 | K18: =F18='03. Dulieutaichinhlamsach_DD'!F18 | L18: =G18='03. Dulieutaichinhlamsach_DD'!G18 | M18: =H18='03. Dulieutaichinhlamsach_DD'!H18
B19: II. Các khoản đầu tư tài chính ngắn hạn | I19: =D19='03. Dulieutaichinhlamsach_DD'!D19 | J19: =E19='03. Dulieutaichinhlamsach_DD'!E19 | K19: =F19='03. Dulieutaichinhlamsach_DD'!F19 | L19: =G19='03. Dulieutaichinhlamsach_DD'!G19 | M19: =H19='03. Dulieutaichinhlamsach_DD'!H19
B20: 1. Chứng khoán đầu tư ngắn hạn | D20: 0 | E20: 2376983000 | F20: 1554000000 | I20: =D20='03. Dulieutaichinhlamsach_DD'!D20 | J20: =E20='03. Dulieutaichinhlamsach_DD'!E20 | K20: =F20='03. Dulieutaichinhlamsach_DD'!F20 | L20: =G20='03. Dulieutaichinhlamsach_DD'!G20 | M20: =H20='03. Dulieutaichinhlamsach_DD'!H20
B21: 2. Đầu tư ngắn hạn khác | I21: =D21='03. Dulieutaichinhlamsach_DD'!D21 | J21: =E21='03. Dulieutaichinhlamsach_DD'!E21 | K21: =F21='03. Dulieutaichinhlamsach_DD'!F21 | L21: =G21='03. Dulieutaichinhlamsach_DD'!G21 | M21: =H21='03. Dulieutaichinhlamsach_DD'!H21
B22: 3. Dự phòng giảm giá đầu tư ngắn hạn | I22: =D22='03. Dulieutaichinhlamsach_DD'!D22 | J22: =E22='03. Dulieutaichinhlamsach_DD'!E22 | K22: =F22='03. Dulieutaichinhlamsach_DD'!F22 | L22: =G22='03. Dulieutaichinhlamsach_DD'!G22 | M22: =H22='03. Dulieutaichinhlamsach_DD'!H22
B23: 4. Đầu tư tài chính ngắn hạn (trong trường hợp báo cáo không có thông tin) | I23: =D23='03. Dulieutaichinhlamsach_DD'!D23 | J23: =E23='03. Dulieutaichinhlamsach_DD'!E23 | K23: =F23='03. Dulieutaichinhlamsach_DD'!F23 | L23: =G23='03. Dulieutaichinhlamsach_DD'!G23 | M23: =H23='03. Dulieutaichinhlamsach_DD'!H23
B24: II. Các khoản phải thu ngắn hạn | I24: =D24='03. Dulieutaichinhlamsach_DD'!D24 | J24: =E24='03. Dulieutaichinhlamsach_DD'!E24 | K24: =F24='03. Dulieutaichinhlamsach_DD'!F24 | L24: =G24='03. Dulieutaichinhlamsach_DD'!G24 | M24: =H24='03. Dulieutaichinhlamsach_DD'!H24
B25: 1. Phải thu khách hàng | D25: 3934341244 | E25: 6534405546 | F25: 60075246323 | I25: =D25='03. Dulieutaichinhlamsach_DD'!D25 | J25: =E25='03. Dulieutaichinhlamsach_DD'!E25 | K25: =F25='03. Dulieutaichinhlamsach_DD'!F25 | L25: =G25='03. Dulieutaichinhlamsach_DD'!G25 | M25: =H25='03. Dulieutaichinhlamsach_DD'!H25
B26: 2. Trả trước cho người bán | D26: 926771100 | E26: 19024451267 | F26: 29725842988 | I26: =D26='03. Dulieutaichinhlamsach_DD'!D26 | J26: =E26='03. Dulieutaichinhlamsach_DD'!E26 | K26: =F26='03. Dulieutaichinhlamsach_DD'!F26 | L26: =G26='03. Dulieutaichinhlamsach_DD'!G26 | M26: =H26='03. Dulieutaichinhlamsach_DD'!H26
B27: 3. Phải thu nội bộ ngắn hạn | D27: 0 | E27: 0 | F27: 6150000000 | I27: =D27='03. Dulieutaichinhlamsach_DD'!D27 | J27: =E27='03. Dulieutaichinhlamsach_DD'!E27 | K27: =F27='03. Dulieutaichinhlamsach_DD'!F27 | L27: =G27='03. Dulieutaichinhlamsach_DD'!G27 | M27: =H27='03. Dulieutaichinhlamsach_DD'!H27
B28: 4. Phải thu theo tiến độ kế hoạch hợp đồng xây dựng | I28: =D28='03. Dulieutaichinhlamsach_DD'!D28 | J28: =E28='03. Dulieutaichinhlamsach_DD'!E28 | K28: =F28='03. Dulieutaichinhlamsach_DD'!F28 | L28: =G28='03. Dulieutaichinhlamsach_DD'!G28 | M28: =H28='03. Dulieutaichinhlamsach_DD'!H28
B29: 5. Các khoản phải thu khác | D29: 5000000 | E29: 17089489834 | F29: 32205108687 | I29: =D29='03. Dulieutaichinhlamsach_DD'!D29 | J29: =E29='03. Dulieutaichinhlamsach_DD'!E29 | K29: =F29='03. Dulieutaichinhlamsach_DD'!F29 | L29: =G29='03. Dulieutaichinhlamsach_DD'!G29 | M29: =H29='03. Dulieutaichinhlamsach_DD'!H29
B30: 6. Dự phòng phải thu ngắn hạn khó đòi | D30: 0 | E30: 0 | F30: -2192564099 | I30: =D30='03. Dulieutaichinhlamsach_DD'!D30 | J30: =E30='03. Dulieutaichinhlamsach_DD'!E30 | K30: =F30='03. Dulieutaichinhlamsach_DD'!F30 | L30: =G30='03. Dulieutaichinhlamsach_DD'!G30 | M30: =H30='03. Dulieutaichinhlamsach_DD'!H30
B31: IV. Hàng tồn kho | I31: =D31='03. Dulieutaichinhlamsach_DD'!D31 | J31: =E31='03. Dulieutaichinhlamsach_DD'!E31 | K31: =F31='03. Dulieutaichinhlamsach_DD'!F31 | L31: =G31='03. Dulieutaichinhlamsach_DD'!G31 | M31: =H31='03. Dulieutaichinhlamsach_DD'!H31
B32: 1. Hàng mua đang đi đường | I32: =D32='03. Dulieutaichinhlamsach_DD'!D32 | J32: =E32='03. Dulieutaichinhlamsach_DD'!E32 | K32: =F32='03. Dulieutaichinhlamsach_DD'!F32 | L32: =G32='03. Dulieutaichinhlamsach_DD'!G32 | M32: =H32='03. Dulieutaichinhlamsach_DD'!H32
B33: 2. Nguyên liệu, vật liệu | I33: =D33='03. Dulieutaichinhlamsach_DD'!D33 | J33: =E33='03. Dulieutaichinhlamsach_DD'!E33 | K33: =F33='03. Dulieutaichinhlamsach_DD'!F33 | L33: =G33='03. Dulieutaichinhlamsach_DD'!G33 | M33: =H33='03. Dulieutaichinhlamsach_DD'!H33
B34: 3. Công cụ, dụng cụ | I34: =D34='03. Dulieutaichinhlamsach_DD'!D34 | J34: =E34='03. Dulieutaichinhlamsach_DD'!E34 | K34: =F34='03. Dulieutaichinhlamsach_DD'!F34 | L34: =G34='03. Dulieutaichinhlamsach_DD'!G34 | M34: =H34='03. Dulieutaichinhlamsach_DD'!H34
B35: 4. Chi phí SX, KD dở dang | I35: =D35='03. Dulieutaichinhlamsach_DD'!D35 | J35: =E35='03. Dulieutaichinhlamsach_DD'!E35 | K35: =F35='03. Dulieutaichinhlamsach_DD'!F35 | L35: =G35='03. Dulieutaichinhlamsach_DD'!G35 | M35: =H35='03. Dulieutaichinhlamsach_DD'!H35
B36: 5. Thành phẩm | I36: =D36='03. Dulieutaichinhlamsach_DD'!D36 | J36: =E36='03. Dulieutaichinhlamsach_DD'!E36 | K36: =F36='03. Dulieutaichinhlamsach_DD'!F36 | L36: =G36='03. Dulieutaichinhlamsach_DD'!G36 | M36: =H36='03. Dulieutaichinhlamsach_DD'!H36
B37: 6. Hàng hóa | I37: =D37='03. Dulieutaichinhlamsach_DD'!D37 | J37: =E37='03. Dulieutaichinhlamsach_DD'!E37 | K37: =F37='03. Dulieutaichinhlamsach_DD'!F37 | L37: =G37='03. Dulieutaichinhlamsach_DD'!G37 | M37: =H37='03. Dulieutaichinhlamsach_DD'!H37
B38: 7. Hàng gửi đi bán | I38: =D38='03. Dulieutaichinhlamsach_DD'!D38 | J38: =E38='03. Dulieutaichinhlamsach_DD'!E38 | K38: =F38='03. Dulieutaichinhlamsach_DD'!F38 | L38: =G38='03. Dulieutaichinhlamsach_DD'!G38 | M38: =H38='03. Dulieutaichinhlamsach_DD'!H38
B39: 8. Hàng hóa kho bảo thuế | I39: =D39='03. Dulieutaichinhlamsach_DD'!D39 | J39: =E39='03. Dulieutaichinhlamsach_DD'!E39 | K39: =F39='03. Dulieutaichinhlamsach_DD'!F39 | L39: =G39='03. Dulieutaichinhlamsach_DD'!G39 | M39: =H39='03. Dulieutaichinhlamsach_DD'!H39
B40: 9. Hàng hóa bất động sản | I40: =D40='03. Dulieutaichinhlamsach_DD'!D40 | J40: =E40='03. Dulieutaichinhlamsach_DD'!E40 | K40: =F40='03. Dulieutaichinhlamsach_DD'!F40 | L40: =G40='03. Dulieutaichinhlamsach_DD'!G40 | M40: =H40='03. Dulieutaichinhlamsach_DD'!H40
B41: 10. Dự phòng giảm giá hàng tồn kho | I41: =D41='03. Dulieutaichinhlamsach_DD'!D41 | J41: =E41='03. Dulieutaichinhlamsach_DD'!E41 | K41: =F41='03. Dulieutaichinhlamsach_DD'!F41 | L41: =G41='03. Dulieutaichinhlamsach_DD'!G41 | M41: =H41='03. Dulieutaichinhlamsach_DD'!H41
B42: 11. Hàng tồn kho (trong trường hợp báo cáo không có thông tin chi tiết) | D42: 3531140741 | E42: 6071337045 | F42: 1471492473 | I42: =D42='03. Dulieutaichinhlamsach_DD'!D42 | J42: =E42='03. Dulieutaichinhlamsach_DD'!E42 | K42: =F42='03. Dulieutaichinhlamsach_DD'!F42 | L42: =G42='03. Dulieutaichinhlamsach_DD'!G42 | M42: =H42='03. Dulieutaichinhlamsach_DD'!H42
B43: V. Tài sản ngắn hạn khác | I43: =D43='03. Dulieutaichinhlamsach_DD'!D43 | J43: =E43='03. Dulieutaichinhlamsach_DD'!E43 | K43: =F43='03. Dulieutaichinhlamsach_DD'!F43 | L43: =G43='03. Dulieutaichinhlamsach_DD'!G43 | M43: =H43='03. Dulieutaichinhlamsach_DD'!H43
B44: 1. Chi phí trả trước ngắn hạn | D44: 0 | E44: 0 | F44: 593497916 | I44: =D44='03. Dulieutaichinhlamsach_DD'!D44 | J44: =E44='03. Dulieutaichinhlamsach_DD'!E44 | K44: =F44='03. Dulieutaichinhlamsach_DD'!F44 | L44: =G44='03. Dulieutaichinhlamsach_DD'!G44 | M44: =H44='03. Dulieutaichinhlamsach_DD'!H44
B45: 2. Thuế GTGT được khấu trừ | D45: 2749046708 | E45: 1144174156 | F45: 12518378703 | I45: =D45='03. Dulieutaichinhlamsach_DD'!D45 | J45: =E45='03. Dulieutaichinhlamsach_DD'!E45 | K45: =F45='03. Dulieutaichinhlamsach_DD'!F45 | L45: =G45='03. Dulieutaichinhlamsach_DD'!G45 | M45: =H45='03. Dulieutaichinhlamsach_DD'!H45
B46: 3. Thuế và các khoản khác phải thu Nhà nước | I46: =D46='03. Dulieutaichinhlamsach_DD'!D46 | J46: =E46='03. Dulieutaichinhlamsach_DD'!E46 | K46: =F46='03. Dulieutaichinhlamsach_DD'!F46 | L46: =G46='03. Dulieutaichinhlamsach_DD'!G46 | M46: =H46='03. Dulieutaichinhlamsach_DD'!H46
B47: 4. Giao dịch mua bán lại trái phiếu chính phủ | I47: =D47='03. Dulieutaichinhlamsach_DD'!D47 | J47: =E47='03. Dulieutaichinhlamsach_DD'!E47 | K47: =F47='03. Dulieutaichinhlamsach_DD'!F47 | L47: =G47='03. Dulieutaichinhlamsach_DD'!G47 | M47: =H47='03. Dulieutaichinhlamsach_DD'!H47
B48: 5. Tài sản ngắn hạn khác | I48: =D48='03. Dulieutaichinhlamsach_DD'!D48 | J48: =E48='03. Dulieutaichinhlamsach_DD'!E48 | K48: =F48='03. Dulieutaichinhlamsach_DD'!F48 | L48: =G48='03. Dulieutaichinhlamsach_DD'!G48 | M48: =H48='03. Dulieutaichinhlamsach_DD'!H48
B49: B. TÀI SẢN DÀI HẠN | I49: =D49='03. Dulieutaichinhlamsach_DD'!D49 | J49: =E49='03. Dulieutaichinhlamsach_DD'!E49 | K49: =F49='03. Dulieutaichinhlamsach_DD'!F49 | L49: =G49='03. Dulieutaichinhlamsach_DD'!G49 | M49: =H49='03. Dulieutaichinhlamsach_DD'!H49
B50: I. Các khoản phải thu dài hạn | I50: =D50='03. Dulieutaichinhlamsach_DD'!D50 | J50: =E50='03. Dulieutaichinhlamsach_DD'!E50 | K50: =F50='03. Dulieutaichinhlamsach_DD'!F50 | L50: =G50='03. Dulieutaichinhlamsach_DD'!G50 | M50: =H50='03. Dulieutaichinhlamsach_DD'!H50
B51: 1. Phải thu dài hạn của khách hàng | I51: =D51='03. Dulieutaichinhlamsach_DD'!D51 | J51: =E51='03. Dulieutaichinhlamsach_DD'!E51 | K51: =F51='03. Dulieutaichinhlamsach_DD'!F51 | L51: =G51='03. Dulieutaichinhlamsach_DD'!G51 | M51: =H51='03. Dulieutaichinhlamsach_DD'!H51
B52: 2. Vốn kinh doanh ở đơn vị trực thuộc | I52: =D52='03. Dulieutaichinhlamsach_DD'!D52 | J52: =E52='03. Dulieutaichinhlamsach_DD'!E52 | K52: =F52='03. Dulieutaichinhlamsach_DD'!F52 | L52: =G52='03. Dulieutaichinhlamsach_DD'!G52 | M52: =H52='03. Dulieutaichinhlamsach_DD'!H52
B53: 3. Phải thu dài hạn nội bộ | I53: =D53='03. Dulieutaichinhlamsach_DD'!D53 | J53: =E53='03. Dulieutaichinhlamsach_DD'!E53 | K53: =F53='03. Dulieutaichinhlamsach_DD'!F53 | L53: =G53='03. Dulieutaichinhlamsach_DD'!G53 | M53: =H53='03. Dulieutaichinhlamsach_DD'!H53
B54: 4. Phải thu dài hạn khác | D54: 57343200 | E54: 57343200 | F54: 100000000 | I54: =D54='03. Dulieutaichinhlamsach_DD'!D54 | J54: =E54='03. Dulieutaichinhlamsach_DD'!E54 | K54: =F54='03. Dulieutaichinhlamsach_DD'!F54 | L54: =G54='03. Dulieutaichinhlamsach_DD'!G54 | M54: =H54='03. Dulieutaichinhlamsach_DD'!H54
B55: 5. Dự phòng phải thu dài hạn khó đòi | I55: =D55='03. Dulieutaichinhlamsach_DD'!D55 | J55: =E55='03. Dulieutaichinhlamsach_DD'!E55 | K55: =F55='03. Dulieutaichinhlamsach_DD'!F55 | L55: =G55='03. Dulieutaichinhlamsach_DD'!G55 | M55: =H55='03. Dulieutaichinhlamsach_DD'!H55
B56: II. Tài sản cố định | I56: =D56='03. Dulieutaichinhlamsach_DD'!D56 | J56: =E56='03. Dulieutaichinhlamsach_DD'!E56 | K56: =F56='03. Dulieutaichinhlamsach_DD'!F56 | L56: =G56='03. Dulieutaichinhlamsach_DD'!G56 | M56: =H56='03. Dulieutaichinhlamsach_DD'!H56
B57: 1. Tài sản cố định hữu hình | I57: =D57='03. Dulieutaichinhlamsach_DD'!D57 | J57: =E57='03. Dulieutaichinhlamsach_DD'!E57 | K57: =F57='03. Dulieutaichinhlamsach_DD'!F57 | L57: =G57='03. Dulieutaichinhlamsach_DD'!G57 | M57: =H57='03. Dulieutaichinhlamsach_DD'!H57
B58: - Nguyên giá | D58: 2934932762 | E58: 3630874053 | F58: 4945028850 | I58: =D58='03. Dulieutaichinhlamsach_DD'!D58 | J58: =E58='03. Dulieutaichinhlamsach_DD'!E58 | K58: =F58='03. Dulieutaichinhlamsach_DD'!F58 | L58: =G58='03. Dulieutaichinhlamsach_DD'!G58 | M58: =H58='03. Dulieutaichinhlamsach_DD'!H58
B59: - Giá trị hao mòn lũy kế | D59: -597366436 | E59: -1108398598 | F59: -1272451346 | I59: =D59='03. Dulieutaichinhlamsach_DD'!D59 | J59: =E59='03. Dulieutaichinhlamsach_DD'!E59 | K59: =F59='03. Dulieutaichinhlamsach_DD'!F59 | L59: =G59='03. Dulieutaichinhlamsach_DD'!G59 | M59: =H59='03. Dulieutaichinhlamsach_DD'!H59
B60: 2. Tài sản cố định thuê tài chính | I60: =D60='03. Dulieutaichinhlamsach_DD'!D60 | J60: =E60='03. Dulieutaichinhlamsach_DD'!E60 | K60: =F60='03. Dulieutaichinhlamsach_DD'!F60 | L60: =G60='03. Dulieutaichinhlamsach_DD'!G60 | M60: =H60='03. Dulieutaichinhlamsach_DD'!H60
B61: - Nguyên giá | I61: =D61='03. Dulieutaichinhlamsach_DD'!D61 | J61: =E61='03. Dulieutaichinhlamsach_DD'!E61 | K61: =F61='03. Dulieutaichinhlamsach_DD'!F61 | L61: =G61='03. Dulieutaichinhlamsach_DD'!G61 | M61: =H61='03. Dulieutaichinhlamsach_DD'!H61
B62: - Giá trị hao mòn lũy kế | I62: =D62='03. Dulieutaichinhlamsach_DD'!D62 | J62: =E62='03. Dulieutaichinhlamsach_DD'!E62 | K62: =F62='03. Dulieutaichinhlamsach_DD'!F62 | L62: =G62='03. Dulieutaichinhlamsach_DD'!G62 | M62: =H62='03. Dulieutaichinhlamsach_DD'!H62
B63: 3. Tài sản cố định vô hình | I63: =D63='03. Dulieutaichinhlamsach_DD'!D63 | J63: =E63='03. Dulieutaichinhlamsach_DD'!E63 | K63: =F63='03. Dulieutaichinhlamsach_DD'!F63 | L63: =G63='03. Dulieutaichinhlamsach_DD'!G63 | M63: =H63='03. Dulieutaichinhlamsach_DD'!H63
B64: - Nguyên giá | I64: =D64='03. Dulieutaichinhlamsach_DD'!D64 | J64: =E64='03. Dulieutaichinhlamsach_DD'!E64 | K64: =F64='03. Dulieutaichinhlamsach_DD'!F64 | L64: =G64='03. Dulieutaichinhlamsach_DD'!G64 | M64: =H64='03. Dulieutaichinhlamsach_DD'!H64
B65: - Giá trị hao mòn lũy kế | I65: =D65='03. Dulieutaichinhlamsach_DD'!D65 | J65: =E65='03. Dulieutaichinhlamsach_DD'!E65 | K65: =F65='03. Dulieutaichinhlamsach_DD'!F65 | L65: =G65='03. Dulieutaichinhlamsach_DD'!G65 | M65: =H65='03. Dulieutaichinhlamsach_DD'!H65
B66: 4. Chi phí xây dựng cơ bản dở dang | D66: 0 | E66: 2456250000 | F66: 0 | I66: =D66='03. Dulieutaichinhlamsach_DD'!D66 | J66: =E66='03. Dulieutaichinhlamsach_DD'!E66 | K66: =F66='03. Dulieutaichinhlamsach_DD'!F66 | L66: =G66='03. Dulieutaichinhlamsach_DD'!G66 | M66: =H66='03. Dulieutaichinhlamsach_DD'!H66
B67: III. Bất động sản đầu tư | I67: =D67='03. Dulieutaichinhlamsach_DD'!D67 | J67: =E67='03. Dulieutaichinhlamsach_DD'!E67 | K67: =F67='03. Dulieutaichinhlamsach_DD'!F67 | L67: =G67='03. Dulieutaichinhlamsach_DD'!G67 | M67: =H67='03. Dulieutaichinhlamsach_DD'!H67
B68: - Nguyên giá | I68: =D68='03. Dulieutaichinhlamsach_DD'!D68 | J68: =E68='03. Dulieutaichinhlamsach_DD'!E68 | K68: =F68='03. Dulieutaichinhlamsach_DD'!F68 | L68: =G68='03. Dulieutaichinhlamsach_DD'!G68 | M68: =H68='03. Dulieutaichinhlamsach_DD'!H68
B69: - Giá trị hao mòn lũy kế | I69: =D69='03. Dulieutaichinhlamsach_DD'!D69 | J69: =E69='03. Dulieutaichinhlamsach_DD'!E69 | K69: =F69='03. Dulieutaichinhlamsach_DD'!F69 | L69: =G69='03. Dulieutaichinhlamsach_DD'!G69 | M69: =H69='03. Dulieutaichinhlamsach_DD'!H69
B70: IV. Các khoản đầu tư tài chính dài hạn | I70: =D70='03. Dulieutaichinhlamsach_DD'!D70 | J70: =E70='03. Dulieutaichinhlamsach_DD'!E70 | K70: =F70='03. Dulieutaichinhlamsach_DD'!F70 | L70: =G70='03. Dulieutaichinhlamsach_DD'!G70 | M70: =H70='03. Dulieutaichinhlamsach_DD'!H70
B71: 1. Đầu tư vào công ty con | I71: =D71='03. Dulieutaichinhlamsach_DD'!D71 | J71: =E71='03. Dulieutaichinhlamsach_DD'!E71 | K71: =F71='03. Dulieutaichinhlamsach_DD'!F71 | L71: =G71='03. Dulieutaichinhlamsach_DD'!G71 | M71: =H71='03. Dulieutaichinhlamsach_DD'!H71
B72: 2. Đầu tư vào công ty liên kết, liên doanh | D72: 500000000 | E72: 500000000 | F72: 0 | I72: =D72='03. Dulieutaichinhlamsach_DD'!D72 | J72: =E72='03. Dulieutaichinhlamsach_DD'!E72 | K72: =F72='03. Dulieutaichinhlamsach_DD'!F72 | L72: =G72='03. Dulieutaichinhlamsach_DD'!G72 | M72: =H72='03. Dulieutaichinhlamsach_DD'!H72
B73: 3. Đầu tư dài hạn khác | I73: =D73='03. Dulieutaichinhlamsach_DD'!D73 | J73: =E73='03. Dulieutaichinhlamsach_DD'!E73 | K73: =F73='03. Dulieutaichinhlamsach_DD'!F73 | L73: =G73='03. Dulieutaichinhlamsach_DD'!G73 | M73: =H73='03. Dulieutaichinhlamsach_DD'!H73
B74: 4. Dự phòng giảm giá đầu tư tài chính dài hạn | I74: =D74='03. Dulieutaichinhlamsach_DD'!D74 | J74: =E74='03. Dulieutaichinhlamsach_DD'!E74 | K74: =F74='03. Dulieutaichinhlamsach_DD'!F74 | L74: =G74='03. Dulieutaichinhlamsach_DD'!G74 | M74: =H74='03. Dulieutaichinhlamsach_DD'!H74
B75: 5. Đầu tư tài chính dài hạn (trong trường hợp báo cáo không có thông tin) | I75: =D75='03. Dulieutaichinhlamsach_DD'!D75 | J75: =E75='03. Dulieutaichinhlamsach_DD'!E75 | K75: =F75='03. Dulieutaichinhlamsach_DD'!F75 | L75: =G75='03. Dulieutaichinhlamsach_DD'!G75 | M75: =H75='03. Dulieutaichinhlamsach_DD'!H75
B76: V. Tài sản dài hạn khác | I76: =D76='03. Dulieutaichinhlamsach_DD'!D76 | J76: =E76='03. Dulieutaichinhlamsach_DD'!E76 | K76: =F76='03. Dulieutaichinhlamsach_DD'!F76 | L76: =G76='03. Dulieutaichinhlamsach_DD'!G76 | M76: =H76='03. Dulieutaichinhlamsach_DD'!H76
B77: 1. Chi phí trả trước dài hạn | I77: =D77='03. Dulieutaichinhlamsach_DD'!D77 | J77: =E77='03. Dulieutaichinhlamsach_DD'!E77 | K77: =F77='03. Dulieutaichinhlamsach_DD'!F77 | L77: =G77='03. Dulieutaichinhlamsach_DD'!G77 | M77: =H77='03. Dulieutaichinhlamsach_DD'!H77
B78: 2. Tài sản thuế thu nhập hoãn lại | I78: =D78='03. Dulieutaichinhlamsach_DD'!D78 | J78: =E78='03. Dulieutaichinhlamsach_DD'!E78 | K78: =F78='03. Dulieutaichinhlamsach_DD'!F78 | L78: =G78='03. Dulieutaichinhlamsach_DD'!G78 | M78: =H78='03. Dulieutaichinhlamsach_DD'!H78
B79: 3. Phải thu dài hạn | I79: =D79='03. Dulieutaichinhlamsach_DD'!D79 | J79: =E79='03. Dulieutaichinhlamsach_DD'!E79 | K79: =F79='03. Dulieutaichinhlamsach_DD'!F79 | L79: =G79='03. Dulieutaichinhlamsach_DD'!G79 | M79: =H79='03. Dulieutaichinhlamsach_DD'!H79
B80: 4. Tài sản dài hạn khác | I80: =D80='03. Dulieutaichinhlamsach_DD'!D80 | J80: =E80='03. Dulieutaichinhlamsach_DD'!E80 | K80: =F80='03. Dulieutaichinhlamsach_DD'!F80 | L80: =G80='03. Dulieutaichinhlamsach_DD'!G80 | M80: =H80='03. Dulieutaichinhlamsach_DD'!H80
B81: 5. Dự phòng phải thu dài hạn khó đòi | I81: =D81='03. Dulieutaichinhlamsach_DD'!D81 | J81: =E81='03. Dulieutaichinhlamsach_DD'!E81 | K81: =F81='03. Dulieutaichinhlamsach_DD'!F81 | L81: =G81='03. Dulieutaichinhlamsach_DD'!G81 | M81: =H81='03. Dulieutaichinhlamsach_DD'!H81
B82: VI. Lợi thế thương mại | I82: =D82='03. Dulieutaichinhlamsach_DD'!D82 | J82: =E82='03. Dulieutaichinhlamsach_DD'!E82 | K82: =F82='03. Dulieutaichinhlamsach_DD'!F82 | L82: =G82='03. Dulieutaichinhlamsach_DD'!G82 | M82: =H82='03. Dulieutaichinhlamsach_DD'!H82
B83: TỔNG NGUỒN VỐN | I83: =D83='03. Dulieutaichinhlamsach_DD'!D83 | J83: =E83='03. Dulieutaichinhlamsach_DD'!E83 | K83: =F83='03. Dulieutaichinhlamsach_DD'!F83 | L83: =G83='03. Dulieutaichinhlamsach_DD'!G83 | M83: =H83='03. Dulieutaichinhlamsach_DD'!H83
B84: A. NỢ PHẢI TRẢ | I84: =D84='03. Dulieutaichinhlamsach_DD'!D84 | J84: =E84='03. Dulieutaichinhlamsach_DD'!E84 | K84: =F84='03. Dulieutaichinhlamsach_DD'!F84 | L84: =G84='03. Dulieutaichinhlamsach_DD'!G84 | M84: =H84='03. Dulieutaichinhlamsach_DD'!H84
B85: I. Nợ ngắn hạn | I85: =D85='03. Dulieutaichinhlamsach_DD'!D85 | J85: =E85='03. Dulieutaichinhlamsach_DD'!E85 | K85: =F85='03. Dulieutaichinhlamsach_DD'!F85 | L85: =G85='03. Dulieutaichinhlamsach_DD'!G85 | M85: =H85='03. Dulieutaichinhlamsach_DD'!H85
B86: 1. Vay và nợ ngắn hạn | D86: 3962372480 | E86: 0 | F86: 27138299197 | I86: =D86='03. Dulieutaichinhlamsach_DD'!D86 | J86: =E86='03. Dulieutaichinhlamsach_DD'!E86 | K86: =F86='03. Dulieutaichinhlamsach_DD'!F86 | L86: =G86='03. Dulieutaichinhlamsach_DD'!G86 | M86: =H86='03. Dulieutaichinhlamsach_DD'!H86
B87: - Tr/đó: vay MSB | I87: =D87='03. Dulieutaichinhlamsach_DD'!D87 | J87: =E87='03. Dulieutaichinhlamsach_DD'!E87 | K87: =F87='03. Dulieutaichinhlamsach_DD'!F87 | L87: =G87='03. Dulieutaichinhlamsach_DD'!G87 | M87: =H87='03. Dulieutaichinhlamsach_DD'!H87
B88: 2. Phải trả người bán | D88: 0 | E88: 23195272991 | F88: 19017162045 | I88: =D88='03. Dulieutaichinhlamsach_DD'!D88 | J88: =E88='03. Dulieutaichinhlamsach_DD'!E88 | K88: =F88='03. Dulieutaichinhlamsach_DD'!F88 | L88: =G88='03. Dulieutaichinhlamsach_DD'!G88 | M88: =H88='03. Dulieutaichinhlamsach_DD'!H88
B89: 3. Người mua trả tiền trước | D89: 3680295181 | E89: 8046359758 | F89: 24583668879 | I89: =D89='03. Dulieutaichinhlamsach_DD'!D89 | J89: =E89='03. Dulieutaichinhlamsach_DD'!E89 | K89: =F89='03. Dulieutaichinhlamsach_DD'!F89 | L89: =G89='03. Dulieutaichinhlamsach_DD'!G89 | M89: =H89='03. Dulieutaichinhlamsach_DD'!H89
B90: 4. Thuế và các khoản phải nộp Nhà nước | D90: 1463563514 | E90: 2039719877 | F90: 7817966288 | I90: =D90='03. Dulieutaichinhlamsach_DD'!D90 | J90: =E90='03. Dulieutaichinhlamsach_DD'!E90 | K90: =F90='03. Dulieutaichinhlamsach_DD'!F90 | L90: =G90='03. Dulieutaichinhlamsach_DD'!G90 | M90: =H90='03. Dulieutaichinhlamsach_DD'!H90
B91: 5. Phải trả người lao động | D91: 669021042 | E91: 1021321284 | F91: 3624743162 | I91: =D91='03. Dulieutaichinhlamsach_DD'!D91 | J91: =E91='03. Dulieutaichinhlamsach_DD'!E91 | K91: =F91='03. Dulieutaichinhlamsach_DD'!F91 | L91: =G91='03. Dulieutaichinhlamsach_DD'!G91 | M91: =H91='03. Dulieutaichinhlamsach_DD'!H91
B92: 6. Chi phí phải trả | D92: 0 | E92: 163000000 | F92: 0 | I92: =D92='03. Dulieutaichinhlamsach_DD'!D92 | J92: =E92='03. Dulieutaichinhlamsach_DD'!E92 | K92: =F92='03. Dulieutaichinhlamsach_DD'!F92 | L92: =G92='03. Dulieutaichinhlamsach_DD'!G92 | M92: =H92='03. Dulieutaichinhlamsach_DD'!H92
B93: 7. Phải trả nội bộ | I93: =D93='03. Dulieutaichinhlamsach_DD'!D93 | J93: =E93='03. Dulieutaichinhlamsach_DD'!E93 | K93: =F93='03. Dulieutaichinhlamsach_DD'!F93 | L93: =G93='03. Dulieutaichinhlamsach_DD'!G93 | M93: =H93='03. Dulieutaichinhlamsach_DD'!H93
B94: 8. Phải trả theo tiến độ kế hoạch hợp đồng xây dựng | I94: =D94='03. Dulieutaichinhlamsach_DD'!D94 | J94: =E94='03. Dulieutaichinhlamsach_DD'!E94 | K94: =F94='03. Dulieutaichinhlamsach_DD'!F94 | L94: =G94='03. Dulieutaichinhlamsach_DD'!G94 | M94: =H94='03. Dulieutaichinhlamsach_DD'!H94
B95: 9. Các khoản phải trả, phải nộp ngắn hạn khác | D95: 7587500 | E95: 7392959 | F95: 5153162 | I95: =D95='03. Dulieutaichinhlamsach_DD'!D95 | J95: =E95='03. Dulieutaichinhlamsach_DD'!E95 | K95: =F95='03. Dulieutaichinhlamsach_DD'!F95 | L95: =G95='03. Dulieutaichinhlamsach_DD'!G95 | M95: =H95='03. Dulieutaichinhlamsach_DD'!H95
B96: 10. Dự phòng phải trả ngắn hạn | D96: 2365701237 | E96: 12789468457 | F96: 17223376202 | I96: =D96='03. Dulieutaichinhlamsach_DD'!D96 | J96: =E96='03. Dulieutaichinhlamsach_DD'!E96 | K96: =F96='03. Dulieutaichinhlamsach_DD'!F96 | L96: =G96='03. Dulieutaichinhlamsach_DD'!G96 | M96: =H96='03. Dulieutaichinhlamsach_DD'!H96
B97: 11. Quỹ khen thưởng, phúc lợi | I97: =D97='03. Dulieutaichinhlamsach_DD'!D97 | J97: =E97='03. Dulieutaichinhlamsach_DD'!E97 | K97: =F97='03. Dulieutaichinhlamsach_DD'!F97 | L97: =G97='03. Dulieutaichinhlamsach_DD'!G97 | M97: =H97='03. Dulieutaichinhlamsach_DD'!H97
B98: 12. Giao dịch mua bán lại trái phiếu chính phủ | I98: =D98='03. Dulieutaichinhlamsach_DD'!D98 | J98: =E98='03. Dulieutaichinhlamsach_DD'!E98 | K98: =F98='03. Dulieutaichinhlamsach_DD'!F98 | L98: =G98='03. Dulieutaichinhlamsach_DD'!G98 | M98: =H98='03. Dulieutaichinhlamsach_DD'!H98
B99: 13. Doanh thu chưa thực hiện ngắn hạn | I99: =D99='03. Dulieutaichinhlamsach_DD'!D99 | J99: =E99='03. Dulieutaichinhlamsach_DD'!E99 | K99: =F99='03. Dulieutaichinhlamsach_DD'!F99 | L99: =G99='03. Dulieutaichinhlamsach_DD'!G99 | M99: =H99='03. Dulieutaichinhlamsach_DD'!H99
B100: II. Nợ dài hạn | I100: =D100='03. Dulieutaichinhlamsach_DD'!D100 | J100: =E100='03. Dulieutaichinhlamsach_DD'!E100 | K100: =F100='03. Dulieutaichinhlamsach_DD'!F100 | L100: =G100='03. Dulieutaichinhlamsach_DD'!G100 | M100: =H100='03. Dulieutaichinhlamsach_DD'!H100
...

Sheet 03. Dulieutaichinhlamsach_DD
B1: NHẬP SỐ LIỆU VỀ TÀI CHÍNH CỦA KHÁCH HÀNG
C2: =IF(OR(E11=0,F11=0),"Đề nghị nhấp số liệu tối thiểu 2 năm gần nhất"," ") | F2: Đơn vị: | G2: ='[1]01. Thong tin chung'!B6 | H2: =G2 | J2: CountBlankBCTC | K2: =COUNTIF(D4:G4,"Chưa cân số") + COUNTIF(G2,"")
B3: I. Bảng cân đối kế toán
D4: =IF(D11<>D83,"Chưa cân số", " ") | E4: =IF(E11<>E83,"Chưa cân số", " ") | F4: =IF(F11<>F83,"Chưa cân số", " ") | G4: =IF(G11<>G83,"Chưa cân số", " ") | H4: =IF(H11<>H83,"Chưa cân số", " ")
B5: Chỉ tiêu | C5: Mã số | D5: =E5-1 | E5: =F5-1 | F5: ='01. Thong tin chung'!B7 | G5: ='01. Thong tin chung'!B8 | H5: ="Dự tính " &F5+1
B6: Mã số thuế | D6: ='02. Nhap lieu tai chinh_DD'!D6 | E6: ='02. Nhap lieu tai chinh_DD'!E6 | F6: ='02. Nhap lieu tai chinh_DD'!F6 | G6: ='02. Nhap lieu tai chinh_DD'!G6 | H6: ='02. Nhap lieu tai chinh_DD'!H6
B7: Năm | D7: ='02. Nhap lieu tai chinh_DD'!D7 | E7: ='02. Nhap lieu tai chinh_DD'!E7 | F7: ='02. Nhap lieu tai chinh_DD'!F7 | G7: ='02. Nhap lieu tai chinh_DD'!G7 | H7: ='02. Nhap lieu tai chinh_DD'!H7
B8: Quý | D8: ='02. Nhap lieu tai chinh_DD'!D8 | E8: ='02. Nhap lieu tai chinh_DD'!E8 | F8: ='02. Nhap lieu tai chinh_DD'!F8 | G8: ='02. Nhap lieu tai chinh_DD'!G8 | H8: ='02. Nhap lieu tai chinh_DD'!H8
B9: Tháng | D9: ='02. Nhap lieu tai chinh_DD'!D9 | E9: ='02. Nhap lieu tai chinh_DD'!E9 | F9: ='02. Nhap lieu tai chinh_DD'!F9 | G9: ='02. Nhap lieu tai chinh_DD'!G9 | H9: ='02. Nhap lieu tai chinh_DD'!H9
B10: Đơn vị tính | D10: ='02. Nhap lieu tai chinh_DD'!D10 | E10: ='02. Nhap lieu tai chinh_DD'!E10 | F10: ='02. Nhap lieu tai chinh_DD'!F10 | G10: ='02. Nhap lieu tai chinh_DD'!G10 | H10: ='02. Nhap lieu tai chinh_DD'!H10
B11: TỔNG TÀI SẢN | D11: =D12+D49 | E11: =E12+E49 | F11: =F12+F49 | G11: =G12+G49 | H11: =H12+H49
B12: A. TÀI SẢN NGẮN HẠN | D12: =D13+D19+D24+D31+D43 | E12: =E13+E19+E24+E31+E43 | F12: =F13+F19+F24+F31+F43 | G12: =G13+G19+G24+G31+G43 | H12: =H13+H19+H24+H31+H43
B13: I. Tiền và các khoản tương đương tiền | D13: =SUM(D14:D18) | E13: =SUM(E14:E18) | F13: =SUM(F14:F18) | G13: =SUM(G14:G18)
B14: 1. Tiền mặt | D14: ='02. Nhap lieu tai chinh_DD'!D14 | E14: ='02. Nhap lieu tai chinh_DD'!E14 | F14: ='02. Nhap lieu tai chinh_DD'!F14 | G14: ='02. Nhap lieu tai chinh_DD'!G14
B15: 2. Tiền gửi ngân hàng | D15: ='02. Nhap lieu tai chinh_DD'!D15 | E15: ='02. Nhap lieu tai chinh_DD'!E15 | F15: ='02. Nhap lieu tai chinh_DD'!F15 | G15: ='02. Nhap lieu tai chinh_DD'!G15
B16: 3. Tiền đang chuyển | D16: ='02. Nhap lieu tai chinh_DD'!D16 | E16: ='02. Nhap lieu tai chinh_DD'!E16 | F16: ='02. Nhap lieu tai chinh_DD'!F16 | G16: ='02. Nhap lieu tai chinh_DD'!G16
B17: 4. Tiền (trong trường hợp Báo cáo không có 3 thông tin trên) | D17: ='02. Nhap lieu tai chinh_DD'!D17 | E17: ='02. Nhap lieu tai chinh_DD'!E17 | F17: ='02. Nhap lieu tai chinh_DD'!F17 | G17: ='02. Nhap lieu tai chinh_DD'!G17
B18: 5. Các khoản tương đương tiền | D18: ='02. Nhap lieu tai chinh_DD'!D18 | E18: ='02. Nhap lieu tai chinh_DD'!E18 | F18: ='02. Nhap lieu tai chinh_DD'!F18 | G18: ='02. Nhap lieu tai chinh_DD'!G18
B19: II. Các khoản đầu tư tài chính ngắn hạn | D19: =SUM(D20:D23) | E19: =SUM(E20:E23) | F19: =SUM(F20:F23) | G19: =SUM(G20:G23)
B20: 1. Chứng khoán đầu tư ngắn hạn | D20: ='02. Nhap lieu tai chinh_DD'!D20 | E20: ='02. Nhap lieu tai chinh_DD'!E20 | F20: ='02. Nhap lieu tai chinh_DD'!F20 | G20: ='02. Nhap lieu tai chinh_DD'!G20
B21: 2. Đầu tư ngắn hạn khác | D21: ='02. Nhap lieu tai chinh_DD'!D21 | E21: ='02. Nhap lieu tai chinh_DD'!E21 | F21: ='02. Nhap lieu tai chinh_DD'!F21 | G21: ='02. Nhap lieu tai chinh_DD'!G21
B22: 3. Dự phòng giảm giá đầu tư ngắn hạn | D22: ='02. Nhap lieu tai chinh_DD'!D22 | E22: ='02. Nhap lieu tai chinh_DD'!E22 | F22: ='02. Nhap lieu tai chinh_DD'!F22 | G22: ='02. Nhap lieu tai chinh_DD'!G22
B23: 4. Đầu tư tài chính ngắn hạn (trong trường hợp báo cáo không có thông tin) | D23: ='02. Nhap lieu tai chinh_DD'!D23 | E23: ='02. Nhap lieu tai chinh_DD'!E23 | F23: ='02. Nhap lieu tai chinh_DD'!F23 | G23: ='02. Nhap lieu tai chinh_DD'!G23
B24: II. Các khoản phải thu ngắn hạn | D24: =SUM(D25:D30) | E24: =SUM(E25:E30) | F24: =SUM(F25:F30) | G24: =SUM(G25:G30)
B25: 1. Phải thu khách hàng | D25: ='02. Nhap lieu tai chinh_DD'!D25 | E25: ='02. Nhap lieu tai chinh_DD'!E25 | F25: ='02. Nhap lieu tai chinh_DD'!F25 | G25: ='02. Nhap lieu tai chinh_DD'!G25
B26: 2. Trả trước cho người bán | D26: ='02. Nhap lieu tai chinh_DD'!D26 | E26: ='02. Nhap lieu tai chinh_DD'!E26 | F26: ='02. Nhap lieu tai chinh_DD'!F26 | G26: ='02. Nhap lieu tai chinh_DD'!G26
B27: 3. Phải thu nội bộ ngắn hạn | D27: ='02. Nhap lieu tai chinh_DD'!D27 | E27: ='02. Nhap lieu tai chinh_DD'!E27 | F27: ='02. Nhap lieu tai chinh_DD'!F27 | G27: ='02. Nhap lieu tai chinh_DD'!G27
B28: 4. Phải thu theo tiến độ kế hoạch hợp đồng xây dựng | D28: ='02. Nhap lieu tai chinh_DD'!D28 | E28: ='02. Nhap lieu tai chinh_DD'!E28 | F28: ='02. Nhap lieu tai chinh_DD'!F28 | G28: ='02. Nhap lieu tai chinh_DD'!G28
B29: 5. Các khoản phải thu khác | D29: ='02. Nhap lieu tai chinh_DD'!D29 | E29: ='02. Nhap lieu tai chinh_DD'!E29 | F29: ='02. Nhap lieu tai chinh_DD'!F29 | G29: ='02. Nhap lieu tai chinh_DD'!G29
B30: 6. Dự phòng phải thu ngắn hạn khó đòi | D30: ='02. Nhap lieu tai chinh_DD'!D30 | E30: ='02. Nhap lieu tai chinh_DD'!E30 | F30: ='02. Nhap lieu tai chinh_DD'!F30 | G30: ='02. Nhap lieu tai chinh_DD'!G30
B31: IV. Hàng tồn kho | D31: =SUM(D32:D42) | E31: =SUM(E32:E42) | F31: =SUM(F32:F42) | G31: =SUM(G32:G42)
B32: 1. Hàng mua đang đi đường | D32: ='02. Nhap lieu tai chinh_DD'!D32 | E32: ='02. Nhap lieu tai chinh_DD'!E32 | F32: ='02. Nhap lieu tai chinh_DD'!F32 | G32: ='02. Nhap lieu tai chinh_DD'!G32
B33: 2. Nguyên liệu, vật liệu | D33: ='02. Nhap lieu tai chinh_DD'!D33 | E33: ='02. Nhap lieu tai chinh_DD'!E33 | F33: ='02. Nhap lieu tai chinh_DD'!F33 | G33: ='02. Nhap lieu tai chinh_DD'!G33
B34: 3. Công cụ, dụng cụ | D34: ='02. Nhap lieu tai chinh_DD'!D34 | E34: ='02. Nhap lieu tai chinh_DD'!E34 | F34: ='02. Nhap lieu tai chinh_DD'!F34 | G34: ='02. Nhap lieu tai chinh_DD'!G34
B35: 4. Chi phí SX, KD dở dang | D35: ='02. Nhap lieu tai chinh_DD'!D35 | E35: ='02. Nhap lieu tai chinh_DD'!E35 | F35: ='02. Nhap lieu tai chinh_DD'!F35 | G35: ='02. Nhap lieu tai chinh_DD'!G35
B36: 5. Thành phẩm | D36: ='02. Nhap lieu tai chinh_DD'!D36 | E36: ='02. Nhap lieu tai chinh_DD'!E36 | F36: ='02. Nhap lieu tai chinh_DD'!F36 | G36: ='02. Nhap lieu tai chinh_DD'!G36
B37: 6. Hàng hóa | D37: ='02. Nhap lieu tai chinh_DD'!D37 | E37: ='02. Nhap lieu tai chinh_DD'!E37 | F37: ='02. Nhap lieu tai chinh_DD'!F37 | G37: ='02. Nhap lieu tai chinh_DD'!G37
B38: 7. Hàng gửi đi bán | D38: ='02. Nhap lieu tai chinh_DD'!D38 | E38: ='02. Nhap lieu tai chinh_DD'!E38 | F38: ='02. Nhap lieu tai chinh_DD'!F38 | G38: ='02. Nhap lieu tai chinh_DD'!G38
B39: 8. Hàng hóa kho bảo thuế | D39: ='02. Nhap lieu tai chinh_DD'!D39 | E39: ='02. Nhap lieu tai chinh_DD'!E39 | F39: ='02. Nhap lieu tai chinh_DD'!F39 | G39: ='02. Nhap lieu tai chinh_DD'!G39
B40: 9. Hàng hóa bất động sản | D40: ='02. Nhap lieu tai chinh_DD'!D40 | E40: ='02. Nhap lieu tai chinh_DD'!E40 | F40: ='02. Nhap lieu tai chinh_DD'!F40 | G40: ='02. Nhap lieu tai chinh_DD'!G40
B41: 10. Dự phòng giảm giá hàng tồn kho | D41: ='02. Nhap lieu tai chinh_DD'!D41 | E41: ='02. Nhap lieu tai chinh_DD'!E41 | F41: ='02. Nhap lieu tai chinh_DD'!F41 | G41: ='02. Nhap lieu tai chinh_DD'!G41
B42: 11. Hàng tồn kho (trong trường hợp báo cáo không có thông tin chi tiết) | D42: ='02. Nhap lieu tai chinh_DD'!D42 | E42: ='02. Nhap lieu tai chinh_DD'!E42 | F42: ='02. Nhap lieu tai chinh_DD'!F42 | G42: ='02. Nhap lieu tai chinh_DD'!G42
B43: V. Tài sản ngắn hạn khác | D43: =SUM(D44:D48) | E43: =SUM(E44:E48) | F43: =SUM(F44:F48) | G43: =SUM(G44:G48)
B44: 1. Chi phí trả trước ngắn hạn | D44: ='02. Nhap lieu tai chinh_DD'!D44 | E44: ='02. Nhap lieu tai chinh_DD'!E44 | F44: ='02. Nhap lieu tai chinh_DD'!F44 | G44: ='02. Nhap lieu tai chinh_DD'!G44
B45: 2. Thuế GTGT được khấu trừ | D45: ='02. Nhap lieu tai chinh_DD'!D45 | E45: ='02. Nhap lieu tai chinh_DD'!E45 | F45: ='02. Nhap lieu tai chinh_DD'!F45 | G45: ='02. Nhap lieu tai chinh_DD'!G45
B46: 3. Thuế và các khoản khác phải thu Nhà nước | D46: ='02. Nhap lieu tai chinh_DD'!D46 | E46: ='02. Nhap lieu tai chinh_DD'!E46 | F46: ='02. Nhap lieu tai chinh_DD'!F46 | G46: ='02. Nhap lieu tai chinh_DD'!G46
B47: 4. Giao dịch mua bán lại trái phiếu chính phủ | D47: ='02. Nhap lieu tai chinh_DD'!D47 | E47: ='02. Nhap lieu tai chinh_DD'!E47 | F47: ='02. Nhap lieu tai chinh_DD'!F47 | G47: ='02. Nhap lieu tai chinh_DD'!G47
B48: 5. Tài sản ngắn hạn khác | D48: ='02. Nhap lieu tai chinh_DD'!D48 | E48: ='02. Nhap lieu tai chinh_DD'!E48 | F48: ='02. Nhap lieu tai chinh_DD'!F48 | G48: ='02. Nhap lieu tai chinh_DD'!G48
B49: B. TÀI SẢN DÀI HẠN | D49: =D50+D56+D67+D70+D76+D82 | E49: =E50+E56+E67+E70+E76+E82 | F49: =F50+F56+F67+F70+F76+F82 | G49: =G50+G56+G67+G70+G76+G82
B50: I. Các khoản phải thu dài hạn | D50: =SUM(D51:D55) | E50: =SUM(E51:E55) | F50: =SUM(F51:F55) | G50: =SUM(G51:G55)
B51: 1. Phải thu dài hạn của khách hàng | D51: ='02. Nhap lieu tai chinh_DD'!D51 | E51: ='02. Nhap lieu tai chinh_DD'!E51 | F51: ='02. Nhap lieu tai chinh_DD'!F51 | G51: ='02. Nhap lieu tai chinh_DD'!G51
B52: 2. Vốn kinh doanh ở đơn vị trực thuộc | D52: ='02. Nhap lieu tai chinh_DD'!D52 | E52: ='02. Nhap lieu tai chinh_DD'!E52 | F52: ='02. Nhap lieu tai chinh_DD'!F52 | G52: ='02. Nhap lieu tai chinh_DD'!G52
B53: 3. Phải thu dài hạn nội bộ | D53: ='02. Nhap lieu tai chinh_DD'!D53 | E53: ='02. Nhap lieu tai chinh_DD'!E53 | F53: ='02. Nhap lieu tai chinh_DD'!F53 | G53: ='02. Nhap lieu tai chinh_DD'!G53
B54: 4. Phải thu dài hạn khác | D54: ='02. Nhap lieu tai chinh_DD'!D54 | E54: ='02. Nhap lieu tai chinh_DD'!E54 | F54: ='02. Nhap lieu tai chinh_DD'!F54 | G54: ='02. Nhap lieu tai chinh_DD'!G54
B55: 5. Dự phòng phải thu dài hạn khó đòi | D55: ='02. Nhap lieu tai chinh_DD'!D55 | E55: ='02. Nhap lieu tai chinh_DD'!E55 | F55: ='02. Nhap lieu tai chinh_DD'!F55 | G55: ='02. Nhap lieu tai chinh_DD'!G55
B56: II. Tài sản cố định | D56: =D57+D60+D63+D66 | E56: =E57+E60+E63+E66 | F56: =F57+F60+F63+F66 | G56: =G57+G60+G63+G66
B57: 1. Tài sản cố định hữu hình | D57: =SUM(D58:D59) | E57: =SUM(E58:E59) | F57: =SUM(F58:F59) | G57: =SUM(G58:G59)
B58: - Nguyên giá | D58: ='02. Nhap lieu tai chinh_DD'!D58 | E58: ='02. Nhap lieu tai chinh_DD'!E58 | F58: ='02. Nhap lieu tai chinh_DD'!F58 | G58: ='02. Nhap lieu tai chinh_DD'!G58
B59: - Giá trị hao mòn lũy kế | D59: ='02. Nhap lieu tai chinh_DD'!D59 | E59: ='02. Nhap lieu tai chinh_DD'!E59 | F59: ='02. Nhap lieu tai chinh_DD'!F59 | G59: ='02. Nhap lieu tai chinh_DD'!G59
B60: 2. Tài sản cố định thuê tài chính | D60: =SUM(D61:D62) | E60: =SUM(E61:E62) | F60: =SUM(F61:F62) | G60: =SUM(G61:G62)
B61: - Nguyên giá | D61: ='02. Nhap lieu tai chinh_DD'!D61 | E61: ='02. Nhap lieu tai chinh_DD'!E61 | F61: ='02. Nhap lieu tai chinh_DD'!F61 | G61: ='02. Nhap lieu tai chinh_DD'!G61
B62: - Giá trị hao mòn lũy kế | D62: ='02. Nhap lieu tai chinh_DD'!D62 | E62: ='02. Nhap lieu tai chinh_DD'!E62 | F62: ='02. Nhap lieu tai chinh_DD'!F62 | G62: ='02. Nhap lieu tai chinh_DD'!G62
B63: 3. Tài sản cố định vô hình | D63: =SUM(D64:D65) | E63: =SUM(E64:E65) | F63: =SUM(F64:F65) | G63: =SUM(G64:G65)
B64: - Nguyên giá | D64: ='02. Nhap lieu tai chinh_DD'!D64 | E64: ='02. Nhap lieu tai chinh_DD'!E64 | F64: ='02. Nhap lieu tai chinh_DD'!F64 | G64: ='02. Nhap lieu tai chinh_DD'!G64
B65: - Giá trị hao mòn lũy kế | D65: ='02. Nhap lieu tai chinh_DD'!D65 | E65: ='02. Nhap lieu tai chinh_DD'!E65 | F65: ='02. Nhap lieu tai chinh_DD'!F65 | G65: ='02. Nhap lieu tai chinh_DD'!G65
B66: 4. Chi phí xây dựng cơ bản dở dang | D66: ='02. Nhap lieu tai chinh_DD'!D66 | E66: ='02. Nhap lieu tai chinh_DD'!E66 | F66: ='02. Nhap lieu tai chinh_DD'!F66 | G66: ='02. Nhap lieu tai chinh_DD'!G66
B67: III. Bất động sản đầu tư | D67: =SUM(D68:D69) | E67: =SUM(E68:E69) | F67: =SUM(F68:F69) | G67: =SUM(G68:G69)
B68: - Nguyên giá | D68: ='02. Nhap lieu tai chinh_DD'!D68 | E68: ='02. Nhap lieu tai chinh_DD'!E68 | F68: ='02. Nhap lieu tai chinh_DD'!F68 | G68: ='02. Nhap lieu tai chinh_DD'!G68
B69: - Giá trị hao mòn lũy kế | D69: ='02. Nhap lieu tai chinh_DD'!D69 | E69: ='02. Nhap lieu tai chinh_DD'!E69 | F69: ='02. Nhap lieu tai chinh_DD'!F69 | G69: ='02. Nhap lieu tai chinh_DD'!G69
B70: IV. Các khoản đầu tư tài chính dài hạn | D70: =SUM(D71:D75) | E70: =SUM(E71:E75) | F70: =SUM(F71:F75) | G70: =SUM(G71:G75)
B71: 1. Đầu tư vào công ty con | D71: ='02. Nhap lieu tai chinh_DD'!D71 | E71: ='02. Nhap lieu tai chinh_DD'!E71 | F71: ='02. Nhap lieu tai chinh_DD'!F71 | G71: ='02. Nhap lieu tai chinh_DD'!G71
B72: 2. Đầu tư vào công ty liên kết, liên doanh | D72: ='02. Nhap lieu tai chinh_DD'!D72 | E72: ='02. Nhap lieu tai chinh_DD'!E72 | F72: ='02. Nhap lieu tai chinh_DD'!F72 | G72: ='02. Nhap lieu tai chinh_DD'!G72
B73: 3. Đầu tư dài hạn khác | D73: ='02. Nhap lieu tai chinh_DD'!D73 | E73: ='02. Nhap lieu tai chinh_DD'!E73 | F73: ='02. Nhap lieu tai chinh_DD'!F73 | G73: ='02. Nhap lieu tai chinh_DD'!G73
B74: 4. Dự phòng giảm giá đầu tư tài chính dài hạn | D74: ='02. Nhap lieu tai chinh_DD'!D74 | E74: ='02. Nhap lieu tai chinh_DD'!E74 | F74: ='02. Nhap lieu tai chinh_DD'!F74 | G74: ='02. Nhap lieu tai chinh_DD'!G74
B75: 5. Đầu tư tài chính dài hạn (trong trường hợp báo cáo không có thông tin) | D75: ='02. Nhap lieu tai chinh_DD'!D75 | E75: ='02. Nhap lieu tai chinh_DD'!E75 | F75: ='02. Nhap lieu tai chinh_DD'!F75 | G75: ='02. Nhap lieu tai chinh_DD'!G75
B76: V. Tài sản dài hạn khác | D76: =SUM(D77:D81) | E76: =SUM(E77:E81) | F76: =SUM(F77:F81) | G76: =SUM(G77:G81)
B77: 1. Chi phí trả trước dài hạn | D77: ='02. Nhap lieu tai chinh_DD'!D77 | E77: ='02. Nhap lieu tai chinh_DD'!E77 | F77: ='02. Nhap lieu tai chinh_DD'!F77 | G77: ='02. Nhap lieu tai chinh_DD'!G77
B78: 2. Tài sản thuế thu nhập hoãn lại | D78: ='02. Nhap lieu tai chinh_DD'!D78 | E78: ='02. Nhap lieu tai chinh_DD'!E78 | F78: ='02. Nhap lieu tai chinh_DD'!F78 | G78: ='02. Nhap lieu tai chinh_DD'!G78
B79: 3. Phải thu dài hạn | D79: ='02. Nhap lieu tai chinh_DD'!D79 | E79: ='02. Nhap lieu tai chinh_DD'!E79 | F79: ='02. Nhap lieu tai chinh_DD'!F79 | G79: ='02. Nhap lieu tai chinh_DD'!G79
B80: 4. Tài sản dài hạn khác | D80: ='02. Nhap lieu tai chinh_DD'!D80 | E80: ='02. Nhap lieu tai chinh_DD'!E80 | F80: ='02. Nhap lieu tai chinh_DD'!F80 | G80: ='02. Nhap lieu tai chinh_DD'!G80
B81: 5. Dự phòng phải thu dài hạn khó đòi | D81: ='02. Nhap lieu tai chinh_DD'!D81 | E81: ='02. Nhap lieu tai chinh_DD'!E81 | F81: ='02. Nhap lieu tai chinh_DD'!F81 | G81: ='02. Nhap lieu tai chinh_DD'!G81
B82: VI. Lợi thế thương mại | D82: ='02. Nhap lieu tai chinh_DD'!D82 | E82: ='02. Nhap lieu tai chinh_DD'!E82 | F82: ='02. Nhap lieu tai chinh_DD'!F82 | G82: ='02. Nhap lieu tai chinh_DD'!G82
B83: TỔNG NGUỒN VỐN | D83: =D84+D112 | E83: =E84+E112 | F83: =F84+F112 | G83: =G84+G112
B84: A. NỢ PHẢI TRẢ | D84: =D85+D100 | E84: =E85+E100 | F84: =F85+F100 | G84: =G85+G100
B85: I. Nợ ngắn hạn | D85: =SUM(D86:D99)-D87 | E85: =SUM(E86:E99)-E87 | F85: =SUM(F86:F99)-F87 | G85: =SUM(G86:G99)-G87
B86: 1. Vay và nợ ngắn hạn | D86: ='02. Nhap lieu tai chinh_DD'!D86 | E86: ='02. Nhap lieu tai chinh_DD'!E86 | F86: ='02. Nhap lieu tai chinh_DD'!F86 | G86: ='02. Nhap lieu tai chinh_DD'!G86
B87: - Tr/đó: vay MSB | D87: ='02. Nhap lieu tai chinh_DD'!D87 | E87: ='02. Nhap lieu tai chinh_DD'!E87 | F87: ='02. Nhap lieu tai chinh_DD'!F87 | G87: ='02. Nhap lieu tai chinh_DD'!G87
B88: 2. Phải trả người bán | D88: ='02. Nhap lieu tai chinh_DD'!D88 | E88: ='02. Nhap lieu tai chinh_DD'!E88 | F88: ='02. Nhap lieu tai chinh_DD'!F88 | G88: ='02. Nhap lieu tai chinh_DD'!G88
B89: 3. Người mua trả tiền trước | D89: ='02. Nhap lieu tai chinh_DD'!D89 | E89: ='02. Nhap lieu tai chinh_DD'!E89 | F89: ='02. Nhap lieu tai chinh_DD'!F89 | G89: ='02. Nhap lieu tai chinh_DD'!G89
B90: 4. Thuế và các khoản phải nộp Nhà nước | D90: ='02. Nhap lieu tai chinh_DD'!D90 | E90: ='02. Nhap lieu tai chinh_DD'!E90 | F90: ='02. Nhap lieu tai chinh_DD'!F90 | G90: ='02. Nhap lieu tai chinh_DD'!G90
B91: 5. Phải trả người lao động | D91: ='02. Nhap lieu tai chinh_DD'!D91 | E91: ='02. Nhap lieu tai chinh_DD'!E91 | F91: ='02. Nhap lieu tai chinh_DD'!F91 | G91: ='02. Nhap lieu tai chinh_DD'!G91
B92: 6. Chi phí phải trả | D92: ='02. Nhap lieu tai chinh_DD'!D92 | E92: ='02. Nhap lieu tai chinh_DD'!E92 | F92: ='02. Nhap lieu tai chinh_DD'!F92 | G92: ='02. Nhap lieu tai chinh_DD'!G92
B93: 7. Phải trả nội bộ | D93: ='02. Nhap lieu tai chinh_DD'!D93 | E93: ='02. Nhap lieu tai chinh_DD'!E93 | F93: ='02. Nhap lieu tai chinh_DD'!F93 | G93: ='02. Nhap lieu tai chinh_DD'!G93
B94: 8. Phải trả theo tiến độ kế hoạch hợp đồng xây dựng | D94: ='02. Nhap lieu tai chinh_DD'!D94 | E94: ='02. Nhap lieu tai chinh_DD'!E94 | F94: ='02. Nhap lieu tai chinh_DD'!F94 | G94: ='02. Nhap lieu tai chinh_DD'!G94
B95: 9. Các khoản phải trả, phải nộp ngắn hạn khác | D95: ='02. Nhap lieu tai chinh_DD'!D95 | E95: ='02. Nhap lieu tai chinh_DD'!E95 | F95: ='02. Nhap lieu tai chinh_DD'!F95 | G95: ='02. Nhap lieu tai chinh_DD'!G95
B96: 10. Dự phòng phải trả ngắn hạn | D96: ='02. Nhap lieu tai chinh_DD'!D96 | E96: ='02. Nhap lieu tai chinh_DD'!E96 | F96: ='02. Nhap lieu tai chinh_DD'!F96 | G96: ='02. Nhap lieu tai chinh_DD'!G96
B97: 11. Quỹ khen thưởng, phúc lợi | D97: ='02. Nhap lieu tai chinh_DD'!D97 | E97: ='02. Nhap lieu tai chinh_DD'!E97 | F97: ='02. Nhap lieu tai chinh_DD'!F97 | G97: ='02. Nhap lieu tai chinh_DD'!G97
... B99: 13. Doanh thu chưa thực hiện ngắn hạn | D99: ='02. Nhap lieu tai chinh_DD'!D99 | E99: ='02. Nhap lieu tai chinh_DD'!E99 | F99: ='02. Nhap lieu tai chinh_DD'!F99 | G99: ='02. Nhap lieu tai chinh_DD'!G99
B100: II. Nợ dài hạn | D100: =SUM(D101:D111)-D105 | E100: =SUM(E101:E111)-E105 | F100: =SUM(F101:F111)-F105 | G100: =SUM(G101:G111)-G105
B101: 1. Phải trả dài hạn người bán | D101: ='02. Nhap lieu tai chinh_DD'!D101 | E101: ='02. Nhap lieu tai chinh_DD'!E101 | F101: ='02. Nhap lieu tai chinh_DD'!F101 | G101: ='02. Nhap lieu tai chinh_DD'!G101
...

Sheet 06. Phan tich tai chinh_DD
J1: MSB
J2: TNR Tower, 54A Nguyễn Chí Thanh, Đống Đa, Hà Nội
A4: PHỤ LỤC: PHÂN TÍCH TÀI CHÍNH
A5: (Kèm theo Tờ trình số ngày / / )
A7: ='[1]01. Thong tin chung'!B3 | B7: =C7-1 | C7: =D7-1 | D7: ='01. Thong tin chung'!B7 | G7: ='01. Thong tin chung'!B8 | I7: ="Dự kiến năm"& D7+1 | J7: Nội dung phân tích (nếu có)
A8: ="Đơn vị tính: "&'[1]01. Thong tin chung'!B6 | B8: =IF(OR(B9-B81>1,B9-B81<-1),"Chưa cân số","") | C8: =IF(OR(C9-C81>1,C9-C81<-1),"Chưa cân số","") | D8: =IF(OR(D9-D81>1,D9-D81<-1),"Chưa cân số","") | E8: Tỷ trọng | F8: Tăng trưởng | G8: =IF(OR(G9-G81>1,G9-G81<-1),"Chưa cân số","") | H8: Tỷ trọng | I8: =IF(OR(I9-I81>1,I9-I81<-1),"Chưa cân số","")
A9: TỔNG TÀI SẢN | B9: =B10+B47 | C9: =C10+C47 | D9: =D10+D47 | E9: =IF($D$9<>0,D9/$D$9,"") | F9: =IF(C9<>0,(D9-C9)/C9,"") | G9: =G10+G47 | H9: =IF($G$9<>0,G9/$G$9,"") | I9: =I10+I47
A10: A. TÀI SẢN NGẮN HẠN | B10: =B11+B17+B22+B29+B41 | C10: =C11+C17+C22+C29+C41 | D10: =D11+D17+D22+D29+D41 | E10: =IF($D$9<>0,D10/$D$9,"") | F10: =IF(C10<>0,(D10-C10)/C10,"") | G10: =G11+G17+G22+G29+G41 | H10: =IF($G$9<>0,G10/$G$9,"") | I10: =I11+I17+I22+I29+I41
A11: I. Tiền và các khoản tương đương tiền | B11: =SUM(B12:B16) | C11: =SUM(C12:C16) | D11: =SUM(D12:D16) | E11: =IF($D$10<>0,D11/$D$10," ") | F11: =IF(C11<>0,(D11-C11)/C11,"") | G11: =SUM(G12:G16) | H11: =IF($G$10<>0,G11/$G$10," ") | I11: =IF(TRIM('03. Dulieutaichinhlamsach_DD'!$G$2)="VND",'03. Dulieutaichinhlamsach_DD'!H13/10^6,'03. Dulieutaichinhlamsach_DD'!H13)
A12: 1. Tiền mặt | B12: =IF(TRIM('03. Dulieutaichinhlamsach_DD'!$G$2)="VND",'03. Dulieutaichinhlamsach_DD'!D14/10^6,'03. Dulieutaichinhlamsach_DD'!D14) | C12: =IF(TRIM('03. Dulieutaichinhlamsach_DD'!$G$2)="VND",'03. Dulieutaichinhlamsach_DD'!E14/10^6,'03. Dulieutaichinhlamsach_DD'!E14) | D12: =IF(TRIM('03. Dulieutaichinhlamsach_DD'!$G$2)="VND",'03. Dulieutaichinhlamsach_DD'!F14/10^6,'03. Dulieutaichinhlamsach_DD'!F14) | E12: =IF($D$10<>0,D12/$D$10," ") | F12: =IF(C12<>0,(D12-C12)/C12,"") | G12: =IF(TRIM('03. Dulieutaichinhlamsach_DD'!$G$2)="VND",'03. Dulieutaichinhlamsach_DD'!G14/10^6,'03. Dulieutaichinhlamsach_DD'!G14) | H12: =IF($G$10<>0,G12/$G$10," ") | I12: =IF(TRIM('03. Dulieutaichinhlamsach_DD'!$G$2)="VND",'03. Dulieutaichinhlamsach_DD'!H14/10^6,'03. Dulieutaichinhlamsach_DD'!H14)
A13: 2. Tiền gửi ngân hàng | B13: =IF(TRIM('03. Dulieutaichinhlamsach_DD'!$G$2)="VND",'03. Dulieutaichinhlamsach_DD'!D15/10^6,'03. Dulieutaichinhlamsach_DD'!D15) | C13: =IF(TRIM('03. Dulieutaichinhlamsach_DD'!$G$2)="VND",'03. Dulieutaichinhlamsach_DD'!E15/10^6,'03. Dulieutaichinhlamsach_DD'!E15) | D13: =IF(TRIM('03. Dulieutaichinhlamsach_DD'!$G$2)="VND",'03. Dulieutaichinhlamsach_DD'!F15/10^6,'03. Dulieutaichinhlamsach_DD'!F15) | E13: =IF($D$10<>0,D13/$D$10," ") | F13: =IF(C13<>0,(D13-C13)/C13,"") | G13: =IF(TRIM('03. Dulieutaichinhlamsach_DD'!$G$2)="VND",'03. Dulieutaichinhlamsach_DD'!G15/10^6,'03. Dulieutaichinhlamsach_DD'!G15) | H13: =IF($G$10<>0,G13/$G$10," ") | I13: =IF(TRIM('03. Dulieutaichinhlamsach_DD'!$G$2)="VND",'03. Dulieutaichinhlamsach_DD'!H15/10^6,'03. Dulieutaichinhlamsach_DD'!H15)
A14: 3. Tiền đang chuyển | B14: =IF(TRIM('03. Dulieutaichinhlamsach_DD'!$G$2)="VND",'03. Dulieutaichinhlamsach_DD'!D16/10^6,'03. Dulieutaichinhlamsach_DD'!D16) | C14: =IF(TRIM('03. Dulieutaichinhlamsach_DD'!$G$2)="VND",'03. Dulieutaichinhlamsach_DD'!E16/10^6,'03. Dulieutaichinhlamsach_DD'!E16) | D14: =IF(TRIM('03. Dulieutaichinhlamsach_DD'!$G$2)="VND",'03. Dulieutaichinhlamsach_DD'!F16/10^6,'03. Dulieutaichinhlamsach_DD'!F16) | E14: =IF($D$10<>0,D14/$D$10," ") | F14: =IF(C14<>0,(D14-C14)/C14,"") | G14: =IF(TRIM('03. Dulieutaichinhlamsach_DD'!$G$2)="VND",'03. Dulieutaichinhlamsach_DD'!G16/10^6,'03. Dulieutaichinhlamsach_DD'!G16) | H14: =IF($G$10<>0,G14/$G$10," ") | I14: =IF(TRIM('03. Dulieutaichinhlamsach_DD'!$G$2)="VND",'03. Dulieutaichinhlamsach_DD'!H16/10^6,'03. Dulieutaichinhlamsach_DD'!H16)
A15: 4. Tiền (trong trường hợp Báo cáo không có 3 thông tin trên) | B15: =IF(TRIM('03. Dulieutaichinhlamsach_DD'!$G$2)="VND",'03. Dulieutaichinhlamsach_DD'!D17/10^6,'03. Dulieutaichinhlamsach_DD'!D17) | C15: =IF(TRIM('03. Dulieutaichinhlamsach_DD'!$G$2)="VND",'03. Dulieutaichinhlamsach_DD'!E17/10^6,'03. Dulieutaichinhlamsach_DD'!E17) | D15: =IF(TRIM('03. Dulieutaichinhlamsach_DD'!$G$2)="VND",'03. Dulieutaichinhlamsach_DD'!F17/10^6,'03. Dulieutaichinhlamsach_DD'!F17) | E15: =IF($D$10<>0,D15/$D$10," ") | F15: =IF(C15<>0,(D15-C15)/C15,"") | G15: =IF(TRIM('03. Dulieutaichinhlamsach_DD'!$G$2)="VND",'03. Dulieutaichinhlamsach_DD'!G17/10^6,'03. Dulieutaichinhlamsach_DD'!G17) | H15: =IF($G$10<>0,G15/$G$10," ") | I15: =IF(TRIM('03. Dulieutaichinhlamsach_DD'!$G$2)="VND",'03. Dulieutaichinhlamsach_DD'!H17/10^6,'03. Dulieutaichinhlamsach_DD'!H17)
A16: 5. Các khoản tương đương tiền | B16: =IF(TRIM('03. Dulieutaichinhlamsach_DD'!$G$2)="VND",'03. Dulieutaichinhlamsach_DD'!D18/10^6,'03. Dulieutaichinhlamsach_DD'!D18) | C16: =IF(TRIM('03. Dulieutaichinhlamsach_DD'!$G$2)="VND",'03. Dulieutaichinhlamsach_DD'!E18/10^6,'03. Dulieutaichinhlamsach_DD'!E18) | D16: =IF(TRIM('03. Dulieutaichinhlamsach_DD'!$G$2)="VND",'03. Dulieutaichinhlamsach_DD'!F18/10^6,'03. Dulieutaichinhlamsach_DD'!F18) | E16: =IF($D$10<>0,D16/$D$10," ") | F16: =IF(C16<>0,(D16-C16)/C16,"") | G16: =IF(TRIM('03. Dulieutaichinhlamsach_DD'!$G$2)="VND",'03. Dulieutaichinhlamsach_DD'!G18/10^6,'03. Dulieutaichinhlamsach_DD'!G18) | H16: =IF($G$10<>0,G16/$G$10," ") | I16: =IF(TRIM('03. Dulieutaichinhlamsach_DD'!$G$2)="VND",'03. Dulieutaichinhlamsach_DD'!H18/10^6,'03. Dulieutaichinhlamsach_DD'!H18)
A17: II. Các khoản đầu tư tài chính ngắn hạn | B17: =SUM(B18:B21) | C17: =SUM(C18:C21) | D17: =SUM(D18:D21) | E17: =IF($D$10<>0,D17/$D$10," ") | F17: =IF(C17<>0,(D17-C17)/C17,"") | G17: =SUM(G18:G21) | H17: =IF($G$10<>0,G17/$G$10," ") | I17: =SUM(I18:I21)
A18: 1. Chứng khoán đầu tư ngắn hạn | B18: =IF(TRIM('03. Dulieutaichinhlamsach_DD'!$G$2)="VND",'03. Dulieutaichinhlamsach_DD'!D20/10^6,'03. Dulieutaichinhlamsach_DD'!D20) | C18: =IF(TRIM('03. Dulieutaichinhlamsach_DD'!$G$2)="VND",'03. Dulieutaichinhlamsach_DD'!E20/10^6,'03. Dulieutaichinhlamsach_DD'!E20) | D18: =IF(TRIM('03. Dulieutaichinhlamsach_DD'!$G$2)="VND",'03. Dulieutaichinhlamsach_DD'!F20/10^6,'03. Dulieutaichinhlamsach_DD'!F20) | E18: =IF($D$10<>0,D18/$D$10," ") | F18: =IF(C18<>0,(D18-C18)/C18,"") | G18: =IF(TRIM('03. Dulieutaichinhlamsach_DD'!$G$2)="VND",'03. Dulieutaichinhlamsach_DD'!G20/10^6,'03. Dulieutaichinhlamsach_DD'!G20) | H18: =IF($G$10<>0,G18/$G$10," ") | I18: =IF(TRIM('03. Dulieutaichinhlamsach_DD'!$G$2)="VND",'03. Dulieutaichinhlamsach_DD'!H20/10^6,'03. Dulieutaichinhlamsach_DD'!H20)
A19: 2. Đầu tư ngắn hạn khác | B19: =IF(TRIM('03. Dulieutaichinhlamsach_DD'!$G$2)="VND",'03. Dulieutaichinhlamsach_DD'!D21/10^6,'03. Dulieutaichinhlamsach_DD'!D21) | C19: =IF(TRIM('03. Dulieutaichinhlamsach_DD'!$G$2)="VND",'03. Dulieutaichinhlamsach_DD'!E21/10^6,'03. Dulieutaichinhlamsach_DD'!E21) | D19: =IF(TRIM('03. Dulieutaichinhlamsach_DD'!$G$2)="VND",'03. Dulieutaichinhlamsach_DD'!F21/10^6,'03. Dulieutaichinhlamsach_DD'!F21) | E19: =IF($D$10<>0,D19/$D$10," ") | F19: =IF(C19<>0,(D19-C19)/C19,"") | G19: =IF(TRIM('03. Dulieutaichinhlamsach_DD'!$G$2)="VND",'03. Dulieutaichinhlamsach_DD'!G21/10^6,'03. Dulieutaichinhlamsach_DD'!G21) | H19: =IF($G$10<>0,G19/$G$10," ") | I19: =IF(TRIM('03. Dulieutaichinhlamsach_DD'!$G$2)="VND",'03. Dulieutaichinhlamsach_DD'!H21/10^6,'03. Dulieutaichinhlamsach_DD'!H21)
A20: 3. Dự phòng giảm giá đầu tư ngắn hạn | B20: =IF(TRIM('03. Dulieutaichinhlamsach_DD'!$G$2)="VND",'03. Dulieutaichinhlamsach_DD'!D22/10^6,'03. Dulieutaichinhlamsach_DD'!D22) | C20: =IF(TRIM('03. Dulieutaichinhlamsach_DD'!$G$2)="VND",'03. Dulieutaichinhlamsach_DD'!E22/10^6,'03. Dulieutaichinhlamsach_DD'!E22) | D20: =IF(TRIM('03. Dulieutaichinhlamsach_DD'!$G$2)="VND",'03. Dulieutaichinhlamsach_DD'!F22/10^6,'03. Dulieutaichinhlamsach_DD'!F22) | E20: =IF($D$10<>0,D20/$D$10," ") | F20: =IF(C20<>0,(D20-C20)/C20,"") | G20: =IF(TRIM('03. Dulieutaichinhlamsach_DD'!$G$2)="VND",'03. Dulieutaichinhlamsach_DD'!G22/10^6,'03. Dulieutaichinhlamsach_DD'!G22) | H20: =IF($G$10<>0,G20/$G$10," ") | I20: =IF(TRIM('03. Dulieutaichinhlamsach_DD'!$G$2)="VND",'03. Dulieutaichinhlamsach_DD'!H22/10^6,'03. Dulieutaichinhlamsach_DD'!H22)
A21: 4. Đầu tư tài chính ngắn hạn (trong trường hợp báo cáo không có thông tin) | B21: =IF(TRIM('03. Dulieutaichinhlamsach_DD'!$G$2)="VND",'03. Dulieutaichinhlamsach_DD'!D23/10^6,'03. Dulieutaichinhlamsach_DD'!D23) | C21: =IF(TRIM('03. Dulieutaichinhlamsach_DD'!$G$2)="VND",'03. Dulieutaichinhlamsach_DD'!E23/10^6,'03. Dulieutaichinhlamsach_DD'!E23) | D21: =IF(TRIM('03. Dulieutaichinhlamsach_DD'!$G$2)="VND",'03. Dulieutaichinhlamsach_DD'!F23/10^6,'03. Dulieutaichinhlamsach_DD'!F23) | E21: =IF($D$10<>0,D21/$D$10," ") | F21: =IF(C21<>0,(D21-C21)/C21,"") | G21: =IF(TRIM('03. Dulieutaichinhlamsach_DD'!$G$2)="VND",'03. Dulieutaichinhlamsach_DD'!G23/10^6,'03. Dulieutaichinhlamsach_DD'!G23) | H21: =IF($G$10<>0,G21/$G$10," ") | I21: =IF(TRIM('03. Dulieutaichinhlamsach_DD'!$G$2)="VND",'03. Dulieutaichinhlamsach_DD'!H23/10^6,'03. Dulieutaichinhlamsach_DD'!H23)
A22: III. Các khoản phải thu ngắn hạn | B22: =SUM(B23:B28) | C22: =SUM(C23:C28) | D22: =SUM(D23:D28) | E22: =IF($D$10<>0,D22/$D$10," ") | F22: =IF(C22<>0,(D22-C22)/C22,"") | G22: =SUM(G23:G28) | H22: =IF($G$10<>0,G22/$G$10," ") | I22: =SUM(I23:I28)
A23: 1. Phải thu khách hàng | B23: =IF(TRIM('03. Dulieutaichinhlamsach_DD'!$G$2)="VND",'03. Dulieutaichinhlamsach_DD'!D25/10^6,'03. Dulieutaichinhlamsach_DD'!D25) | C23: =IF(TRIM('03. Dulieutaichinhlamsach_DD'!$G$2)="VND",'03. Dulieutaichinhlamsach_DD'!E25/10^6,'03. Dulieutaichinhlamsach_DD'!E25) | D23: =IF(TRIM('03. Dulieutaichinhlamsach_DD'!$G$2)="VND",'03. Dulieutaichinhlamsach_DD'!F25/10^6,'03. Dulieutaichinhlamsach_DD'!F25) | E23: =IF($D$10<>0,D23/$D$10," ") | F23: =IF(C23<>0,(D23-C23)/C23,"") | G23: =IF(TRIM('03. Dulieutaichinhlamsach_DD'!$G$2)="VND",'03. Dulieutaichinhlamsach_DD'!G25/10^6,'03. Dulieutaichinhlamsach_DD'!G25) | H23: =IF($G$10<>0,G23/$G$10," ") | I23: =IF(TRIM('03. Dulieutaichinhlamsach_DD'!$G$2)="VND",'03. Dulieutaichinhlamsach_DD'!H25/10^6,'03. Dulieutaichinhlamsach_DD'!H25)
A24: 2. Trả trước cho người bán | B24: =IF(TRIM('03. Dulieutaichinhlamsach_DD'!$G$2)="VND",'03. Dulieutaichinhlamsach_DD'!D26/10^6,'03. Dulieutaichinhlamsach_DD'!D26) | C24: =IF(TRIM('03. Dulieutaichinhlamsach_DD'!$G$2)="VND",'03. Dulieutaichinhlamsach_DD'!E26/10^6,'03. Dulieutaichinhlamsach_DD'!E26) | D24: =IF(TRIM('03. Dulieutaichinhlamsach_DD'!$G$2)="VND",'03. Dulieutaichinhlamsach_DD'!F26/10^6,'03. Dulieutaichinhlamsach_DD'!F26) | E24: =IF($D$10<>0,D24/$D$10," ") | F24: =IF(C24<>0,(D24-C24)/C24,"") | G24: =IF(TRIM('03. Dulieutaichinhlamsach_DD'!$G$2)="VND",'03. Dulieutaichinhlamsach_DD'!G26/10^6,'03. Dulieutaichinhlamsach_DD'!G26) | H24: =IF($G$10<>0,G24/$G$10," ") | I24: =IF(TRIM('03. Dulieutaichinhlamsach_DD'!$G$2)="VND",'03. Dulieutaichinhlamsach_DD'!H26/10^6,'03. Dulieutaichinhlamsach_DD'!H26)
A25: 3. Phải thu nội bộ ngắn hạn | B25: =IF(TRIM('03. Dulieutaichinhlamsach_DD'!$G$2)="VND",'03. Dulieutaichinhlamsach_DD'!D27/10^6,'03. Dulieutaichinhlamsach_DD'!D27) | C25: =IF(TRIM('03. Dulieutaichinhlamsach_DD'!$G$2)="VND",'03. Dulieutaichinhlamsach_DD'!E27/10^6,'03. Dulieutaichinhlamsach_DD'!E27) | D25: =IF(TRIM('03. Dulieutaichinhlamsach_DD'!$G$2)="VND",'03. Dulieutaichinhlamsach_DD'!F27/10^6,'03. Dulieutaichinhlamsach_DD'!F27) | E25: =IF($D$10<>0,D25/$D$10," ") | F25: =IF(C25<>0,(D25-C25)/C25,"") | G25: =IF(TRIM('03. Dulieutaichinhlamsach_DD'!$G$2)="VND",'03. Dulieutaichinhlamsach_DD'!G27/10^6,'03. Dulieutaichinhlamsach_DD'!G27) | H25: =IF($G$10<>0,G25/$G$10," ") | I25: =IF(TRIM('03. Dulieutaichinhlamsach_DD'!$G$2)="VND",'03. Dulieutaichinhlamsach_DD'!H27/10^6,'03. Dulieutaichinhlamsach_DD'!H27)
A26: 4. Phải thu theo tiến độ kế hoạch hợp đồng xây dựng | B26: =IF(TRIM('03. Dulieutaichinhlamsach_DD'!$G$2)="VND",'03. Dulieutaichinhlamsach_DD'!D28/10^6,'03. Dulieutaichinhlamsach_DD'!D28) | C26: =IF(TRIM('03. Dulieutaichinhlamsach_DD'!$G$2)="VND",'03. Dulieutaichinhlamsach_DD'!E28/10^6,'03. Dulieutaichinhlamsach_DD'!E28) | D26: =IF(TRIM('03. Dulieutaichinhlamsach_DD'!$G$2)="VND",'03. Dulieutaichinhlamsach_DD'!F28/10^6,'03. Dulieutaichinhlamsach_DD'!F28) | E26: =IF($D$10<>0,D26/$D$10," ") | F26: =IF(C26<>0,(D26-C26)/C26,"") | G26: =IF(TRIM('03. Dulieutaichinhlamsach_DD'!$G$2)="VND",'03. Dulieutaichinhlamsach_DD'!G28/10^6,'03. Dulieutaichinhlamsach_DD'!G28) | H26: =IF($G$10<>0,G26/$G$10," ") | I26: =IF(TRIM('03. Dulieutaichinhlamsach_DD'!$G$2)="VND",'03. Dulieutaichinhlamsach_DD'!H28/10^6,'03. Dulieutaichinhlamsach_DD'!H28)
A27: 5. Các khoản phải thu khác | B27: =IF(TRIM('03. Dulieutaichinhlamsach_DD'!$G$2)="VND",'03. Dulieutaichinhlamsach_DD'!D29/10^6,'03. Dulieutaichinhlamsach_DD'!D29) | C27: =IF(TRIM('03. Dulieutaichinhlamsach_DD'!$G$2)="VND",'03. Dulieutaichinhlamsach_DD'!E29/10^6,'03. Dulieutaichinhlamsach_DD'!E29) | D27: =IF(TRIM('03. Dulieutaichinhlamsach_DD'!$G$2)="VND",'03. Dulieutaichinhlamsach_DD'!F29/10^6,'03. Dulieutaichinhlamsach_DD'!F29) | E27: =IF($D$10<>0,D27/$D$10," ") | F27: =IF(C27<>0,(D27-C27)/C27,"") | G27: =IF(TRIM('03. Dulieutaichinhlamsach_DD'!$G$2)="VND",'03. Dulieutaichinhlamsach_DD'!G29/10^6,'03. Dulieutaichinhlamsach_DD'!G29) | H27: =IF($G$10<>0,G27/$G$10," ") | I27: =IF(TRIM('03. Dulieutaichinhlamsach_DD'!$G$2)="VND",'03. Dulieutaichinhlamsach_DD'!H29/10^6,'03. Dulieutaichinhlamsach_DD'!H29)
A28: 6. Dự phòng phải thu ngắn hạn khó đòi | B28: =IF(TRIM('03. Dulieutaichinhlamsach_DD'!$G$2)="VND",'03. Dulieutaichinhlamsach_DD'!D30/10^6,'03. Dulieutaichinhlamsach_DD'!D30) | C28: =IF(TRIM('03. Dulieutaichinhlamsach_DD'!$G$2)="VND",'03. Dulieutaichinhlamsach_DD'!E30/10^6,'03. Dulieutaichinhlamsach_DD'!E30) | D28: =IF(TRIM('03. Dulieutaichinhlamsach_DD'!$G$2)="VND",'03. Dulieutaichinhlamsach_DD'!F30/10^6,'03. Dulieutaichinhlamsach_DD'!F30) | E28: =IF($D$10<>0,D28/$D$10," ") | F28: =IF(C28<>0,(D28-C28)/C28,"") | G28: =IF(TRIM('03. Dulieutaichinhlamsach_DD'!$G$2)="VND",'03. Dulieutaichinhlamsach_DD'!G30/10^6,'03. Dulieutaichinhlamsach_DD'!G30) | H28: =IF($G$10<>0,G28/$G$10," ") | I28: =IF(TRIM('03. Dulieutaichinhlamsach_DD'!$G$2)="VND",'03. Dulieutaichinhlamsach_DD'!H30/10^6,'03. Dulieutaichinhlamsach_DD'!H30)
A29: IV. Hàng tồn kho | B29: =SUM(B30:B40) | C29: =SUM(C30:C40) | D29: =SUM(D30:D40) | E29: =IF($D$10<>0,D29/$D$10," ") | F29: =IF(C29<>0,(D29-C29)/C29,"") | G29: =SUM(G30:G40) | H29: =IF($G$10<>0,G29/$G$10," ") | I29: =SUM(I30:I40)
A30: 1. Hàng mua đang đi đường | B30: =IF(TRIM('03. Dulieutaichinhlamsach_DD'!$G$2)="VND",'03. Dulieutaichinhlamsach_DD'!D32/10^6,'03. Dulieutaichinhlamsach_DD'!D32) | C30: =IF(TRIM('03. Dulieutaichinhlamsach_DD'!$G$2)="VND",'03. Dulieutaichinhlamsach_DD'!E32/10^6,'03. Dulieutaichinhlamsach_DD'!E32) | D30: =IF(TRIM('03. Dulieutaichinhlamsach_DD'!$G$2)="VND",'03. Dulieutaichinhlamsach_DD'!F32/10^6,'03. Dulieutaichinhlamsach_DD'!F32) | E30: =IF($D$10<>0,D30/$D$10," ") | F30: =IF(C30<>0,(D30-C30)/C30,"") | G30: =IF(TRIM('03. Dulieutaichinhlamsach_DD'!$G$2)="VND",'03. Dulieutaichinhlamsach_DD'!G32/10^6,'03. Dulieutaichinhlamsach_DD'!G32) | H30: =IF($G$10<>0,G30/$G$10," ") | I30: =IF(TRIM('03. Dulieutaichinhlamsach_DD'!$G$2)="VND",'03. Dulieutaichinhlamsach_DD'!H32/10^6,'03. Dulieutaichinhlamsach_DD'!H32)
A31: 2. Nguyên liệu, vật liệu | B31: =IF(TRIM('03. Dulieutaichinhlamsach_DD'!$G$2)="VND",'03. Dulieutaichinhlamsach_DD'!D33/10^6,'03. Dulieutaichinhlamsach_DD'!D33) | C31: =IF(TRIM('03. Dulieutaichinhlamsach_DD'!$G$2)="VND",'03. Dulieutaichinhlamsach_DD'!E33/10^6,'03. Dulieutaichinhlamsach_DD'!E33) | D31: =IF(TRIM('03. Dulieutaichinhlamsach_DD'!$G$2)="VND",'03. Dulieutaichinhlamsach_DD'!F33/10^6,'03. Dulieutaichinhlamsach_DD'!F33) | E31: =IF($D$10<>0,D31/$D$10," ") | F31: =IF(C31<>0,(D31-C31)/C31,"") | G31: =IF(TRIM('03. Dulieutaichinhlamsach_DD'!$G$2)="VND",'03. Dulieutaichinhlamsach_DD'!G33/10^6,'03. Dulieutaichinhlamsach_DD'!G33) | H31: =IF($G$10<>0,G31/$G$10," ") | I31: =IF(TRIM('03. Dulieutaichinhlamsach_DD'!$G$2)="VND",'03. Dulieutaichinhlamsach_DD'!H33/10^6,'03. Dulieutaichinhlamsach_DD'!H33)
A32: 3. Công cụ, dụng cụ | B32: =IF(TRIM('03. Dulieutaichinhlamsach_DD'!$G$2)="VND",'03. Dulieutaichinhlamsach_DD'!D34/10^6,'03. Dulieutaichinhlamsach_DD'!D34) | C32: =IF(TRIM('03. Dulieutaichinhlamsach_DD'!$G$2)="VND",'03. Dulieutaichinhlamsach_DD'!E34/10^6,'03. Dulieutaichinhlamsach_DD'!E34) | D32: =IF(TRIM('03. Dulieutaichinhlamsach_DD'!$G$2)="VND",'03. Dulieutaichinhlamsach_DD'!F34/10^6,'03. Dulieutaichinhlamsach_DD'!F34) | E32: =IF($D$10<>0,D32/$D$10," ") | F32: =IF(C32<>0,(D32-C32)/C32,"") | G32: =IF(TRIM('03. Dulieutaichinhlamsach_DD'!$G$2)="VND",'03. Dulieutaichinhlamsach_DD'!G34/10^6,'03. Dulieutaichinhlamsach_DD'!G34) | H32: =IF($G$10<>0,G32/$G$10," ") | I32: =IF(TRIM('03. Dulieutaichinhlamsach_DD'!$G$2)="VND",'03. Dulieutaichinhlamsach_DD'!H34/10^6,'03. Dulieutaichinhlamsach_DD'!H34)
A33: 4. Chi phí SX, KD dở dang | B33: =IF(TRIM('03. Dulieutaichinhlamsach_DD'!$G$2)="VND",'03. Dulieutaichinhlamsach_DD'!D35/10^6,'03. Dulieutaichinhlamsach_DD'!D35) | C33: =IF(TRIM('03. Dulieutaichinhlamsach_DD'!$G$2)="VND",'03. Dulieutaichinhlamsach_DD'!E35/10^6,'03. Dulieutaichinhlamsach_DD'!E35) | D33: =IF(TRIM('03. Dulieutaichinhlamsach_DD'!$G$2)="VND",'03. Dulieutaichinhlamsach_DD'!F35/10^6,'03. Dulieutaichinhlamsach_DD'!F35) | E33: =IF($D$10<>0,D33/$D$10," ") | F33: =IF(C33<>0,(D33-C33)/C33,"") | G33: =IF(TRIM('03. Dulieutaichinhlamsach_DD'!$G$2)="VND",'03. Dulieutaichinhlamsach_DD'!G35/10^6,'03. Dulieutaichinhlamsach_DD'!G35) | H33: =IF($G$10<>0,G33/$G$10," ") | I33: =IF(TRIM('03. Dulieutaichinhlamsach_DD'!$G$2)="VND",'03. Dulieutaichinhlamsach_DD'!H35/10^6,'03. Dulieutaichinhlamsach_DD'!H35)
A34: 5. Thành phẩm | B34: =IF(TRIM('03. Dulieutaichinhlamsach_DD'!$G$2)="VND",'03. Dulieutaichinhlamsach_DD'!D36/10^6,'03. Dulieutaichinhlamsach_DD'!D36) | C34: =IF(TRIM('03. Dulieutaichinhlamsach_DD'!$G$2)="VND",'03. Dulieutaichinhlamsach_DD'!E36/10^6,'03. Dulieutaichinhlamsach_DD'!E36) | D34: =IF(TRIM('03. Dulieutaichinhlamsach_DD'!$G$2)="VND",'03. Dulieutaichinhlamsach_DD'!F36/10^6,'03. Dulieutaichinhlamsach_DD'!F36) | E34: =IF($D$10<>0,D34/$D$10," ") | F34: =IF(C34<>0,(D34-C34)/C34,"") | G34: =IF(TRIM('03. Dulieutaichinhlamsach_DD'!$G$2)="VND",'03. Dulieutaichinhlamsach_DD'!G36/10^6,'03. Dulieutaichinhlamsach_DD'!G36) | H34: =IF($G$10<>0,G34/$G$10," ") | I34: =IF(TRIM('03. Dulieutaichinhlamsach_DD'!$G$2)="VND",'03. Dulieutaichinhlamsach_DD'!H36/10^6,'03. Dulieutaichinhlamsach_DD'!H36)
A35: 6. Hàng hóa | B35: =IF(TRIM('03. Dulieutaichinhlamsach_DD'!$G$2)="VND",'03. Dulieutaichinhlamsach_DD'!D37/10^6,'03. Dulieutaichinhlamsach_DD'!D37) | C35: =IF(TRIM('03. Dulieutaichinhlamsach_DD'!$G$2)="VND",'03. Dulieutaichinhlamsach_DD'!E37/10^6,'03. Dulieutaichinhlamsach_DD'!E37) | D35: =IF(TRIM('03. Dulieutaichinhlamsach_DD'!$G$2)="VND",'03. Dulieutaichinhlamsach_DD'!F37/10^6,'03. Dulieutaichinhlamsach_DD'!F37) | E35: =IF($D$10<>0,D35/$D$10," ") | F35: =IF(C35<>0,(D35-C35)/C35,"") | G35: =IF(TRIM('03. Dulieutaichinhlamsach_DD'!$G$2)="VND",'03. Dulieutaichinhlamsach_DD'!G37/10^6,'03. Dulieutaichinhlamsach_DD'!G37) | H35: =IF($G$10<>0,G35/$G$10," ") | I35: =IF(TRIM('03. Dulieutaichinhlamsach_DD'!$G$2)="VND",'03. Dulieutaichinhlamsach_DD'!H37/10^6,'03. Dulieutaichinhlamsach_DD'!H37)
A36: 7. Hàng gửi đi bán | B36: =IF(TRIM('03. Dulieutaichinhlamsach_DD'!$G$2)="VND",'03. Dulieutaichinhlamsach_DD'!D38/10^6,'03. Dulieutaichinhlamsach_DD'!D38) | C36: =IF(TRIM('03. Dulieutaichinhlamsach_DD'!$G$2)="VND",'03. Dulieutaichinhlamsach_DD'!E38/10^6,'03. Dulieutaichinhlamsach_DD'!E38) | D36: =IF(TRIM('03. Dulieutaichinhlamsach_DD'!$G$2)="VND",'03. Dulieutaichinhlamsach_DD'!F38/10^6,'03. Dulieutaichinhlamsach_DD'!F38) | E36: =IF($D$10<>0,D36/$D$10," ") | F36: =IF(C36<>0,(D36-C36)/C36,"") | G36: =IF(TRIM('03. Dulieutaichinhlamsach_DD'!$G$2)="VND",'03. Dulieutaichinhlamsach_DD'!G38/10^6,'03. Dulieutaichinhlamsach_DD'!G38) | H36: =IF($G$10<>0,G36/$G$10," ") | I36: =IF(TRIM('03. Dulieutaichinhlamsach_DD'!$G$2)="VND",'03. Dulieutaichinhlamsach_DD'!H38/10^6,'03. Dulieutaichinhlamsach_DD'!H38)
A37: 8. Hàng hóa kho bảo thuế | B37: =IF(TRIM('03. Dulieutaichinhlamsach_DD'!$G$2)="VND",'03. Dulieutaichinhlamsach_DD'!D39/10^6,'03. Dulieutaichinhlamsach_DD'!D39) | C37: =IF(TRIM('03. Dulieutaichinhlamsach_DD'!$G$2)="VND",'03. Dulieutaichinhlamsach_DD'!E39/10^6,'03. Dulieutaichinhlamsach_DD'!E39) | D37: =IF(TRIM('03. Dulieutaichinhlamsach_DD'!$G$2)="VND",'03. Dulieutaichinhlamsach_DD'!F39/10^6,'03. Dulieutaichinhlamsach_DD'!F39) | E37: =IF($D$10<>0,D37/$D$10," ") | F37: =IF(C37<>0,(D37-C37)/C37,"") | G37: =IF(TRIM('03. Dulieutaichinhlamsach_DD'!$G$2)="VND",'03. Dulieutaichinhlamsach_DD'!G39/10^6,'03. Dulieutaichinhlamsach_DD'!G39) | H37: =IF($G$10<>0,G37/$G$10," ") | I37: =IF(TRIM('03. Dulieutaichinhlamsach_DD'!$G$2)="VND",'03. Dulieutaichinhlamsach_DD'!H39/10^6,'03. Dulieutaichinhlamsach_DD'!H39)
A38: 9. Hàng hóa bất động sản | B38: =IF(TRIM('03. Dulieutaichinhlamsach_DD'!$G$2)="VND",'03. Dulieutaichinhlamsach_DD'!D40/10^6,'03. Dulieutaichinhlamsach_DD'!D40) | C38: =IF(TRIM('03. Dulieutaichinhlamsach_DD'!$G$2)="VND",'03. Dulieutaichinhlamsach_DD'!E40/10^6,'03. Dulieutaichinhlamsach_DD'!E40) | D38: =IF(TRIM('03. Dulieutaichinhlamsach_DD'!$G$2)="VND",'03. Dulieutaichinhlamsach_DD'!F40/10^6,'03. Dulieutaichinhlamsach_DD'!F40) | E38: =IF($D$10<>0,D38/$D$10," ") | F38: =IF(C38<>0,(D38-C38)/C38,"") | G38: =IF(TRIM('03. Dulieutaichinhlamsach_DD'!$G$2)="VND",'03. Dulieutaichinhlamsach_DD'!G40/10^6,'03. Dulieutaichinhlamsach_DD'!G40) | H38: =IF($G$10<>0,G38/$G$10," ") | I38: =IF(TRIM('03. Dulieutaichinhlamsach_DD'!$G$2)="VND",'03. Dulieutaichinhlamsach_DD'!H40/10^6,'03. Dulieutaichinhlamsach_DD'!H40)
A39: 10. Dự phòng giảm giá hàng tồn kho | B39: =IF(TRIM('03. Dulieutaichinhlamsach_DD'!$G$2)="VND",'03. Dulieutaichinhlamsach_DD'!D41/10^6,'03. Dulieutaichinhlamsach_DD'!D41) | C39: =IF(TRIM('03. Dulieutaichinhlamsach_DD'!$G$2)="VND",'03. Dulieutaichinhlamsach_DD'!E41/10^6,'03. Dulieutaichinhlamsach_DD'!E41) | D39: =IF(TRIM('03. Dulieutaichinhlamsach_DD'!$G$2)="VND",'03. Dulieutaichinhlamsach_DD'!F41/10^6,'03. Dulieutaichinhlamsach_DD'!F41) | E39: =IF($D$10<>0,D39/$D$10," ") | F39: =IF(C39<>0,(D39-C39)/C39,"") | G39: =IF(TRIM('03. Dulieutaichinhlamsach_DD'!$G$2)="VND",'03. Dulieutaichinhlamsach_DD'!G41/10^6,'03. Dulieutaichinhlamsach_DD'!G41) | H39: =IF($G$10<>0,G39/$G$10," ") | I39: =IF(TRIM('03. Dulieutaichinhlamsach_DD'!$G$2)="VND",'03. Dulieutaichinhlamsach_DD'!H41/10^6,'03. Dulieutaichinhlamsach_DD'!H41)
